Workbook
Name Company_Name: Control!$B$3
Name Date: Control!$B$2
Name Days_In_Year: #REF!
Name Debt_Amount: 'Merger-Model'!$L$9
Name Debt_Date: Control!$B$2
Name Diluted_Shares: Control!$B$5
Name Enterprise_Value: Control!$B$7
Name Equity_Value: Control!$B$6
Name Hist_Year: Control!$B$8
Name Purchase_Price: 'Merger-Model'!$F$7
Name Seller_Name: Control!$B$15
Name Seller_Share_Price: Control!$B$16
Name Share_Price: Control!$B$4
Name Tax_Rate: Control!$B$11
Name Units: Control!$B$9
Name Company_Name: #REF!
Name Date: #REF!
Name Debt_Amount: #REF!
Name Debt_Date: #REF!
Name Diluted_Shares: #REF!
Name Enterprise_Value: #REF!
Name Equity_Value: #REF!
Name Hist_Year: #REF!
Name Purchase_Price: #REF!
Name Seller_Name: #REF!
Name Seller_Share_Price: #REF!
Name Share_Price: #REF!
Name Tax_Rate: #REF!
Name Units: #REF!
Name Company_Name: #REF!
Name Date: #REF!
Name Debt_Amount: #REF!
Name Debt_Date: #REF!
Name Diluted_Shares: #REF!
Name Enterprise_Value: #REF!
Name Equity_Value: #REF!
Name Hist_Year: #REF!
Name Purchase_Price: #REF!
Name Seller_Name: #REF!
Name Seller_Share_Price: #REF!
Name Share_Price: #REF!
Name Tax_Rate: #REF!
Name Units: #REF!
Name Company_Name: #REF!
Name Date: #REF!
Name Debt_Amount: #REF!
Name Debt_Date: #REF!
Name Diluted_Shares: #REF!
Name Enterprise_Value: #REF!
Name Equity_Value: #REF!
Name Hist_Year: #REF!
Name Purchase_Price: #REF!
Name Seller_Name: #REF!
Name Seller_Share_Price: #REF!
Name Share_Price: #REF!
Name Tax_Rate: #REF!
Name Units: #REF!
Name Company_Name: #REF!
Name Date: #REF!
Name Debt_Amount: #REF!

Sheet Cover Page
B2: M&A MERGER MODEL
B3: Acquisition of PT Solusi Sinergi Digital Tbk. (WIFI) by PT Sarana Menara Nusantara Tbk. (TOWR)
B5: Deal Summary
B7: Acquirer | E7: ='Merger-Model'!F33
B8: Target | E8: ='Merger-Model'!L33
B9: Offer Price / Share (IDR) | E9: ='Merger-Model'!F7
B10: Takeover Premium | E10: ='Financing_Mix'!B4
B11: Equity Purchase Price (IDR mm) | E11: ='Merger-Model'!L7
B12: Offer Enterprise Value (IDR mm) | E12: ='M&A_Valuation'!C33
B13: Consideration (Cash / Debt / Stock) | E13: =TEXT('Merger-Model'!F8,"0%")&" / "&TEXT('Merger-Model'!F9,"0%")&" / "&TEXT('Merger-Model'!F10,"0%")
B14: Total Goodwill Created (IDR mm) | E14: ='Merger-Model'!F28
B15: Synergy NPV — perpetuity (IDR mm) | E15: ='M&A_Valuation'!C35
B16: Pro Forma Net Debt / EBITDA | E16: ='Financing_Mix'!B41
B17: EPS Accretion / (Dilution) | E17: ='M&A_Valuation'!J9
B19: Contents
B20: • Deal Assumptions & Analysis
B21: • TOWR VALUATION · WIFI VALUATION (standalone DCF)
B22: • WIFI BLENDED · Football Field
B23: • Merger-Model · Synergy_Schedule · Returns Analysis
B25: Figures in IDR millions unless stated · Green = live link to model · Prepared for FFI Finals

Sheet Deal Assumptions & Analysis
A1: Merger Assumptions — TOWR (Acquirer) & WIFI (Target)
A2: PT Sarana Menara Nusantara Tbk. acquires PT Solusi Sinergi Digital Tbk. · Figures in IDR millions, shares in ’000, prices in IDR/share
A4: Transaction Inputs | F4: Financing & Synergies
A5: Acquirer Name | D5: ='Merger-Model'!F33 | F5: % Cash | H5: ='Merger-Model'!F8
A6: Target Name | D6: ='Merger-Model'!L33 | F6: % Debt | H6: ='Merger-Model'!F9
A7: Acquirer Share Price | D7: ='Merger-Model'!F34 | F7: % Stock | H7: ='Merger-Model'!F10
A8: Target Share Price | D8: ='Merger-Model'!L34 | F8: Debt Interest Rate | H8: ='Merger-Model'!L11
A9: Transaction Close Date | D9: 46387 | F9: Foregone Cash Rate | H9: ='Merger-Model'!F11
A10: Financial Reporting Units | D10: IDR mm | F10: Purchase Premium | H10: ='Financing_Mix'!B4
A11: Currency | D11: IDR
A12: Acquirer FD Shares (’000) | D12: ='Merger-Model'!F35 | F12: Synergy NPV — perpetuity | H12: ='M&A_Valuation'!C35
A13: Target FD Shares (’000) | D13: ='Merger-Model'!L35 | F13: Synergy NPV — exit multiple | H13: ='M&A_Valuation'!C36
A14: Acquirer Tax Rate | D14: ='Merger-Model'!F38 | F14: Buyer standalone EPS (IDR) | H14: ='M&A_Valuation'!J7
A15: Target Tax Rate | D15: ='Merger-Model'!L38 | F15: Pro forma combined EPS (IDR) | H15: ='M&A_Valuation'!J8
A18: Purchase Price | F18: Sources & Uses of Cash
A19: Target Share Price | D19: ='Merger-Model'!L34 | F19: Sources of Cash | K19: Uses of Cash
A20: Takeover Premium | D20: ='Financing_Mix'!B4 | F20: Cash on Hand | H20: ='Merger-Model'!L8 | K20: Cash Consideration | M20: ='Merger-Model'!L8
A21: Offer Price / Share | D21: ='Merger-Model'!F7 | F21: New Debt Issued | H21: ='Merger-Model'!L9 | K21: Debt Consideration | M21: ='Merger-Model'!L9
A22: Target FD Shares (’000) | D22: ='Merger-Model'!L35 | F22: Stock Issued | H22: ='Financing_Mix'!B28 | K22: Stock Consideration | M22: ='Financing_Mix'!B28
A23: Equity Purchase Price | D23: ='Merger-Model'!L7 | F23: Total Sources | H23: =SUM(H20:H22) | K23: Total Uses | M23: =SUM(M20:M22)
A24: Less: Target Cash | D24: =-'Merger-Shares-BS'!E16
A25: Plus: Target Debt | D25: ='Merger-Shares-BS'!E17
A26: Plus: Minority Interest | D26: ='Merger-Shares-BS'!E18
A27: Offer Enterprise Value | D27: ='M&A_Valuation'!C33
A30: Goodwill & Purchase Price Allocation | F30: Accretion / (Dilution) & Leverage
A31: Equity Purchase Price | D31: ='Merger-Model'!F19 | F31: Acquirer Standalone EPS (IDR) | H31: ='M&A_Valuation'!J7
A32: Less: Target Book Value | D32: ='Merger-Model'!F20 | F32: Pro Forma Combined EPS (IDR) | H32: ='M&A_Valuation'!J8
A33: Plus: Write-off Existing Goodwill | D33: ='Merger-Model'!F21 | F33: EPS Accretion / (Dilution) % | H33: ='M&A_Valuation'!J9
A34: Total Allocable Premium | D34: ='Merger-Model'!F22
A35: Less: Write-up of Intangibles | D35: ='Merger-Model'!F25 | F35: Pro Forma Gross Debt (IDR mm) | H35: ='Financing_Mix'!B39
A36: Less: Write-down of DTL | D36: ='Merger-Model'!F26 | F36: Pro Forma Net Debt / EBITDA | H36: ='Financing_Mix'!B41
A37: Plus: New Deferred Tax Liability | D37: ='Merger-Model'!F27 | F37: Pro Forma Share Count (’000) | H37: ='Financing_Mix'!B42
A38: Total Goodwill Created | D38: ='Merger-Model'!F28
A40: Legend: | B40: Blue = input | D40: Green = link to another sheet | H40: Black = formula

Sheet Control
A1: TOWR + WIFI merger controls
A2: Model date | B2: 2026-04-02
A3: Buyer name | B3: PT Sarana Menara Nusantara Tbk.
A4: Buyer share price (IDR) | B4: 434
A5: Buyer diluted shares (000) | B5: 58202694
A6: Buyer equity value (IDR mm) | B6: =B4*B5/1000
A7: Buyer enterprise value (IDR mm) | B7: =B6+('TOWR-3-Statements'!G80+'TOWR-3-Statements'!G87-'TOWR-3-Statements'!G59+'TOWR-3-Statements'!G98)/1000
A8: Last historical year | B8: 2025
A9: Units (share count basis) | B9: 1000
A10: Premium to seller price | B10: ='Merger-Shares-BS'!E9/'Merger-Shares-BS'!E8-1
A11: Buyer tax rate | B11: =-'TOWR-3-Statements'!G50/'TOWR-3-Statements'!G48
A12: Foregone cash interest rate | B12: 0.02
A13: Debt interest rate | B13: 0.07
A14: % of seller acquired | B14: 0.51
A15: Seller name | B15: PT Solusi Sinergi Digital Tbk.
A16: Seller share price (IDR) | B16: 2090
A17: Seller diluted shares (000) | B17: 5308549
A18: Seller equity value (IDR mm) | B18: =B16*B17/1000
A19: Seller enterprise value (IDR mm) | B19: =B18+('WIFI 3-Statement Model'!H66+'WIFI 3-Statement Model'!H71-'WIFI 3-Statement Model'!H51+'WIFI 3-Statement Model'!H78)/1000

Sheet Merger-Model
B2: ="Merger Model - "&TEXT(Company_Name,"")&" and "&Seller_Name
B3: ($ in IDR mm, except per share amounts in IDR and share counts in thousands)
B5: Transaction Assumptions
B7: Per Share Purchase Price: | F7: ='WIFI BLENDED'!D9 | H7: Equity Purchase Price: | L7: ='Merger-Shares-BS'!J15*Control!$B$14
B8: % Cash: | F8: 0 | H8: Cash Used: | L8: =F8*L7
B9: % Debt: | F9: 0.6 | H9: Debt Issued: | L9: =F9*L7
B10: % Stock: | F10: =1-F8-F9 | H10: New Shares Issued: | L10: =F10*L7/F34*Units
B11: Foregone Cash Interest Rate: | F11: =Control!$B$12 | H11: Debt Interest Rate: | L11: =Control!$B$13
H13: Revenue Synergy COGS %: | L13: 0.6
B16: Goodwill Creation & Balance Sheet Adjustments
B18: Goodwill Calculation: | H18: Fixed Asset Write-Up:
B19: Equity Purchase Price: | F19: =L7 | H19: PP&E Write-Up %: | L19: 0
B20: Less: Seller Book Value: | F20: =-'Merger-Shares-BS'!J62 | H20: PP&E Write-Up Amount: | L20: =L19*'Merger-Shares-BS'!J36
B21: Plus: Write-Off of Existing Goodwill: | F21: ='Merger-Shares-BS'!J37 | H21: Depreciation Period (Years): | L21: 8
B22: Total Allocable Purchase Premium: | F22: =F19+F20+F21
H23: Intangible Asset Write-Up:
B24: Less: Write-Up of PP&E: | F24: =-L20 | H24: Purchase Price to Allocate: | L24: =F22
B25: Less: Write-Up of Intangibles: | F25: =-L26 | H25: % Allocated to Intangibles: | L25: 0.2
B26: Less: Write-Down of DTL: | F26: =-'Merger-Shares-BS'!J52 | H26: Intangibles Write-Up Amount: | L26: =0.3*(L7-Control!$B$14*'Merger-Shares-BS'!J62)
B27: Plus: New Deferred Tax Liability: | F27: =L29 | H27: Amortization Period (Years): | L27: 15
B28: Total Goodwill Created: | F28: =0.7*(L7-Control!$B$14*'Merger-Shares-BS'!J62)
H29: New Deferred Tax Liability: | L29: 0
H30: Non-Controlling Interest (new): | L30: =(1-Control!$B$14)*'Merger-Shares-BS'!J62
B31: Buyer - Financial Profile | H31: Seller - Financial Profile
B33: Buyer Name: | F33: =Company_Name | H33: Seller Name: | L33: =Seller_Name
B34: Share Price: | F34: =Share_Price | H34: Share Price: | L34: =Seller_Share_Price
B35: Diluted Shares Outstanding: | F35: =Diluted_Shares | H35: Diluted Shares Outstanding: | L35: =Control!$B$17
B36: Diluted Equity Value: | F36: =Equity_Value | H36: Diluted Equity Value: | L36: =Control!$B$18
B37: Enterprise Value: | F37: =Enterprise_Value | H37: Enterprise Value: | L37: =Control!$B$19
B38: Tax Rate: | F38: =Control!$B$11 | H38: Tax Rate: | L38: =-'WIFI 3-Statement Model'!H43/'WIFI 3-Statement Model'!H42
B40: Buyer - Income Statement | H40: Seller - Income Statement
E42: 2025 | F42: 2026 | K42: 2025 | L42: 2026
B43: Revenue: | E43: ='TOWR-3-Statements'!G30/1000 | F43: ='TOWR-3-Statements'!H30/1000 | H43: Revenue: | K43: ='WIFI 3-Statement Model'!H28/1000 | L43: ='WIFI 3-Statement Model'!I28/1000
B44: Cost of Goods Sold: | E44: =-('TOWR-3-Statements'!G31+'TOWR-3-Statements'!G32)/1000 | F44: =-('TOWR-3-Statements'!H31+'TOWR-3-Statements'!H32)/1000 | H44: Cost of Goods Sold: | K44: =-'WIFI 3-Statement Model'!H29/1000 | L44: =-'WIFI 3-Statement Model'!I29/1000
B45: Gross Profit: | E45: =E43-E44 | F45: =F43-F44 | H45: Gross Profit: | K45: =K43-K44 | L45: =L43-L44
B47: Operating Expenses: | E47: =E45-E53-E49-E50-E51 | F47: =F45-F53-F49-F50-F51 | H47: Operating Expenses: | K47: =K45-K53-K49-K50-K51 | L47: =L45-L53-L49-L50-L51
B49: Depreciation of PP&E: | E49: =-'TOWR-3-Statements'!G31/1000 | F49: =-'TOWR-3-Statements'!H31/1000 | H49: Depreciation of PP&E: | K49: ='WIFI 3-Statement Model'!H36/1000 | L49: ='WIFI 3-Statement Model'!I36/1000
B50: Amortization of Intangibles: | E50: 0 | F50: 0 | H50: Amortization of Intangibles: | K50: 0 | L50: 0
B51: Stock-Based Compensation: | E51: 0 | F51: 0 | H51: Stock-Based Compensation: | K51: 0 | L51: 0
B53: Operating Income: | E53: ='TOWR-3-Statements'!G38/1000 | F53: ='TOWR-3-Statements'!H38/1000 | H53: Operating Income: | K53: ='WIFI 3-Statement Model'!H34/1000 | L53: ='WIFI 3-Statement Model'!I34/1000
B54: Interest Income / (Expense): | E54: =E55-E53 | F54: =F55-F53 | H54: Interest Income / (Expense): | K54: =K55-K53 | L54: =L55-L53
B55: Pre-Tax Income: | E55: ='TOWR-3-Statements'!G48/1000 | F55: ='TOWR-3-Statements'!H48/1000 | H55: Pre-Tax Income: | K55: ='WIFI 3-Statement Model'!H42/1000 | L55: ='WIFI 3-Statement Model'!I42/1000
B56: Income Tax Provision: | E56: =-'TOWR-3-Statements'!G50/1000 | F56: =-'TOWR-3-Statements'!H50/1000 | H56: Income Tax Provision: | K56: =-'WIFI 3-Statement Model'!H43/1000 | L56: =-'WIFI 3-Statement Model'!I43/1000
B58: Net Income: | E58: =E55-E56 | F58: =F55-F56 | H58: Net Income: | K58: ='WIFI 3-Statement Model'!H46/1000 | L58: ='WIFI 3-Statement Model'!I46/1000
B60: Earnings Per Share (EPS): | E60: =E58*Units/E61 | F60: =F58*Units/F61 | H60: Earnings Per Share (EPS): | K60: =K58*Units/K61 | L60: =L58*Units/L61
B61: Diluted Shares Outstanding: | E61: =Diluted_Shares | F61: =Diluted_Shares | H61: Diluted Shares Outstanding: | K61: =Control!$B$17 | L61: =Control!$B$17
B63: Combined Income Statement
E65: =E42 | F65: =F42
B66: Combined Revenue: | E66: =E43+K43 | F66: =F43+L43
B67: Revenue Synergies (bottom-up: Rev Synergy tab) | E67: ='Synergies'!$H$48 | F67: ='Synergies'!$H$48
B68: Cost of Goods Sold: | E68: =E44+K44 | F68: =F44+L44
B69: Revenue Synergy COGS: | E69: =E67-'Synergies'!$H$49 | F69: =F67-'Synergies'!$H$49
B70: Gross Profit: | E70: =E66+E67-E68-E69 | F70: =F66+F67-F68-F69
B72: Operating Expenses: | E72: =E47+K47 | F72: =F47+L47
B73: OpEx / Cost Synergies (bottom-up: Cost Synergy tab) | E73: ='Synergies'!$H$32-'Dissynergy'!$F$30*1000 | F73: ='Synergies'!$H$32-'Dissynergy'!$F$30*1000
B75: Depreciation of PP&E: | E75: =E49+K49 | F75: =F49+L49
B76: Depr. of PP&E Write-Up: | E76: =$L$20/$L$21 | F76: =$L$20/$L$21
B77: Amortization of Intangibles: | E77: =E50+K50 | F77: =F50+L50
B78: Amort. of New Intangibles: | E78: =$L$26/$L$27 | F78: =$L$26/$L$27
B79: Stock-Based Compensation: | E79: =E51+K51 | F79: =F51+L51
B81: Operating Income: | E81: =E70-E72+E73-E75-E76-E77-E78-E79 | F81: =F70-F72+F73-F75-F76-F77-F78-F79
B82: Interest Income/(Expense) incl. financing synergy | E82: =E54+K54+'Synergies'!$H$58 | F82: =F54+L54+'Synergies'!$H$58
B83: Foregone Interest on Cash: | E83: =-$L$8*$F$11 | F83: =-$L$8*$F$11
B84: Interest Paid on New Debt: | E84: =-$L$9*$L$11 | F84: =-$L$9*$L$11
B85: Pre-Tax Income: | E85: =E81+E82+E83+E84 | F85: =F81+F82+F83+F84
B86: Income Tax Provision: | E86: =E85*$F$38 | F86: =F85*$F$38
B88: Net Income: | E88: =E85-E86 | F88: =F85-F86
B89: Less: NCI (non-controlling interest): | E89: =-(1-Control!$B$14)*K58 | F89: =-(1-Control!$B$14)*L58
B90: Earnings Per Share (EPS): | E90: =(E88+E89)*Units/E91 | F90: =(F88+F89)*Units/F91
B91: Diluted Shares Outstanding: | E91: =E61+$L$10 | F91: =F61+$L$10
B93: Accretion / Dilution: | E93: =E90-E60 | F93: =F90-F60
B94: Accretion / Dilution %: | E94: =E93/E60 | F94: =F93/F60
B96: Multi-Year Accretion / Dilution (Year 1-5, full consolidation of 51% stake)
B97: (IDR mm) | E97: 2026 | F97: 2027 | G97: 2028 | H97: 2029 | I97: 2030
B98: TOWR standalone net income | E98: ='TOWR-3-Statements'!H51/1000 | F98: ='TOWR-3-Statements'!I51/1000 | G98: ='TOWR-3-Statements'!J51/1000 | H98: ='TOWR-3-Statements'!K51/1000 | I98: ='TOWR-3-Statements'!L51/1000
B99: WIFI net income (100% consolidated) | E99: ='WIFI 3-Statement Model'!I46/1000 | F99: ='WIFI 3-Statement Model'!J46/1000 | G99: ='WIFI 3-Statement Model'!K46/1000 | H99: ='WIFI 3-Statement Model'!L46/1000 | I99: ='WIFI 3-Statement Model'!M46/1000
B100: Less: NCI | E100: =-(1-Control!$B$14)*E99 | F100: =-(1-Control!$B$14)*F99 | G100: =-(1-Control!$B$14)*G99 | H100: =-(1-Control!$B$14)*H99 | I100: =-(1-Control!$B$14)*I99
B101: Plus: after-tax synergies (ramped) | E101: =Synergy_Schedule!C32 | F101: =Synergy_Schedule!D32 | G101: =Synergy_Schedule!E32 | H101: =Synergy_Schedule!F32 | I101: =Synergy_Schedule!G32
B102: Less: after-tax incremental interest | E102: =-$L$9*Control!$B$13*(1-$F$38) | F102: =-$L$9*Control!$B$13*(1-$F$38) | G102: =-$L$9*Control!$B$13*(1-$F$38) | H102: =-$L$9*Control!$B$13*(1-$F$38) | I102: =-$L$9*Control!$B$13*(1-$F$38)
B103: Less: after-tax PPA amortization | E103: =-($L$26/$L$27)*(1-$F$38) | F103: =-($L$26/$L$27)*(1-$F$38) | G103: =-($L$26/$L$27)*(1-$F$38) | H103: =-($L$26/$L$27)*(1-$F$38) | I103: =-($L$26/$L$27)*(1-$F$38)
B104: Less: after-tax integration cost | E104: =-Synergy_Schedule!C30*(1-$F$38) | F104: =-Synergy_Schedule!D30*(1-$F$38) | G104: =-Synergy_Schedule!E30*(1-$F$38) | H104: =-Synergy_Schedule!F30*(1-$F$38) | I104: =-Synergy_Schedule!G30*(1-$F$38)
B105: Pro-forma net income to parent | E105: =SUM(E98:E104) | F105: =SUM(F98:F104) | G105: =SUM(G98:G104) | H105: =SUM(H98:H104) | I105: =SUM(I98:I104)
B106: Pro-forma diluted shares (000) | E106: =Control!$B$5+$L$10 | F106: =Control!$B$5+$L$10 | G106: =Control!$B$5+$L$10 | H106: =Control!$B$5+$L$10 | I106: =Control!$B$5+$L$10
B107: Pro-forma EPS (IDR) | E107: =E105*Units/E106 | F107: =F105*Units/F106 | G107: =G105*Units/G106 | H107: =H105*Units/H106 | I107: =I105*Units/I106
B108: Standalone EPS (IDR) | E108: =E98*Units/Control!$B$5 | F108: =F98*Units/Control!$B$5 | G108: =G98*Units/Control!$B$5 | H108: =H98*Units/Control!$B$5 | I108: =I98*Units/Control!$B$5
B109: Accretion / (dilution) % | E109: =E107/E108-1 | F109: =F107/F108-1 | G109: =G107/G108-1 | H109: =H107/H108-1 | I109: =I107/I108-1

Sheet Merger-Shares-BS
B2: ="Merger Model - Seller Diluted Share Count & Combined Balance Sheets"
B3: ($ in IDR millions, except per share amounts in IDR and share counts in thousands)
B5: Diluted Share & Enterprise Value Calculations - Seller
B7: Company Name: | E7: =Seller_Name | L7: Options Calculations - Current Price:
B8: Share Price: | E8: =Seller_Share_Price
B9: Offer Price Per Share: | E9: =Purchase_Price | G9: Effective Tax Rate: | J9: ='TOWR-3-Statements'!H176*-1 | N9: Exercise
L10: Name | M10: Number | N10: Price | O10: Dilution
B11: Current Share Price: | G11: Purchase Price: | L11: Tranche A | M11: 0 | N11: 0 | O11: =IF(N11>Seller_Share_Price,0,M11-M11*N11/Seller_Share_Price)
B12: Basic Shares Outstanding: | E12: =Control!$B$17 | G12: Basic Shares Outstanding: | J12: =E12 | L12: Tranche B
B13: Basic Equity Value: | E13: =E12/Units*Seller_Share_Price | G13: Basic Equity Value: | J13: =J12/Units*E9 | L13: Total | O13: 0
B14: Diluted Shares Outstanding: | E14: =E12+O13 | G14: Diluted Shares Outstanding: | J14: =J12+O21
B15: Diluted Equity Value: | E15: =E14/Units*Seller_Share_Price | G15: Diluted Equity Value: | J15: =J14/Units*E9 | L15: Options Calculations - Purchase Price:
B16: Less: Cash & Investments | E16: ='WIFI 3-Statement Model'!H51/1000 | G16: Less: Cash & Investments | J16: =E16
B17: Plus: Debt | E17: =('WIFI 3-Statement Model'!H66+'WIFI 3-Statement Model'!H71)/1000 | G17: Plus: Debt | J17: =E17 | N17: Exercise
B18: Plus: Minority Interest | E18: ='WIFI 3-Statement Model'!H78/1000 | G18: Plus: Minority Interest | J18: =E18 | L18: Name | M18: Number | N18: Price | O18: Dilution
B19: Plus: Preferred Stock | E19: 0 | G19: Plus: Preferred Stock | J19: =E19 | L19: Tranche A | M19: 10470 | N19: 38.57 | O19: =IF(N19>E9,0,M19-M19*N19/E9)
B20: Plus: Other Liabilities | E20: 0 | G20: Plus: Other Liabilities | J20: =E20 | L20: Tranche B
B21: Enterprise Value: | E21: =E15-E16+E17+E18+E19+E20 | G21: Enterprise Value: | J21: =J15-J16+J17+J18+J19+J20 | L21: Total | O21: 0
B23: Balance Sheets - Buyer, Seller & Combined
B25: Assets: | H25: Buyer | J25: Seller | L25: Adjustments | N25: Combined
B26: Current Assets:
B27: Cash & Short-Term Securities: | H27: ='TOWR-3-Statements'!G59/1000 | J27: ='WIFI 3-Statement Model'!H51/1000 | L27: =-'Merger-Model'!L8 | N27: =H27+J27+L27
B28: Accounts Receivable: | H28: ='TOWR-3-Statements'!G60/1000 | J28: ='WIFI 3-Statement Model'!H52/1000 | L28: 0 | N28: =H28+J28+L28
B29: Inventory: | H29: ='TOWR-3-Statements'!G61/1000 | J29: ='WIFI 3-Statement Model'!H53/1000 | L29: 0 | N29: =H29+J29+L29
B30: Deferred Tax Assets: | H30: 0 | J30: 0 | L30: 0 | N30: =H30+J30+L30
B31: Other Current Assets: | H31: =('TOWR-3-Statements'!G62+'TOWR-3-Statements'!G63)/1000 | J31: =('WIFI 3-Statement Model'!H54+'WIFI 3-Statement Model'!H55)/1000 | L31: 0 | N31: =H31+J31+L31
B32: Total Current Assets: | H32: =SUM(H27:H31) | J32: =SUM(J27:J31) | L32: =SUM(L27:L31) | N32: =SUM(N27:N31)
B34: Long-Term Assets:
B35: Long-Term Securities: | H35: =('TOWR-3-Statements'!G67+'TOWR-3-Statements'!G68+'TOWR-3-Statements'!G69+'TOWR-3-Statements'!G70)/1000 | J35: =0 | L35: 0 | N35: =H35+J35+L35
B36: Plants, Property & Equipment: | H36: ='TOWR-3-Statements'!G71/1000 | J36: ='WIFI 3-Statement Model'!H58/1000 | L36: ='Merger-Model'!L20 | N36: =H36+J36+L36
B37: Goodwill: | H37: 0 | J37: 0 | L37: ='Merger-Model'!F28 | N37: =H37+J37+L37
B38: Other Intangible Assets: | H38: =('TOWR-3-Statements'!G72+'TOWR-3-Statements'!G73)/1000 | J38: =('WIFI 3-Statement Model'!H59+'WIFI 3-Statement Model'!H60)/1000 | L38: ='Merger-Model'!L26 | N38: =H38+J38+L38
B39: Other Assets: | H39: 0 | J39: 0 | L39: 0 | N39: =H39+J39+L39
B40: Total Assets: | H40: =SUM(H35:H39)+H32 | J40: =SUM(J35:J39)+J32 | L40: =SUM(L35:L39)+L32 | N40: =SUM(N35:N39)+N32
B42: Liabilities & Shareholders' Equity:
B43: Current Liabilities:
B44: Accounts Payable: | H44: ='TOWR-3-Statements'!G79/1000 | J44: ='WIFI 3-Statement Model'!H65/1000 | L44: 0 | N44: =H44+J44+L44
B45: Accrued Expenses: | H45: =('TOWR-3-Statements'!G81+'TOWR-3-Statements'!G82+'TOWR-3-Statements'!G83)/1000 | J45: =('WIFI 3-Statement Model'!H67+'WIFI 3-Statement Model'!H68)/1000 | L45: 0 | N45: =H45+J45+L45
B46: Deferred Revenue: | H46: 0 | J46: 0 | L46: 0 | N46: =H46+J46+L46
B47: Total Current Liabilities: | H47: =SUM(H44:H46) | J47: =SUM(J44:J46) | L47: =SUM(L44:L46) | N47: =SUM(N44:N46)
B49: Long-Term Liabilities:
B50: Deferred Revenue: | H50: 0 | J50: 0 | L50: 0 | N50: =H50+J50+L50
B51: Long-Term Debt: | H51: =('TOWR-3-Statements'!G80+'TOWR-3-Statements'!G87)/1000 | J51: =('WIFI 3-Statement Model'!H66+'WIFI 3-Statement Model'!H71)/1000 | L51: ='Merger-Model'!L9 | N51: =H51+J51+L51
B52: Deferred Income Tax Liability: | H52: ='TOWR-3-Statements'!G89/1000 | J52: ='WIFI 3-Statement Model'!H72/1000 | L52: ='Merger-Model'!L29 | N52: =H52+J52+L52
B53: Other Long-Term Liabilities: | H53: =('TOWR-3-Statements'!G88+'TOWR-3-Statements'!G90)/1000 | J53: =0 | L53: 0 | N53: =H53+J53+L53
B54: Total Liabilities: | H54: =SUM(H50:H53)+H47 | J54: =SUM(J50:J53)+J47 | L54: =SUM(L50:L53)+L47 | N54: =SUM(N50:N53)+N47
B56: Shareholders' Equity:
B57: Common Stock: | H57: ='TOWR-3-Statements'!G96/1000 | J57: ='WIFI 3-Statement Model'!H76/1000 | L57: =-J57 | N57: =H57+J57+L57
B58: Additional Paid-In Capital: | H58: 0 | J58: 0 | L58: =-J58+'Merger-Model'!F10*'Merger-Model'!L7 | N58: =H58+J58+L58
B59: Treasury Stock: | H59: 0 | J59: 0 | L59: =-J59 | N59: =H59+J59+L59
B60: Retained Earnings: | H60: ='TOWR-3-Statements'!G95/1000 | J60: ='WIFI 3-Statement Model'!H77/1000 | L60: =-J60 | N60: =H60+J60+L60
B61: Accumulated Other Comprehensive Income: | H61: =('TOWR-3-Statements'!G97+'TOWR-3-Statements'!G98)/1000 | J61: ='WIFI 3-Statement Model'!H78/1000 | L61: =-J61+'Merger-Model'!L30 | N61: =H61+J61+L61
B62: Total Shareholders' Equity: | H62: =SUM(H57:H61) | J62: =SUM(J57:J61) | L62: =SUM(L57:L61) | N62: =SUM(N57:N61)
B64: Total Liabilities & SE: | H64: =H62+H54 | J64: =J62+J54 | L64: =L62+L54 | N64: =N62+N54

Sheet Synergy_Schedule
B2: TOWR + WIFI synergy schedule
B3: IDR mm unless stated otherwise
B5: Assumptions / drivers
B6: Tax rate | C6: =Control!$B$11
B7: Discount rate / WACC | C7: 0.09
B8: Terminal growth rate | C8: 0.03
B9: Exit EBITDA multiple | C9: 8.5
B10: Revenue synergy % (LEGACY — superseded by bottom-up) | C10: ='Merger-Model'!F13
B11: Revenue synergy COGS % | C11: ='Merger-Model'!$L$13
B12: Cost synergy % (LEGACY — superseded by bottom-up) | C12: ='Merger-Model'!$F$14
B13: Integration cost as % of annual cost synergies | C13: 0.5
B15: Recurring synergy schedule
B16: Fiscal year | C16: ='WIFI 3-Statement Model'!I2 | D16: ='WIFI 3-Statement Model'!J2 | E16: ='WIFI 3-Statement Model'!K2 | F16: ='WIFI 3-Statement Model'!L2 | G16: ='WIFI 3-Statement Model'!M2
B17: Synergy ramp | C17: 0.5 | D17: 0.75 | E17: 1 | F17: 1 | G17: 1
B19: Seller revenue | C19: =IFERROR('WIFI 3-Statement Model'!I28/1000,0) | D19: =IFERROR('WIFI 3-Statement Model'!J28/1000,0) | E19: =IFERROR('WIFI 3-Statement Model'!K28/1000,0) | F19: =IFERROR('WIFI 3-Statement Model'!L28/1000,0) | G19: =IFERROR('WIFI 3-Statement Model'!M28/1000,0)
B20: Seller gross profit | C20: =IFERROR('WIFI 3-Statement Model'!I30/1000,0) | D20: =IFERROR('WIFI 3-Statement Model'!J30/1000,0) | E20: =IFERROR('WIFI 3-Statement Model'!K30/1000,0) | F20: =IFERROR('WIFI 3-Statement Model'!L30/1000,0) | G20: =IFERROR('WIFI 3-Statement Model'!M30/1000,0)
B21: Seller operating income | C21: =IFERROR('WIFI 3-Statement Model'!I34/1000,0) | D21: =IFERROR('WIFI 3-Statement Model'!J34/1000,0) | E21: =IFERROR('WIFI 3-Statement Model'!K34/1000,0) | F21: =IFERROR('WIFI 3-Statement Model'!L34/1000,0) | G21: =IFERROR('WIFI 3-Statement Model'!M34/1000,0)
B22: Seller depreciation | C22: =IFERROR('WIFI 3-Statement Model'!I36/1000,0) | D22: =IFERROR('WIFI 3-Statement Model'!J36/1000,0) | E22: =IFERROR('WIFI 3-Statement Model'!K36/1000,0) | F22: =IFERROR('WIFI 3-Statement Model'!L36/1000,0) | G22: =IFERROR('WIFI 3-Statement Model'!M36/1000,0)
B23: Seller OpEx excl. D&A | C23: =IFERROR(-('WIFI 3-Statement Model'!I32+'WIFI 3-Statement Model'!I33)/1000,0) | D23: =IFERROR(-('WIFI 3-Statement Model'!J32+'WIFI 3-Statement Model'!J33)/1000,0) | E23: =IFERROR(-('WIFI 3-Statement Model'!K32+'WIFI 3-Statement Model'!K33)/1000,0) | F23: =IFERROR(-('WIFI 3-Statement Model'!L32+'WIFI 3-Statement Model'!L33)/1000,0) | G23: =IFERROR(-('WIFI 3-Statement Model'!M32+'WIFI 3-Statement Model'!M33)/1000,0)
B25: Revenue synergies (gross) — from 'Rev Synergy Bottom-Up' | C25: ='Synergies'!$H$48*C17 | D25: ='Synergies'!$H$48*D17 | E25: ='Synergies'!$H$48*E17 | F25: ='Synergies'!$H$48*F17 | G25: ='Synergies'!$H$48*G17
B26: Less: variable cost / COGS (implied by bottom-up EBIT) | C26: =C25-'Synergies'!$H$49*C17 | D26: =D25-'Synergies'!$H$49*D17 | E26: =E25-'Synergies'!$H$49*E17 | F26: =F25-'Synergies'!$H$49*F17 | G26: =G25-'Synergies'!$H$49*G17
B27: Revenue synergies (EBIT) | C27: =C25-C26 | D27: =D25-D26 | E27: =E25-E26 | F27: =F25-F26 | G27: =G25-G26
B28: Cost synergies — from 'Cost Synergy Bottom-Up' | C28: ='Synergies'!$H$32*C17 | D28: ='Synergies'!$H$32*D17 | E28: ='Synergies'!$H$32*E17 | F28: ='Synergies'!$H$32*F17 | G28: ='Synergies'!$H$32*G17
B29: Recurring pre-tax synergies NET of dissynergies (D3 transitional: yr1–3 only) | C29: =C27+C28+'Synergies'!$H$58*C17-'Dissynergy'!$F$30*1000 | D29: =D27+D28+'Synergies'!$H$58*D17-'Dissynergy'!$F$30*1000 | E29: =E27+E28+'Synergies'!$H$58*E17-'Dissynergy'!$F$30*1000 | F29: =F27+F28+'Synergies'!$H$58*F17-'Dissynergy'!$F$29*1000 | G29: =G27+G28+'Synergies'!$H$58*G17-'Dissynergy'!$F$29*1000
B30: Integration costs (one-time) | C30: =C28*$C$13*(1-C17+0.25) | D30: =D28*$C$13*(1-D17+0.25) | E30: =E28*$C$13*(1-E17+0.25) | F30: =F28*$C$13*(1-F17+0.25) | G30: =G28*$C$13*(1-G17+0.25)
B31: Pre-tax net synergies | C31: =C29-C30 | D31: =D29-D30 | E31: =E29-E30 | F31: =F29-F30 | G31: =G29-G30
B32: After-tax recurring synergies | C32: =C29*(1-$C$6) | D32: =D29*(1-$C$6) | E32: =E29*(1-$C$6) | F32: =F29*(1-$C$6) | G32: =G29*(1-$C$6)
B33: After-tax net synergies | C33: =C31*(1-$C$6) | D33: =D31*(1-$C$6) | E33: =E31*(1-$C$6) | F33: =F31*(1-$C$6) | G33: =G31*(1-$C$6)
B34: Discount factor | C34: =IFERROR(1/(1+$C$7)^(1),0) | D34: =IFERROR(1/(1+$C$7)^(2),0) | E34: =IFERROR(1/(1+$C$7)^(3),0) | F34: =IFERROR(1/(1+$C$7)^(4),0) | G34: =IFERROR(1/(1+$C$7)^(5),0)
B35: PV of recurring synergies | C35: =C32*C34 | D35: =D32*D34 | E35: =E32*E34 | F35: =F32*F34 | G35: =G32*G34
B36: PV of net synergies | C36: =C33*C34 | D36: =D33*D34 | E36: =E33*E34 | F36: =F33*F34 | G36: =G33*G34
B37: of which: Financing synergy (pre-tax, incl. above) | C37: ='Synergies'!$H$58*C17 | D37: ='Synergies'!$H$58*D17 | E37: ='Synergies'!$H$58*E17 | F37: ='Synergies'!$H$58*F17 | G37: ='Synergies'!$H$58*G17
B38: Synergy terminal value
B40: Terminal value - perpetuity | C40: =IFERROR(G32*(1+$C$8)/($C$7-$C$8),0)
B41: PV of terminal value | C41: =C40*G34
B42: Terminal value - exit multiple | C42: =(G27+G28)*$C$9
B43: PV of exit multiple terminal value | C43: =C42*G34
B44: Synergy NPV (perpetuity) | C44: =SUM(C35:G35)+C41-SUMPRODUCT(C30:G30*(1-$C$6),C34:G34)
B45: Synergy NPV (exit multiple) | C45: =SUM(C35:G35)+C43-SUMPRODUCT(C30:G30*(1-$C$6),C34:G34)
B46: Cost synergy now bottom-up in 'Cost Synergy Bottom-Up'; financing synergy added as a new component from 'Fin Synergy Bottom-Up' (interest saving, in row 29 & 37). Exit-multiple TV intentionally excludes financing.
A48: COST SYNERGY BREAKDOWN BY CATEGORY (annual run-rate, Rp bn)
A49: Category | B49: Driver / basis | C49: Run-rate
A50: 1. Tenancy / co-location uplift | B50: 5,000 FWA sites x Rp3mn/site/mo net x 12 | C50: =5000*3*12/1000
A51: 2. SG&A consolidation | B51: 7% of combined SG&A | C51: =0.07*(-'TOWR-3-Statements'!G36-'WIFI 3-Statement Model'!I32)/1000000
A52: 3. Financing cost reduction | B52: 1.5% spread x WIFI debt refinanced | C52: =0.015*('WIFI 3-Statement Model'!H66+'WIFI 3-Statement Model'!H71)/1000000
A53: 4. Procurement & backbone integration | B53: combined purchasing + fiber backbone | C53: 30
A54: Total cost-synergy run-rate | C54: =SUM(C50:C53)
A55: Realization ramp: 25% / 60% / 85% / 100% (Yr1-4)

Sheet M&A_Valuation
B2: TOWR + WIFI valuation bridge
B3: standalone DCF (linked to WIFI VALUATION) + synergy NPV + offer bridge
B5: Target standalone DCF | I5: Pro forma accretion / dilution
B6: Target tax rate | C6: =-'WIFI 3-Statement Model'!H43/'WIFI 3-Statement Model'!H42
B7: Target WACC | C7: =Synergy_Schedule!C7 | I7: Buyer standalone EPS | J7: ='Merger-Model'!F60
B8: Terminal growth | C8: =Synergy_Schedule!C8 | I8: Pro forma combined EPS | J8: ='Merger-Model'!F90
I9: Accretion / dilution % | J9: ='Merger-Model'!F94
C10: ='WIFI 3-Statement Model'!I2 | D10: ='WIFI 3-Statement Model'!J2 | E10: ='WIFI 3-Statement Model'!K2 | F10: ='WIFI 3-Statement Model'!L2 | G10: ='WIFI 3-Statement Model'!M2 | I10: Cash funding % | J10: ='Merger-Model'!F8
B11: Revenue | C11: =IFERROR('WIFI 3-Statement Model'!I28/1000,0) | D11: =IFERROR('WIFI 3-Statement Model'!J28/1000,0) | E11: =IFERROR('WIFI 3-Statement Model'!K28/1000,0) | F11: =IFERROR('WIFI 3-Statement Model'!L28/1000,0) | G11: =IFERROR('WIFI 3-Statement Model'!M28/1000,0) | I11: Stock funding % | J11: ='Merger-Model'!F10
B12: EBIT | C12: =IFERROR('WIFI 3-Statement Model'!I34/1000,0) | D12: =IFERROR('WIFI 3-Statement Model'!J34/1000,0) | E12: =IFERROR('WIFI 3-Statement Model'!K34/1000,0) | F12: =IFERROR('WIFI 3-Statement Model'!L34/1000,0) | G12: =IFERROR('WIFI 3-Statement Model'!M34/1000,0)
B13: Tax on EBIT | C13: =C12*$C$6 | D13: =D12*$C$6 | E13: =E12*$C$6 | F13: =F12*$C$6 | G13: =G12*$C$6
B14: NOPAT | C14: =C12-C13 | D14: =D12-D13 | E14: =E12-E13 | F14: =F12-F13 | G14: =G12-G13
B15: Depreciation & amortization | C15: =IFERROR('WIFI 3-Statement Model'!I36/1000,0) | D15: =IFERROR('WIFI 3-Statement Model'!J36/1000,0) | E15: =IFERROR('WIFI 3-Statement Model'!K36/1000,0) | F15: =IFERROR('WIFI 3-Statement Model'!L36/1000,0) | G15: =IFERROR('WIFI 3-Statement Model'!M36/1000,0)
B16: Capex | C16: =IFERROR('WIFI 3-Statement Model'!I113/1000,0) | D16: =IFERROR('WIFI 3-Statement Model'!J113/1000,0) | E16: =IFERROR('WIFI 3-Statement Model'!K113/1000,0) | F16: =IFERROR('WIFI 3-Statement Model'!L113/1000,0) | G16: =IFERROR('WIFI 3-Statement Model'!M113/1000,0)
B17: Change in NWC (fixed: WIFI r120, source/(use)) | C17: =-IFERROR('WIFI 3-Statement Model'!I120/1000,0) | D17: =-IFERROR('WIFI 3-Statement Model'!J120/1000,0) | E17: =-IFERROR('WIFI 3-Statement Model'!K120/1000,0) | F17: =-IFERROR('WIFI 3-Statement Model'!L120/1000,0) | G17: =-IFERROR('WIFI 3-Statement Model'!M120/1000,0)
B18: Unlevered FCF | C18: =C14+C15-C16-C17 | D18: =D14+D15-D16-D17 | E18: =E14+E15-E16-E17 | F18: =F14+F15-F16-F17 | G18: =G14+G15-G16-G17
B19: Discount factor | C19: =IFERROR(1/(1+$C$7)^(1),0) | D19: =IFERROR(1/(1+$C$7)^(2),0) | E19: =IFERROR(1/(1+$C$7)^(3),0) | F19: =IFERROR(1/(1+$C$7)^(4),0) | G19: =IFERROR(1/(1+$C$7)^(5),0)
B20: PV of FCF | C20: =C18*C19 | D20: =D18*D19 | E20: =E18*E19 | F20: =F18*F19 | G20: =G18*G19
B22: Terminal value (reference only - not used; see C24) | C22: =IFERROR(G18*(1+$C$8)/($C$7-$C$8),0)
B23: PV of terminal (reference only) | C23: =C22*G19
B24: Standalone target EV (from WIFI VALUATION, calibrated DCF) | C24: ='WIFI VALUATION'!H22/1000
B25: Less: target cash | C25: ='Merger-Shares-BS'!E16
B26: Plus: target debt | C26: ='Merger-Shares-BS'!E17
B27: Plus: minority interest | C27: ='WIFI VALUATION'!H24/1000
B28: Standalone target equity value | C28: =C24+C25-C26-C27
B29: Implied standalone value / share (IDR) | C29: =IFERROR(C28*1000/Control!$B$17,0)
B31: Offer price / share (IDR) | C31: =Purchase_Price
B32: Offer equity value | C32: ='Merger-Model'!$L$7
B33: Offer enterprise value | C33: =C32+Control!$B$19-Control!$B$18
B35: Synergy NPV (perpetuity) | C35: =Synergy_Schedule!$C$44
B36: Synergy NPV (exit multiple) | C36: =Synergy_Schedule!$C$45
B37: Buyer affordable EV incl. synergies (perpetuity) | C37: =C24+C35
B38: Buyer affordable EV incl. synergies (exit multiple) | C38: =C24+C36
B39: Offer EV premium vs standalone DCF | C39: =IFERROR(C33/C24-1,0)
B40: Offer EV discount/(premium) vs synergy-backed EV | C40: =IFERROR(C33/C37-1,0)

Sheet OJK Compliance
B2: OJK Regulatory Checklist — Acquisition of a Listed Company
B3: TOWR acquiring 51% of WIFI (Tbk) → change of control. Verified against OJK regulations (see sources).
B5: Regulation / trigger | C5: What it requires | D5: Impact on this deal
B6: POJK 9/POJK.04/2018 — Pengambilalihan (Takeover) | C6: Buying >50% voting shares OR gaining control = becoming 'Pengendali' (Art 1(4)). Acquiring 51% triggers a MANDATORY TENDER OFFER (Penawaran Tender Wajib) to all remaining public shareholders. | D6: TRIGGERED. TOWR must launch an MTO for the ~49% public float.
B7: MTO price floor (POJK 9/2018, Art 17) | C7: For listed & liquid shares, MTO price ≥ the HIGHER of: (a) the acquisition price paid for control, or (b) the average of the highest daily prices over the 90 days before announcement. | D7: Offer @35% = Rp2.822 > 90-day high (~Rp2.530), so the acquisition price sets the floor. TOWR must pay Rp2.822 to ALL tendering public holders — a higher premium raises total cash sharply.
B8: MTO timeline (POJK 9/2018, Art 7/14/16) | C8: Announce in a newspaper + file with OJK (Art 7); 30-day offer period (Art 14); settle within 12 days; report results to OJK within 5 days (Art 16). | D8: Plan announcement + 30-day tender window into the deal timetable.
B9: Refloat requirement (POJK 9/2018, Art 21) | C9: If after the MTO the controller holds >80% of capital, it must divest so the public again holds ≥20%, within a maximum of 2 years. | D9: If take-up is high, TOWR may need to sell down to keep ≥20% public float within 2 years.
B10: POJK 17/POJK.04/2020 — Transaksi Material | C10: Transaction value ≥20% of equity → public disclosure + independent appraiser (KJPP) report. >50% → also independent-shareholder RUPS approval. | D10: The WIFI stake is material for TOWR → disclosure + KJPP fairness opinion required (RUPS if it crosses 50% of TOWR equity).
B11: POJK 42/POJK.04/2020 — Transaksi Afiliasi / Benturan Kepentingan | C11: If buyer & target are affiliated or a conflict of interest exists: independent appraiser fairness opinion + disclosure + independent-shareholder approval. Exempt if <0.5% of paid-up capital or <Rp5bn. | D11: Check TOWR–WIFI affiliation (common controllers). If affiliated → independent RUPS + KJPP fairness opinion needed.
B12: Independent appraiser (KJPP) | C12: A registered valuer must issue a valuation & fairness opinion supporting the offer price for MTO / material / affiliated transactions. | D12: This football field + valuation supports the fairness opinion; a licensed KJPP must formally sign off.
B14: Key takeaway for offer price: because the MTO floor = the control-acquisition price extended to the full 49% public float, every extra point of premium is paid on ~100% of shares, not just the 51% block. This is a strong reason to keep the premium disciplined (≈35%) rather than pushing toward the blended ceiling (~73%).
B17: Sources
B18: • POJK No. 9/POJK.04/2018 — Pengambilalihan Perusahaan Terbuka (ojk.go.id, full text PDF)
B19: • POJK No. 17/POJK.04/2020 — Transaksi Material dan Perubahan Kegiatan Usaha
B20: • POJK No. 42/POJK.04/2020 — Transaksi Afiliasi dan Transaksi Benturan Kepentingan

Sheet Football Field
B2: WIFI (Surge) — Valuation Football Field vs Offer Price
B3: Implied value per WIFI share (IDR). Low–Base = coklat muda · Base–High = coklat tua. Ties to the recommended 35% offer / MTO floor.
B5: Valuation method | C5: Low | D5: Base | E5: High | F5: Base vs market | G5: Source / note
B6: 52-week trading range | C6: 1365 | D6: 2090 | E6: 4250 | F6: =D6/2090-1 | G6: WIFI BETA daily price, last 52 weeks
B7: Relative — P/E peers | C7: 1320 | D7: 1782 | E7: 2353 | F7: =D7/2090-1 | G7: Comparable sheet: Worst/Base/Best (G53:G55)
B8: Relative — EV/EBITDA peers | C8: 1940 | D8: 2795 | E8: 4785 | F8: =D8/2090-1 | G8: Comparable sheet: Worst/Base/Best (E53:E55)
B9: Relative — P/BV peers | C9: 2028 | D9: 2475 | E9: 4675 | F9: =D9/2090-1 | G9: Comparable sheet: Worst/Base/Best (F53:F55)
B10: Sum-of-the-Parts (SOTP) | C10: 3082 | D10: 3424 | E10: 3767 | F10: =D10/2090-1 | G10: WIFI SOTP base Rp3,424 ± ~10% band
B11: DCF (WACC 9–11%) | C11: 3299 | D11: 3666 | E11: 4106 | F11: =D11/2090-1 | G11: WIFI VALUATION base Rp3,666; WACC sensitivity band
B12: Blended target | C12: 3295 | D12: 3619 | E12: 3666 | F12: =D12/2090-1 | G12: WIFI BLENDED: simple avg / weighted / top method
B13: Precedent (Indo→intl fiber) | C13: 2900 | D13: 4847 | E13: 6794 | F13: =D13/2090-1 | G13: OUTLIER, 10% weight — intl EV/homepass (Verizon/AT&T). Verify.
B15: Offer-price references
B16: Reference | C16: Rp/share | D16: Premium vs market
B17: Market price (21 Aug) | C17: 2090 | D17: =C17/2090-1
B18: Recommended offer @35% = MTO floor | C18: 2822 | D18: =C18/2090-1
B19: Blended fair value (ceiling) | C19: 3619 | D19: =C19/2090-1
B21: Reading: at 35% premium (Rp2.822) the offer sits ABOVE market and the relative-multiple base cases (P/E, EV/EBITDA, P/BV) but BELOW the intrinsic methods (SOTP, DCF, blended Rp3.619) — a real premium to holders with a margin of safety for TOWR. Under POJK 9/2018 this offer price also becomes the Mandatory Tender Offer floor extended to ALL public shareholders (see OJK Compliance tab).

Sheet Sensitivities
B2: TOWR + WIFI accretion / dilution sensitivities
B3: formula-based tables; no fragile Excel data tables
B5: Base buyer pre-tax income | C5: =IFERROR('TOWR-3-Statements'!G48/1000,0)
B6: Base seller pre-tax income | C6: =IFERROR('WIFI 3-Statement Model'!H42/1000,0)
B7: Buyer tax rate | C7: =Control!$B$11
B8: Buyer shares (000) | C8: =Control!$B$5
B9: Seller shares (000) | C9: =Control!$B$17
B10: Buyer share price | C10: =Control!$B$4
B11: Cash funding % | C11: ='Merger-Model'!$F$8
B12: Debt funding % | C12: ='Merger-Model'!$F$9
B13: Stock funding % | C13: ='Merger-Model'!$F$10
B14: Foregone cash rate | C14: =Control!$B$12
B15: Debt rate | C15: =Control!$B$13
B16: Seller 2026 revenue | C16: =IFERROR('WIFI 3-Statement Model'!I28/1000,0)
B17: Seller 2026 OpEx ex D&A | C17: =IFERROR(-('WIFI 3-Statement Model'!I32+'WIFI 3-Statement Model'!I33)/1000,0)
B18: Blended rev-synergy margin (data-linked) | C18: ='Synergies'!J45/'Synergies'!H45 | D18: EBIT ÷ gross rev (margin segmen aktual — ganti 60% legacy)
B20: 2026 EPS accretion / dilution: purchase premium vs cost synergies
B22: Cost synergy % | D22: 0.1 | E22: 0.2 | F22: 0.3 | G22: 0.4 | H22: 0.5
B23: 0 | D23: =IFERROR((((((($C$5+$C$6+($C$17*$B23))*(1-$C$7)-((Control!$B$16*(1+D$22)*Control!$B$17/1000)*$C$11*$C$14)-((Control!$B$16*(1+D$22)*Control!$B$17/1000)*$C$12*$C$15))/($C$8+((Control!$B$16*(1+D$22)*Control!$B$17/1000)*$C$13/Control!$B$4*1000)))*1000)-'Merger-Model'!F60)/'Merger-Model'!F60),0) | E23: =IFERROR((((((($C$5+$C$6+($C$17*$B23))*(1-$C$7)-((Control!$B$16*(1+E$22)*Control!$B$17/1000)*$C$11*$C$14)-((Control!$B$16*(1+E$22)*Control!$B$17/1000)*$C$12*$C$15))/($C$8+((Control!$B$16*(1+E$22)*Control!$B$17/1000)*$C$13/Control!$B$4*1000)))*1000)-'Merger-Model'!F60)/'Merger-Model'!F60),0) | F23: =IFERROR((((((($C$5+$C$6+($C$17*$B23))*(1-$C$7)-((Control!$B$16*(1+F$22)*Control!$B$17/1000)*$C$11*$C$14)-((Control!$B$16*(1+F$22)*Control!$B$17/1000)*$C$12*$C$15))/($C$8+((Control!$B$16*(1+F$22)*Control!$B$17/1000)*$C$13/Control!$B$4*1000)))*1000)-'Merger-Model'!F60)/'Merger-Model'!F60),0) | G23: =IFERROR((((((($C$5+$C$6+($C$17*$B23))*(1-$C$7)-((Control!$B$16*(1+G$22)*Control!$B$17/1000)*$C$11*$C$14)-((Control!$B$16*(1+G$22)*Control!$B$17/1000)*$C$12*$C$15))/($C$8+((Control!$B$16*(1+G$22)*Control!$B$17/1000)*$C$13/Control!$B$4*1000)))*1000)-'Merger-Model'!F60)/'Merger-Model'!F60),0) | H23: =IFERROR((((((($C$5+$C$6+($C$17*$B23))*(1-$C$7)-((Control!$B$16*(1+H$22)*Control!$B$17/1000)*$C$11*$C$14)-((Control!$B$16*(1+H$22)*Control!$B$17/1000)*$C$12*$C$15))/($C$8+((Control!$B$16*(1+H$22)*Control!$B$17/1000)*$C$13/Control!$B$4*1000)))*1000)-'Merger-Model'!F60)/'Merger-Model'!F60),0)
B24: 0.025 | D24: =IFERROR((((((($C$5+$C$6+($C$17*$B24))*(1-$C$7)-((Control!$B$16*(1+D$22)*Control!$B$17/1000)*$C$11*$C$14)-((Control!$B$16*(1+D$22)*Control!$B$17/1000)*$C$12*$C$15))/($C$8+((Control!$B$16*(1+D$22)*Control!$B$17/1000)*$C$13/Control!$B$4*1000)))*1000)-'Merger-Model'!F60)/'Merger-Model'!F60),0) | E24: =IFERROR((((((($C$5+$C$6+($C$17*$B24))*(1-$C$7)-((Control!$B$16*(1+E$22)*Control!$B$17/1000)*$C$11*$C$14)-((Control!$B$16*(1+E$22)*Control!$B$17/1000)*$C$12*$C$15))/($C$8+((Control!$B$16*(1+E$22)*Control!$B$17/1000)*$C$13/Control!$B$4*1000)))*1000)-'Merger-Model'!F60)/'Merger-Model'!F60),0) | F24: =IFERROR((((((($C$5+$C$6+($C$17*$B24))*(1-$C$7)-((Control!$B$16*(1+F$22)*Control!$B$17/1000)*$C$11*$C$14)-((Control!$B$16*(1+F$22)*Control!$B$17/1000)*$C$12*$C$15))/($C$8+((Control!$B$16*(1+F$22)*Control!$B$17/1000)*$C$13/Control!$B$4*1000)))*1000)-'Merger-Model'!F60)/'Merger-Model'!F60),0) | G24: =IFERROR((((((($C$5+$C$6+($C$17*$B24))*(1-$C$7)-((Control!$B$16*(1+G$22)*Control!$B$17/1000)*$C$11*$C$14)-((Control!$B$16*(1+G$22)*Control!$B$17/1000)*$C$12*$C$15))/($C$8+((Control!$B$16*(1+G$22)*Control!$B$17/1000)*$C$13/Control!$B$4*1000)))*1000)-'Merger-Model'!F60)/'Merger-Model'!F60),0) | H24: =IFERROR((((((($C$5+$C$6+($C$17*$B24))*(1-$C$7)-((Control!$B$16*(1+H$22)*Control!$B$17/1000)*$C$11*$C$14)-((Control!$B$16*(1+H$22)*Control!$B$17/1000)*$C$12*$C$15))/($C$8+((Control!$B$16*(1+H$22)*Control!$B$17/1000)*$C$13/Control!$B$4*1000)))*1000)-'Merger-Model'!F60)/'Merger-Model'!F60),0)
B25: 0.05 | D25: =IFERROR((((((($C$5+$C$6+($C$17*$B25))*(1-$C$7)-((Control!$B$16*(1+D$22)*Control!$B$17/1000)*$C$11*$C$14)-((Control!$B$16*(1+D$22)*Control!$B$17/1000)*$C$12*$C$15))/($C$8+((Control!$B$16*(1+D$22)*Control!$B$17/1000)*$C$13/Control!$B$4*1000)))*1000)-'Merger-Model'!F60)/'Merger-Model'!F60),0) | E25: =IFERROR((((((($C$5+$C$6+($C$17*$B25))*(1-$C$7)-((Control!$B$16*(1+E$22)*Control!$B$17/1000)*$C$11*$C$14)-((Control!$B$16*(1+E$22)*Control!$B$17/1000)*$C$12*$C$15))/($C$8+((Control!$B$16*(1+E$22)*Control!$B$17/1000)*$C$13/Control!$B$4*1000)))*1000)-'Merger-Model'!F60)/'Merger-Model'!F60),0) | F25: =IFERROR((((((($C$5+$C$6+($C$17*$B25))*(1-$C$7)-((Control!$B$16*(1+F$22)*Control!$B$17/1000)*$C$11*$C$14)-((Control!$B$16*(1+F$22)*Control!$B$17/1000)*$C$12*$C$15))/($C$8+((Control!$B$16*(1+F$22)*Control!$B$17/1000)*$C$13/Control!$B$4*1000)))*1000)-'Merger-Model'!F60)/'Merger-Model'!F60),0) | G25: =IFERROR((((((($C$5+$C$6+($C$17*$B25))*(1-$C$7)-((Control!$B$16*(1+G$22)*Control!$B$17/1000)*$C$11*$C$14)-((Control!$B$16*(1+G$22)*Control!$B$17/1000)*$C$12*$C$15))/($C$8+((Control!$B$16*(1+G$22)*Control!$B$17/1000)*$C$13/Control!$B$4*1000)))*1000)-'Merger-Model'!F60)/'Merger-Model'!F60),0) | H25: =IFERROR((((((($C$5+$C$6+($C$17*$B25))*(1-$C$7)-((Control!$B$16*(1+H$22)*Control!$B$17/1000)*$C$11*$C$14)-((Control!$B$16*(1+H$22)*Control!$B$17/1000)*$C$12*$C$15))/($C$8+((Control!$B$16*(1+H$22)*Control!$B$17/1000)*$C$13/Control!$B$4*1000)))*1000)-'Merger-Model'!F60)/'Merger-Model'!F60),0)
B26: 0.075 | D26: =IFERROR((((((($C$5+$C$6+($C$17*$B26))*(1-$C$7)-((Control!$B$16*(1+D$22)*Control!$B$17/1000)*$C$11*$C$14)-((Control!$B$16*(1+D$22)*Control!$B$17/1000)*$C$12*$C$15))/($C$8+((Control!$B$16*(1+D$22)*Control!$B$17/1000)*$C$13/Control!$B$4*1000)))*1000)-'Merger-Model'!F60)/'Merger-Model'!F60),0) | E26: =IFERROR((((((($C$5+$C$6+($C$17*$B26))*(1-$C$7)-((Control!$B$16*(1+E$22)*Control!$B$17/1000)*$C$11*$C$14)-((Control!$B$16*(1+E$22)*Control!$B$17/1000)*$C$12*$C$15))/($C$8+((Control!$B$16*(1+E$22)*Control!$B$17/1000)*$C$13/Control!$B$4*1000)))*1000)-'Merger-Model'!F60)/'Merger-Model'!F60),0) | F26: =IFERROR((((((($C$5+$C$6+($C$17*$B26))*(1-$C$7)-((Control!$B$16*(1+F$22)*Control!$B$17/1000)*$C$11*$C$14)-((Control!$B$16*(1+F$22)*Control!$B$17/1000)*$C$12*$C$15))/($C$8+((Control!$B$16*(1+F$22)*Control!$B$17/1000)*$C$13/Control!$B$4*1000)))*1000)-'Merger-Model'!F60)/'Merger-Model'!F60),0) | G26: =IFERROR((((((($C$5+$C$6+($C$17*$B26))*(1-$C$7)-((Control!$B$16*(1+G$22)*Control!$B$17/1000)*$C$11*$C$14)-((Control!$B$16*(1+G$22)*Control!$B$17/1000)*$C$12*$C$15))/($C$8+((Control!$B$16*(1+G$22)*Control!$B$17/1000)*$C$13/Control!$B$4*1000)))*1000)-'Merger-Model'!F60)/'Merger-Model'!F60),0) | H26: =IFERROR((((((($C$5+$C$6+($C$17*$B26))*(1-$C$7)-((Control!$B$16*(1+H$22)*Control!$B$17/1000)*$C$11*$C$14)-((Control!$B$16*(1+H$22)*Control!$B$17/1000)*$C$12*$C$15))/($C$8+((Control!$B$16*(1+H$22)*Control!$B$17/1000)*$C$13/Control!$B$4*1000)))*1000)-'Merger-Model'!F60)/'Merger-Model'!F60),0)
B27: 0.1 | D27: =IFERROR((((((($C$5+$C$6+($C$17*$B27))*(1-$C$7)-((Control!$B$16*(1+D$22)*Control!$B$17/1000)*$C$11*$C$14)-((Control!$B$16*(1+D$22)*Control!$B$17/1000)*$C$12*$C$15))/($C$8+((Control!$B$16*(1+D$22)*Control!$B$17/1000)*$C$13/Control!$B$4*1000)))*1000)-'Merger-Model'!F60)/'Merger-Model'!F60),0) | E27: =IFERROR((((((($C$5+$C$6+($C$17*$B27))*(1-$C$7)-((Control!$B$16*(1+E$22)*Control!$B$17/1000)*$C$11*$C$14)-((Control!$B$16*(1+E$22)*Control!$B$17/1000)*$C$12*$C$15))/($C$8+((Control!$B$16*(1+E$22)*Control!$B$17/1000)*$C$13/Control!$B$4*1000)))*1000)-'Merger-Model'!F60)/'Merger-Model'!F60),0) | F27: =IFERROR((((((($C$5+$C$6+($C$17*$B27))*(1-$C$7)-((Control!$B$16*(1+F$22)*Control!$B$17/1000)*$C$11*$C$14)-((Control!$B$16*(1+F$22)*Control!$B$17/1000)*$C$12*$C$15))/($C$8+((Control!$B$16*(1+F$22)*Control!$B$17/1000)*$C$13/Control!$B$4*1000)))*1000)-'Merger-Model'!F60)/'Merger-Model'!F60),0) | G27: =IFERROR((((((($C$5+$C$6+($C$17*$B27))*(1-$C$7)-((Control!$B$16*(1+G$22)*Control!$B$17/1000)*$C$11*$C$14)-((Control!$B$16*(1+G$22)*Control!$B$17/1000)*$C$12*$C$15))/($C$8+((Control!$B$16*(1+G$22)*Control!$B$17/1000)*$C$13/Control!$B$4*1000)))*1000)-'Merger-Model'!F60)/'Merger-Model'!F60),0) | H27: =IFERROR((((((($C$5+$C$6+($C$17*$B27))*(1-$C$7)-((Control!$B$16*(1+H$22)*Control!$B$17/1000)*$C$11*$C$14)-((Control!$B$16*(1+H$22)*Control!$B$17/1000)*$C$12*$C$15))/($C$8+((Control!$B$16*(1+H$22)*Control!$B$17/1000)*$C$13/Control!$B$4*1000)))*1000)-'Merger-Model'!F60)/'Merger-Model'!F60),0)
B31: 2026 EPS accretion / dilution: purchase premium vs revenue synergies
B33: Revenue synergy % | D33: 0.1 | E33: 0.2 | F33: 0.3 | G33: 0.4 | H33: 0.5
B34: 0 | D34: =IFERROR((((((($C$5+$C$6+($C$16*$B34*$C$18))*(1-$C$7)-((Control!$B$16*(1+D$33)*Control!$B$17/1000)*$C$11*$C$14)-((Control!$B$16*(1+D$33)*Control!$B$17/1000)*$C$12*$C$15))/($C$8+((Control!$B$16*(1+D$33)*Control!$B$17/1000)*$C$13/Control!$B$4*1000)))*1000)-'Merger-Model'!F60)/'Merger-Model'!F60),0) | E34: =IFERROR((((((($C$5+$C$6+($C$16*$B34*$C$18))*(1-$C$7)-((Control!$B$16*(1+E$33)*Control!$B$17/1000)*$C$11*$C$14)-((Control!$B$16*(1+E$33)*Control!$B$17/1000)*$C$12*$C$15))/($C$8+((Control!$B$16*(1+E$33)*Control!$B$17/1000)*$C$13/Control!$B$4*1000)))*1000)-'Merger-Model'!F60)/'Merger-Model'!F60),0) | F34: =IFERROR((((((($C$5+$C$6+($C$16*$B34*$C$18))*(1-$C$7)-((Control!$B$16*(1+F$33)*Control!$B$17/1000)*$C$11*$C$14)-((Control!$B$16*(1+F$33)*Control!$B$17/1000)*$C$12*$C$15))/($C$8+((Control!$B$16*(1+F$33)*Control!$B$17/1000)*$C$13/Control!$B$4*1000)))*1000)-'Merger-Model'!F60)/'Merger-Model'!F60),0) | G34: =IFERROR((((((($C$5+$C$6+($C$16*$B34*$C$18))*(1-$C$7)-((Control!$B$16*(1+G$33)*Control!$B$17/1000)*$C$11*$C$14)-((Control!$B$16*(1+G$33)*Control!$B$17/1000)*$C$12*$C$15))/($C$8+((Control!$B$16*(1+G$33)*Control!$B$17/1000)*$C$13/Control!$B$4*1000)))*1000)-'Merger-Model'!F60)/'Merger-Model'!F60),0) | H34: =IFERROR((((((($C$5+$C$6+($C$16*$B34*$C$18))*(1-$C$7)-((Control!$B$16*(1+H$33)*Control!$B$17/1000)*$C$11*$C$14)-((Control!$B$16*(1+H$33)*Control!$B$17/1000)*$C$12*$C$15))/($C$8+((Control!$B$16*(1+H$33)*Control!$B$17/1000)*$C$13/Control!$B$4*1000)))*1000)-'Merger-Model'!F60)/'Merger-Model'!F60),0)
B35: 0.01 | D35: =IFERROR((((((($C$5+$C$6+($C$16*$B35*$C$18))*(1-$C$7)-((Control!$B$16*(1+D$33)*Control!$B$17/1000)*$C$11*$C$14)-((Control!$B$16*(1+D$33)*Control!$B$17/1000)*$C$12*$C$15))/($C$8+((Control!$B$16*(1+D$33)*Control!$B$17/1000)*$C$13/Control!$B$4*1000)))*1000)-'Merger-Model'!F60)/'Merger-Model'!F60),0) | E35: =IFERROR((((((($C$5+$C$6+($C$16*$B35*$C$18))*(1-$C$7)-((Control!$B$16*(1+E$33)*Control!$B$17/1000)*$C$11*$C$14)-((Control!$B$16*(1+E$33)*Control!$B$17/1000)*$C$12*$C$15))/($C$8+((Control!$B$16*(1+E$33)*Control!$B$17/1000)*$C$13/Control!$B$4*1000)))*1000)-'Merger-Model'!F60)/'Merger-Model'!F60),0) | F35: =IFERROR((((((($C$5+$C$6+($C$16*$B35*$C$18))*(1-$C$7)-((Control!$B$16*(1+F$33)*Control!$B$17/1000)*$C$11*$C$14)-((Control!$B$16*(1+F$33)*Control!$B$17/1000)*$C$12*$C$15))/($C$8+((Control!$B$16*(1+F$33)*Control!$B$17/1000)*$C$13/Control!$B$4*1000)))*1000)-'Merger-Model'!F60)/'Merger-Model'!F60),0) | G35: =IFERROR((((((($C$5+$C$6+($C$16*$B35*$C$18))*(1-$C$7)-((Control!$B$16*(1+G$33)*Control!$B$17/1000)*$C$11*$C$14)-((Control!$B$16*(1+G$33)*Control!$B$17/1000)*$C$12*$C$15))/($C$8+((Control!$B$16*(1+G$33)*Control!$B$17/1000)*$C$13/Control!$B$4*1000)))*1000)-'Merger-Model'!F60)/'Merger-Model'!F60),0) | H35: =IFERROR((((((($C$5+$C$6+($C$16*$B35*$C$18))*(1-$C$7)-((Control!$B$16*(1+H$33)*Control!$B$17/1000)*$C$11*$C$14)-((Control!$B$16*(1+H$33)*Control!$B$17/1000)*$C$12*$C$15))/($C$8+((Control!$B$16*(1+H$33)*Control!$B$17/1000)*$C$13/Control!$B$4*1000)))*1000)-'Merger-Model'!F60)/'Merger-Model'!F60),0)
B36: 0.02 | D36: =IFERROR((((((($C$5+$C$6+($C$16*$B36*$C$18))*(1-$C$7)-((Control!$B$16*(1+D$33)*Control!$B$17/1000)*$C$11*$C$14)-((Control!$B$16*(1+D$33)*Control!$B$17/1000)*$C$12*$C$15))/($C$8+((Control!$B$16*(1+D$33)*Control!$B$17/1000)*$C$13/Control!$B$4*1000)))*1000)-'Merger-Model'!F60)/'Merger-Model'!F60),0) | E36: =IFERROR((((((($C$5+$C$6+($C$16*$B36*$C$18))*(1-$C$7)-((Control!$B$16*(1+E$33)*Control!$B$17/1000)*$C$11*$C$14)-((Control!$B$16*(1+E$33)*Control!$B$17/1000)*$C$12*$C$15))/($C$8+((Control!$B$16*(1+E$33)*Control!$B$17/1000)*$C$13/Control!$B$4*1000)))*1000)-'Merger-Model'!F60)/'Merger-Model'!F60),0) | F36: =IFERROR((((((($C$5+$C$6+($C$16*$B36*$C$18))*(1-$C$7)-((Control!$B$16*(1+F$33)*Control!$B$17/1000)*$C$11*$C$14)-((Control!$B$16*(1+F$33)*Control!$B$17/1000)*$C$12*$C$15))/($C$8+((Control!$B$16*(1+F$33)*Control!$B$17/1000)*$C$13/Control!$B$4*1000)))*1000)-'Merger-Model'!F60)/'Merger-Model'!F60),0) | G36: =IFERROR((((((($C$5+$C$6+($C$16*$B36*$C$18))*(1-$C$7)-((Control!$B$16*(1+G$33)*Control!$B$17/1000)*$C$11*$C$14)-((Control!$B$16*(1+G$33)*Control!$B$17/1000)*$C$12*$C$15))/($C$8+((Control!$B$16*(1+G$33)*Control!$B$17/1000)*$C$13/Control!$B$4*1000)))*1000)-'Merger-Model'!F60)/'Merger-Model'!F60),0) | H36: =IFERROR((((((($C$5+$C$6+($C$16*$B36*$C$18))*(1-$C$7)-((Control!$B$16*(1+H$33)*Control!$B$17/1000)*$C$11*$C$14)-((Control!$B$16*(1+H$33)*Control!$B$17/1000)*$C$12*$C$15))/($C$8+((Control!$B$16*(1+H$33)*Control!$B$17/1000)*$C$13/Control!$B$4*1000)))*1000)-'Merger-Model'!F60)/'Merger-Model'!F60),0)
B37: 0.03 | D37: =IFERROR((((((($C$5+$C$6+($C$16*$B37*$C$18))*(1-$C$7)-((Control!$B$16*(1+D$33)*Control!$B$17/1000)*$C$11*$C$14)-((Control!$B$16*(1+D$33)*Control!$B$17/1000)*$C$12*$C$15))/($C$8+((Control!$B$16*(1+D$33)*Control!$B$17/1000)*$C$13/Control!$B$4*1000)))*1000)-'Merger-Model'!F60)/'Merger-Model'!F60),0) | E37: =IFERROR((((((($C$5+$C$6+($C$16*$B37*$C$18))*(1-$C$7)-((Control!$B$16*(1+E$33)*Control!$B$17/1000)*$C$11*$C$14)-((Control!$B$16*(1+E$33)*Control!$B$17/1000)*$C$12*$C$15))/($C$8+((Control!$B$16*(1+E$33)*Control!$B$17/1000)*$C$13/Control!$B$4*1000)))*1000)-'Merger-Model'!F60)/'Merger-Model'!F60),0) | F37: =IFERROR((((((($C$5+$C$6+($C$16*$B37*$C$18))*(1-$C$7)-((Control!$B$16*(1+F$33)*Control!$B$17/1000)*$C$11*$C$14)-((Control!$B$16*(1+F$33)*Control!$B$17/1000)*$C$12*$C$15))/($C$8+((Control!$B$16*(1+F$33)*Control!$B$17/1000)*$C$13/Control!$B$4*1000)))*1000)-'Merger-Model'!F60)/'Merger-Model'!F60),0) | G37: =IFERROR((((((($C$5+$C$6+($C$16*$B37*$C$18))*(1-$C$7)-((Control!$B$16*(1+G$33)*Control!$B$17/1000)*$C$11*$C$14)-((Control!$B$16*(1+G$33)*Control!$B$17/1000)*$C$12*$C$15))/($C$8+((Control!$B$16*(1+G$33)*Control!$B$17/1000)*$C$13/Control!$B$4*1000)))*1000)-'Merger-Model'!F60)/'Merger-Model'!F60),0) | H37: =IFERROR((((((($C$5+$C$6+($C$16*$B37*$C$18))*(1-$C$7)-((Control!$B$16*(1+H$33)*Control!$B$17/1000)*$C$11*$C$14)-((Control!$B$16*(1+H$33)*Control!$B$17/1000)*$C$12*$C$15))/($C$8+((Control!$B$16*(1+H$33)*Control!$B$17/1000)*$C$13/Control!$B$4*1000)))*1000)-'Merger-Model'!F60)/'Merger-Model'!F60),0)
B38: 0.04 | D38: =IFERROR((((((($C$5+$C$6+($C$16*$B38*$C$18))*(1-$C$7)-((Control!$B$16*(1+D$33)*Control!$B$17/1000)*$C$11*$C$14)-((Control!$B$16*(1+D$33)*Control!$B$17/1000)*$C$12*$C$15))/($C$8+((Control!$B$16*(1+D$33)*Control!$B$17/1000)*$C$13/Control!$B$4*1000)))*1000)-'Merger-Model'!F60)/'Merger-Model'!F60),0) | E38: =IFERROR((((((($C$5+$C$6+($C$16*$B38*$C$18))*(1-$C$7)-((Control!$B$16*(1+E$33)*Control!$B$17/1000)*$C$11*$C$14)-((Control!$B$16*(1+E$33)*Control!$B$17/1000)*$C$12*$C$15))/($C$8+((Control!$B$16*(1+E$33)*Control!$B$17/1000)*$C$13/Control!$B$4*1000)))*1000)-'Merger-Model'!F60)/'Merger-Model'!F60),0) | F38: =IFERROR((((((($C$5+$C$6+($C$16*$B38*$C$18))*(1-$C$7)-((Control!$B$16*(1+F$33)*Control!$B$17/1000)*$C$11*$C$14)-((Control!$B$16*(1+F$33)*Control!$B$17/1000)*$C$12*$C$15))/($C$8+((Control!$B$16*(1+F$33)*Control!$B$17/1000)*$C$13/Control!$B$4*1000)))*1000)-'Merger-Model'!F60)/'Merger-Model'!F60),0) | G38: =IFERROR((((((($C$5+$C$6+($C$16*$B38*$C$18))*(1-$C$7)-((Control!$B$16*(1+G$33)*Control!$B$17/1000)*$C$11*$C$14)-((Control!$B$16*(1+G$33)*Control!$B$17/1000)*$C$12*$C$15))/($C$8+((Control!$B$16*(1+G$33)*Control!$B$17/1000)*$C$13/Control!$B$4*1000)))*1000)-'Merger-Model'!F60)/'Merger-Model'!F60),0) | H38: =IFERROR((((((($C$5+$C$6+($C$16*$B38*$C$18))*(1-$C$7)-((Control!$B$16*(1+H$33)*Control!$B$17/1000)*$C$11*$C$14)-((Control!$B$16*(1+H$33)*Control!$B$17/1000)*$C$12*$C$15))/($C$8+((Control!$B$16*(1+H$33)*Control!$B$17/1000)*$C$13/Control!$B$4*1000)))*1000)-'Merger-Model'!F60)/'Merger-Model'!F60),0)
B39: 0.05 | D39: =IFERROR((((((($C$5+$C$6+($C$16*$B39*$C$18))*(1-$C$7)-((Control!$B$16*(1+D$33)*Control!$B$17/1000)*$C$11*$C$14)-((Control!$B$16*(1+D$33)*Control!$B$17/1000)*$C$12*$C$15))/($C$8+((Control!$B$16*(1+D$33)*Control!$B$17/1000)*$C$13/Control!$B$4*1000)))*1000)-'Merger-Model'!F60)/'Merger-Model'!F60),0) | E39: =IFERROR((((((($C$5+$C$6+($C$16*$B39*$C$18))*(1-$C$7)-((Control!$B$16*(1+E$33)*Control!$B$17/1000)*$C$11*$C$14)-((Control!$B$16*(1+E$33)*Control!$B$17/1000)*$C$12*$C$15))/($C$8+((Control!$B$16*(1+E$33)*Control!$B$17/1000)*$C$13/Control!$B$4*1000)))*1000)-'Merger-Model'!F60)/'Merger-Model'!F60),0) | F39: =IFERROR((((((($C$5+$C$6+($C$16*$B39*$C$18))*(1-$C$7)-((Control!$B$16*(1+F$33)*Control!$B$17/1000)*$C$11*$C$14)-((Control!$B$16*(1+F$33)*Control!$B$17/1000)*$C$12*$C$15))/($C$8+((Control!$B$16*(1+F$33)*Control!$B$17/1000)*$C$13/Control!$B$4*1000)))*1000)-'Merger-Model'!F60)/'Merger-Model'!F60),0) | G39: =IFERROR((((((($C$5+$C$6+($C$16*$B39*$C$18))*(1-$C$7)-((Control!$B$16*(1+G$33)*Control!$B$17/1000)*$C$11*$C$14)-((Control!$B$16*(1+G$33)*Control!$B$17/1000)*$C$12*$C$15))/($C$8+((Control!$B$16*(1+G$33)*Control!$B$17/1000)*$C$13/Control!$B$4*1000)))*1000)-'Merger-Model'!F60)/'Merger-Model'!F60),0) | H39: =IFERROR((((((($C$5+$C$6+($C$16*$B39*$C$18))*(1-$C$7)-((Control!$B$16*(1+H$33)*Control!$B$17/1000)*$C$11*$C$14)-((Control!$B$16*(1+H$33)*Control!$B$17/1000)*$C$12*$C$15))/($C$8+((Control!$B$16*(1+H$33)*Control!$B$17/1000)*$C$13/Control!$B$4*1000)))*1000)-'Merger-Model'!F60)/'Merger-Model'!F60),0)
B41: Catatan: margin revenue synergy kini = margin segmen aktual (data-linked C18), bukan asumsi 60% legacy. Axis tetap % untuk what-if.
B43: Valuation cross-check
B45: Standalone target EV | C45: ='M&A_Valuation'!C24
B46: Offer EV | C46: ='M&A_Valuation'!C33
B47: Synergy NPV | C47: ='M&A_Valuation'!C35
B48: Affordable EV incl. synergies | C48: ='M&A_Valuation'!C37

Sheet Financing_Mix
A1: Financing Mix (Aligned to Merger-Model & Sensitivities)
A3: Model-Linked Financing Assumptions
A4: Purchase premium | B4: =Control!$B$10 | C4: Linked to Control and used in Merger-Model purchase price | E4: Interpretation
A5: % cash funding | B5: ='Merger-Model'!$F$8 | C5: Must match Sensitivities C11 | E5: Funding structure
A6: % debt funding | B6: ='Merger-Model'!$F$9 | C6: Must match Sensitivities C12 | E6: Cash coverage vs equity purchase price | F6: =IFERROR(B15/B24,0)
A7: % stock funding | B7: ='Merger-Model'!$F$10 | C7: Must match Sensitivities C13 | E7: Implied stock issuance as % of buyer shares | F7: =IFERROR(B27/B18,0)
A8: Foregone cash rate | B8: =Control!$B$12 | C8: Used in Sensitivities as financing drag on cash portion | E8: Estimated financing drag / buyer EBITDA | F8: =IFERROR(B33/B17,0)
A9: Debt interest rate | B9: =Control!$B$13 | C9: Used in Sensitivities as financing drag on debt portion | E9: Pro forma gross debt / EBITDA | F9: =B40
A10: Buyer tax rate | B10: =Control!$B$11 | C10: Applied to combined pre-tax earnings in sensitivities
A11: Buyer share price (IDR) | B11: =Control!$B$4 | C11: Used to translate stock consideration into new shares
A14: Buyer Standalone Position (FY2025) | E14: Metric | F14: Value
A15: Buyer cash (IDR mm) | B15: ='TOWR-3-Statements'!G59/1000 | C15: Cash & short-term securities | E15: Buyer cash | F15: =B15
A16: Buyer gross debt (IDR mm) | B16: =('TOWR-3-Statements'!G80+'TOWR-3-Statements'!G87)/1000 | C16: ST + LT debt | E16: Cash used | F16: =B25
A17: Buyer EBITDA (IDR mm) | B17: ='TOWR-3-Statements'!G41/1000 | C17: EBIT + D&A proxy | E17: Remaining cash | F17: =B38
A18: Buyer shares (000) | B18: =Control!$B$5 | C18: Diluted share count
A19: Buyer pre-deal EPS (IDR/share) | B19: ='Merger-Model'!F60 | C19: Base EPS used for accretion/dilution
A22: Sources & Uses (Directly Aligned to Merger-Model)
A23: Seller offer price / share (IDR) | B23: ='Merger-Model'!$F$7 | C23: Purchase price incl. premium
A24: Equity purchase price (IDR mm) | B24: ='Merger-Model'!$L$7 | C24: Used in Merger-Model rows 7-10
A25: Cash used (IDR mm) | B25: ='Merger-Model'!$L$8 | C25: Cash-funded portion
A26: Debt issued (IDR mm) | B26: ='Merger-Model'!$L$9 | C26: Debt-funded portion
A27: New shares issued (000) | B27: ='Merger-Model'!$L$10 | C27: Stock-funded portion translated into shares
A28: Stock consideration value (IDR mm) | B28: =B27*$B$11/1000 | C28: Implied value of stock consideration
A30: Financing Drag (Mirror of Sensitivities Formula Logic)
A31: Foregone cash cost (pre-tax, IDR mm) | B31: =B25*$B$8 | C31: Cash used × foregone cash rate
A32: Debt interest cost (pre-tax, IDR mm) | B32: =B26*$B$9 | C32: Debt issued × debt rate
A33: Total financing drag (pre-tax, IDR mm) | B33: =SUM(B31:B32) | C33: Directly mirrors cash and debt deductions in Sensitivities
A34: Estimated after-tax financing drag (IDR mm) | B34: =B33*(1-$B$10) | C34: Shown for analytical reference
A37: Pro Forma Capitalization & Balance Sheet Effects
A38: Remaining buyer cash after deal (IDR mm) | B38: =B15-B25 | C38: Post-deal cash balance
A39: Pro forma gross debt (IDR mm) | B39: =B16+B26 | C39: Buyer debt + new debt issued
A40: Pro forma net cash / (debt) (IDR mm) | B40: =B38-B39 | C40: Positive = net cash, negative = net debt
A41: Pro forma gross debt / EBITDA | B41: =IFERROR(B39/B17,0) | C41: Headline leverage after transaction
A42: Pro forma share count (000) | B42: =B18+B27 | C42: Buyer shares + new shares issued

Sheet Financing Strategy
A1: TOWR + WIFI | Financing Strategy (Section 4)
A2: All figures Rp bn. Linked to Control / Merger-Model. 51% acquisition, 60% debt / 40% equity funding.
A4: Key assumptions
A5: Run-rate synergy (full, Rp bn) | B5: 400
A6: Min. interest-coverage covenant (x) | B6: 2.5
A7: Bridge/acquisition debt rate | B7: =Control!B13
A8: Refloat proceeds (Rp bn) | B8: 10000
A10: A. LEVERAGE PROFILE ACROSS TENDER-ACCEPTANCE SCENARIOS
B11: Standalone | C11: Pro-forma 0% tender | D11: Pro-forma 50% tender | E11: Pro-forma 100% tender | F11: Post-refloat
A12: Net debt | B12: =('TOWR-3-Statements'!G80+'TOWR-3-Statements'!G87-'TOWR-3-Statements'!G59)/1000000 | C12: =B12+'Merger-Model'!L9/1000 | D12: =C12+0.5*(1-Control!B14)*'Merger-Shares-BS'!J15/1000 | E12: =C12+(1-Control!B14)*'Merger-Shares-BS'!J15/1000 | F12: =E12-B8
A13: EBITDA (+synergies post-refloat) | B13: ='TOWR-3-Statements'!G41/1000000 | C13: =('TOWR-3-Statements'!G41+'WIFI 3-Statement Model'!H37)/1000000 | D13: =C13 | E13: =C13 | F13: =C13+B5
A14: Net debt / EBITDA | B14: =B12/B13 | C14: =C12/C13 | D14: =D12/D13 | E14: =E12/E13 | F14: =F12/F13
A15: Interest expense | B15: =-'TOWR-3-Statements'!G44/1000000 | C15: =B15+(C12-B12)*$B$7 | D15: =B15+(D12-B12)*$B$7 | E15: =B15+(E12-B12)*$B$7 | F15: =B15+(F12-B12)*$B$7
A16: Interest coverage (EBITDA / interest) | B16: =B13/B15 | C16: =C13/C15 | D16: =D13/D15 | E16: =E13/E15 | F16: =F13/F15
A17: Debt / equity | B17: =('TOWR-3-Statements'!G80+'TOWR-3-Statements'!G87)/'TOWR-3-Statements'!G99 | C17: =(('TOWR-3-Statements'!G80+'TOWR-3-Statements'!G87)/1000000+'Merger-Model'!L9/1000)/(('TOWR-3-Statements'!G99)/1000000+'Merger-Model'!F10*'Merger-Model'!L7/1000) | D17: =C17 | E17: =C17 | F17: =C17
A18: Debt / total assets | B18: =('TOWR-3-Statements'!G80+'TOWR-3-Statements'!G87)/'TOWR-3-Statements'!G75 | C18: =(('TOWR-3-Statements'!G80+'TOWR-3-Statements'!G87)/1000000+'Merger-Model'!L9/1000)/('TOWR-3-Statements'!G75/1000000+'WIFI 3-Statement Model'!H62/1000000+'Merger-Model'!F28/1000) | D18: =C18 | E18: =C18 | F18: =C18
A20: B. COVENANT HEADROOM
A21: Binding covenant: interest coverage (tightest in infra credit agreements)
A22: Pro-forma interest coverage (0% tender) | B22: =C16
A23: Covenant floor | B23: =B6
A24: Headroom vs covenant (x) | B24: =B22-B23
A25: EBITDA decline to breach covenant | B25: =1-B23*C15/C13
A26: Full-tender interim coverage (pre-refloat) | B26: =E16
A27: Post-refloat coverage | B27: =F16
A29: C. CREDIT-RATING IMPLICATIONS
A30: • Leverage rises only modestly (4.07x -> 4.23x) as the 40% equity portion limits new debt.
A31: • Interest coverage is the tightest metric; kept above the covenant floor under the base case.
A32: • Full-tender acceptance pushes interim leverage to ~5.07x -> refloat timetable is a rating commitment.
A33: • Rating-preservation actions: pre-brief agencies, publish refloat & deleveraging schedule,
A34: retain option to raise the equity portion if rating indications weaken.
A35: • Target's net-cash position (Rp565bn) and Rp1,106bn incremental EBITDA cushion the added debt.

Sheet Returns Analysis
A1: TOWR + WIFI | Return Analysis (Section 5)
A2: Rp bn. Acquirer cash flow = 51% of target FCF + after-tax synergies - integration. Discounted at WACC.
A4: Assumptions
A5: WACC (acquirer) | B5: ='TOWR WACC'!D9
A6: Stake acquired | B6: =Control!B14
A7: Exit EV/EBITDA (terminal) | B7: 8.5
A8: Full run-rate synergy (Rp bn) — linked to bottom-up gross | B8: ='Synergies'!J45+'Synergies'!J30+'Synergies'!J56
A9: Synergy realization % — implied by bottom-up haircut | B9: =('Synergies'!M45+'Synergies'!M30+'Synergies'!M56)/B8
A10: Transaction cost (Rp bn) | B10: 310.5
A11: Integration cost total (Rp bn) | B11: 520
A12: Net tender cost after refloat (Rp bn) | B12: 850
A13: FWA expansion option value (Rp bn) | B13: 1120
A14: Tax rate | B14: =Control!B11
A16: A. ACQUIRER CASH FLOW, NPV, IRR & PAYBACK (base case)
B17: Year: | C17: 0 | D17: 1 | E17: 2 | F17: 3 | G17: 4 | H17: 5
A18: 51% controlling-block price | C18: =-'Merger-Model'!L7/1000
A19: Net tender cost (after refloat) | C19: =-B12
A20: Transaction cost | C20: =-B10
A21: 51% of target FCF | D21: =$B$6*'M&A_Valuation'!C18/1000 | E21: =$B$6*'M&A_Valuation'!D18/1000 | F21: =$B$6*'M&A_Valuation'!E18/1000 | G21: =$B$6*'M&A_Valuation'!F18/1000 | H21: =$B$6*'M&A_Valuation'!G18/1000
A22: After-tax synergies net of dissynergies (D1–D3 yr1–3; D1–D2 only from yr4 — D3 is transitional) | D22: =($B$8*$B$9*0.25-'Dissynergy'!$F$30)*(1-$B$14) | E22: =($B$8*$B$9*0.6-'Dissynergy'!$F$30)*(1-$B$14) | F22: =($B$8*$B$9*0.85-'Dissynergy'!$F$30)*(1-$B$14) | G22: =($B$8*$B$9*1-'Dissynergy'!$F$29)*(1-$B$14) | H22: =($B$8*$B$9*1-'Dissynergy'!$F$29)*(1-$B$14)
A23: Integration cost (yr1-2) | D23: =-B11/2 | E23: =-B11/2
A24: Terminal equity value (51% x [exit x EBITDA - net debt]) | H24: =$B$6*($B$7*'WIFI 3-Statement Model'!M37/1000000-('WIFI 3-Statement Model'!M66+'WIFI 3-Statement Model'!M71-'WIFI 3-Statement Model'!M51)/1000000)
A25: Net cash flow | C25: =SUM(C18:C24) | D25: =SUM(D18:D24) | E25: =SUM(E18:E24) | F25: =SUM(F18:F24) | G25: =SUM(G18:G24) | H25: =SUM(H18:H24)
A26: Discount factor | C26: =1/(1+$B$5)^0 | D26: =1/(1+$B$5)^1 | E26: =1/(1+$B$5)^2 | F26: =1/(1+$B$5)^3 | G26: =1/(1+$B$5)^4 | H26: =1/(1+$B$5)^5
A27: PV of net cash flow | C27: =C25*C26 | D27: =D25*D26 | E27: =E25*E26 | F27: =F25*F26 | G27: =G25*G26 | H27: =H25*H26
A28: Cumulative cash flow | C28: =C25 | D28: =C28+D25 | E28: =D28+E25 | F28: =E28+F25 | G28: =F28+G25 | H28: =G28+H25
A30: NPV | B30: =SUM(C27:H27)
A31: IRR | B31: =IRR(C25:H25)
A32: Payback period (years, incl. exit value) | B32: =IFERROR((SUMPRODUCT(--(C28:H28<0))-1)+(-INDEX(C28:H28,SUMPRODUCT(--(C28:H28<0))))/INDEX(C25:H25,SUMPRODUCT(--(C28:H28<0))+1),"beyond horizon")
A33: vs WACC hurdle | B33: =B31-B5
A34: Payback on operating CF only (excl. exit) | B34: "beyond 5-yr window"
A35: B. VALUE CREATION BRIDGE
A36: Standalone value of the 51% stake | B36: =$B$6*Control!B18/1000
A37: PV of risk-adjusted synergies | B37: =SUMPRODUCT(D22:H22,D26:H26)+(H22/($B$5-0.03))*H26
A38: Option value of FWA expansion | B38: =B13
A39: Less: acquisition premium paid | B39: =-('Merger-Model'!L7/1000-B36)
A40: Less: integration cost | B40: =-B11
A41: Less: transaction cost | B41: =-B10
A42: Less: net tender-offer cost | B42: =-B12
A43: NET VALUE CREATION (all-in: synergies − dissynergies − costs + one-time) | B43: =SUM(B37:B42)+B44
A44: Plus: one-time items (C8 capex avoidance + F4 tax shield + F5 working capital − D4 overrun − D5 attrition) | B44: ='Synergies'!H35+'Synergies'!H61+'Synergies'!H62-'Dissynergy'!F27-'Dissynergy'!F28
A45: C. SCENARIO ANALYSIS (IRR / NPV / payback)
A46: Driver | B46: Bear | C46: Base | D46: Bull
A47: Synergy realization | B47: 0.4 | C47: =B9 | D47: 1
A48: Target FCF scalar (rev growth) | B48: 0.7 | C48: 1 | D48: 1.3
A49: Exit EV/EBITDA | B49: 6 | C49: 8.5 | D49: 11
B52: Cash-flow stream (Rp bn): | C52: Y0 | D52: Y1 | E52: Y2 | F52: Y3 | G52: Y4 | H52: Y5 | I52: NPV | J52: IRR
A53: Bear | C53: =SUM($C$18:$C$20) | D53: =$B$48*D21+($B$47/$B$9)*D22+D23 | E53: =$B$48*E21+($B$47/$B$9)*E22+E23 | F53: =$B$48*F21+($B$47/$B$9)*F22+F23 | G53: =$B$48*G21+($B$47/$B$9)*G22+G23 | H53: =$B$48*H21+($B$47/$B$9)*H22+H23+$B$48*($B$49/$B$7)*$H$24 | I53: =C53+NPV($B$5,D53:H53) | J53: =IFERROR(IRR(C53:H53),"n.m.")
A54: Base | C54: =SUM($C$18:$C$20) | D54: =$C$48*D21+($C$47/$B$9)*D22+D23 | E54: =$C$48*E21+($C$47/$B$9)*E22+E23 | F54: =$C$48*F21+($C$47/$B$9)*F22+F23 | G54: =$C$48*G21+($C$47/$B$9)*G22+G23 | H54: =$C$48*H21+($C$47/$B$9)*H22+H23+$C$48*($C$49/$B$7)*$H$24 | I54: =C54+NPV($B$5,D54:H54) | J54: =IFERROR(IRR(C54:H54),"n.m.")
A55: Bull | C55: =SUM($C$18:$C$20) | D55: =$D$48*D21+($D$47/$B$9)*D22+D23 | E55: =$D$48*E21+($D$47/$B$9)*E22+E23 | F55: =$D$48*F21+($D$47/$B$9)*F22+F23 | G55: =$D$48*G21+($D$47/$B$9)*G22+G23 | H55: =$D$48*H21+($D$47/$B$9)*H22+H23+$D$48*($D$49/$B$7)*$H$24 | I55: =C55+NPV($B$5,D55:H55) | J55: =IFERROR(IRR(C55:H55),"n.m.")
A64: Sensitivity helpers
A65: PV of base 51% target FCF (yr1-5) | B65: =SUMPRODUCT($D$21:$H$21,$D$26:$H$26)
A66: PV of base after-tax synergy (yr1-5) | B66: =SUMPRODUCT($D$22:$H$22,$D$26:$H$26)
A67: PV of terminal per 1.0x exit | B67: =($H$24/$B$7)*$H$26
A68: Upfront (price+tender+txn)+integ PV | B68: =SUM($C$18:$C$20)+SUMPRODUCT($D$23:$E$23,$D$26:$E$26)
A70: D. SENSITIVITY 1 - NPV (Rp bn): Exit EV/EBITDA (rows) x Synergy realization (cols)
A71: FCF scalar held at base (1.0x)
B72: NPV | C72: 0.4 | D72: 0.55 | E72: 0.7 | F72: 0.85 | G72: 1
B73: 6 | C73: =$B$65+(C$72/$B$9)*$B$66+$B73*$B$67+$B$68 | D73: =$B$65+(D$72/$B$9)*$B$66+$B73*$B$67+$B$68 | E73: =$B$65+(E$72/$B$9)*$B$66+$B73*$B$67+$B$68 | F73: =$B$65+(F$72/$B$9)*$B$66+$B73*$B$67+$B$68 | G73: =$B$65+(G$72/$B$9)*$B$66+$B73*$B$67+$B$68
B74: 7.5 | C74: =$B$65+(C$72/$B$9)*$B$66+$B74*$B$67+$B$68 | D74: =$B$65+(D$72/$B$9)*$B$66+$B74*$B$67+$B$68 | E74: =$B$65+(E$72/$B$9)*$B$66+$B74*$B$67+$B$68 | F74: =$B$65+(F$72/$B$9)*$B$66+$B74*$B$67+$B$68 | G74: =$B$65+(G$72/$B$9)*$B$66+$B74*$B$67+$B$68
B75: 8.5 | C75: =$B$65+(C$72/$B$9)*$B$66+$B75*$B$67+$B$68 | D75: =$B$65+(D$72/$B$9)*$B$66+$B75*$B$67+$B$68 | E75: =$B$65+(E$72/$B$9)*$B$66+$B75*$B$67+$B$68 | F75: =$B$65+(F$72/$B$9)*$B$66+$B75*$B$67+$B$68 | G75: =$B$65+(G$72/$B$9)*$B$66+$B75*$B$67+$B$68
B76: 10 | C76: =$B$65+(C$72/$B$9)*$B$66+$B76*$B$67+$B$68 | D76: =$B$65+(D$72/$B$9)*$B$66+$B76*$B$67+$B$68 | E76: =$B$65+(E$72/$B$9)*$B$66+$B76*$B$67+$B$68 | F76: =$B$65+(F$72/$B$9)*$B$66+$B76*$B$67+$B$68 | G76: =$B$65+(G$72/$B$9)*$B$66+$B76*$B$67+$B$68
B77: 11 | C77: =$B$65+(C$72/$B$9)*$B$66+$B77*$B$67+$B$68 | D77: =$B$65+(D$72/$B$9)*$B$66+$B77*$B$67+$B$68 | E77: =$B$65+(E$72/$B$9)*$B$66+$B77*$B$67+$B$68 | F77: =$B$65+(F$72/$B$9)*$B$66+$B77*$B$67+$B$68 | G77: =$B$65+(G$72/$B$9)*$B$66+$B77*$B$67+$B$68
A80: E. SENSITIVITY 2 - NPV (Rp bn): Exit EV/EBITDA (rows) x Revenue-growth scalar (cols)
A81: Synergy realization held at base (70%)
B82: NPV | C82: 0.7 | D82: 0.85 | E82: 1 | F82: 1.15 | G82: 1.3
B83: 6 | C83: =C$82*$B$65+$B$66+C$82*$B83*$B$67+$B$68 | D83: =D$82*$B$65+$B$66+D$82*$B83*$B$67+$B$68 | E83: =E$82*$B$65+$B$66+E$82*$B83*$B$67+$B$68 | F83: =F$82*$B$65+$B$66+F$82*$B83*$B$67+$B$68 | G83: =G$82*$B$65+$B$66+G$82*$B83*$B$67+$B$68
B84: 7.5 | C84: =C$82*$B$65+$B$66+C$82*$B84*$B$67+$B$68 | D84: =D$82*$B$65+$B$66+D$82*$B84*$B$67+$B$68 | E84: =E$82*$B$65+$B$66+E$82*$B84*$B$67+$B$68 | F84: =F$82*$B$65+$B$66+F$82*$B84*$B$67+$B$68 | G84: =G$82*$B$65+$B$66+G$82*$B84*$B$67+$B$68
B85: 8.5 | C85: =C$82*$B$65+$B$66+C$82*$B85*$B$67+$B$68 | D85: =D$82*$B$65+$B$66+D$82*$B85*$B$67+$B$68 | E85: =E$82*$B$65+$B$66+E$82*$B85*$B$67+$B$68 | F85: =F$82*$B$65+$B$66+F$82*$B85*$B$67+$B$68 | G85: =G$82*$B$65+$B$66+G$82*$B85*$B$67+$B$68
B86: 10 | C86: =C$82*$B$65+$B$66+C$82*$B86*$B$67+$B$68 | D86: =D$82*$B$65+$B$66+D$82*$B86*$B$67+$B$68 | E86: =E$82*$B$65+$B$66+E$82*$B86*$B$67+$B$68 | F86: =F$82*$B$65+$B$66+F$82*$B86*$B$67+$B$68 | G86: =G$82*$B$65+$B$66+G$82*$B86*$B$67+$B$68
B87: 11 | C87: =C$82*$B$65+$B$66+C$82*$B87*$B$67+$B$68 | D87: =D$82*$B$65+$B$66+D$82*$B87*$B$67+$B$68 | E87: =E$82*$B$65+$B$66+E$82*$B87*$B$67+$B$68 | F87: =F$82*$B$65+$B$66+F$82*$B87*$B$67+$B$68 | G87: =G$82*$B$65+$B$66+G$82*$B87*$B$67+$B$68

Sheet Synergies
A1: SYNERGIES — Consolidated Bottom-Up (Cost · Revenue · Financing)
A2: All figures IDR bn unless stated. Blue = input · Green = link to another sheet · Black = formula. Single source feeding Synergy_Schedule, Merger-Model, Sensitivities & Returns Analysis.
A4: ASSUMPTIONS & REFERENCE DATA
B5: Modelling basis (1 = Gross · 2 = Risk-adjusted) | D5: 2
B7: Reference data — actual FY2025 (filings)
B8: WIFI cash SG&A ex-advertising & D&A | D8: 176.7 | O8: Surge AR2025: 211.9 − 22.4 ad − 12.8 D&A
B9: WIFI cost of revenue — unclassified | D9: 349.5 | O9: SOURCE WIFI IS 2025
B10: TOWR cost of revenue — unclassified | D10: 1115.1 | O10: SOURCE TOWR IS 2025
B11: STARLITE revenue (for 20% commission) | D11: 541.1 | O11: Surge AR p.104
B12: TOWR towers | D12: 36247 | O12: SMN AR2025 p.47
B13: TOWR revenue per tenant (IDR bn) | D13: 0.1442 | O13: 8,730 ÷ 60,540
B14: TOWR FTTH home passes (unpenetrated) | D14: 1954000 | O14: 2.34m × (1−16.6%), SMN AR2025 p.158
B15: STARLITE FTTH subscribers | D15: 1500000 | O15: Surge AR2025 p.104
B16: IRA FWA pre-registrations | D16: 1000000 | O16: Surge AR2025 p.106
B17: WIFI B2B / enterprise revenue (IDR bn) | D17: 668.2 | O17: Surge AR2025 (40.3% of revenue)
B18: WIFI broadband tariff (IDR bn/yr) | D18: 0.0012 | O18: Rp100k/month
B19: TOWR cost of debt (Kd, pre-tax) | D19: ='TOWR WACC'!D15 | O19: Link TOWR WACC
A21: A. COST SYNERGIES (run-rate, IDR bn)
A22: Code | B22: Initiative | C22: Bottom-up basis | D22: Base driver | E22: Lever | F22: Qty | G22: Unit | H22: Gross | I22: Drop% | J22: Gross EBIT | K22: Conf. | L22: Ret.% | M22: RA EBIT | N22: RA rev | O22: Source / note
A23: C1 | B23: Corporate & public-co overhead | C23: De-dup finance/HR/IT/audit/listing/board on WIFI cash SG&A | D23: =$D$8 | E23: 0.3 | H23: =D23*E23 | I23: 1 | J23: =H23*I23 | K23: High | L23: 0.85 | M23: =J23*L23 | O23: 30% of WIFI cash SG&A Rp176.7bn (actual)
A24: C2 | B24: FWA/BTS site-lease avoidance | C24: IRA sites co-located on TOWR towers vs leased third-party sites | D24: 2000 | E24: 0.03 | H24: =D24*E24 | I24: 1 | J24: =H24*I24 | K24: Medium | L24: 0.7 | M24: =J24*L24 | O24: 2,000 sites × Rp2.5m/mo × 12
A25: C3 | B25: Fiber backbone & transport | C25: Route WIFI backhaul over TOWR ~185,000 km fibre | D25: =$D$9 | E25: 0.075 | H25: =D25*E25 | I25: 1 | J25: =H25*I25 | K25: Medium | L25: 0.65 | M25: =J25*L25 | O25: 25% of WIFI COR addressable × 30% saving
A26: C4 | B26: Network ops / NOC / field O&M | C26: Merge NOCs & overlapping field-maintenance crews | D26: 1 | E26: 20 | H26: =D26*E26 | I26: 1 | J26: =H26*I26 | K26: Medium | L26: 0.65 | M26: =J26*L26 | O26: Consolidation on overlapping O&M
A27: C5 | B27: Procurement & supply-chain scale | C27: Scale purchasing across combined cost of revenue | D27: =($D$9+$D$10) | E27: 0.015 | H27: =D27*E27 | I27: 1 | J27: =H27*I27 | K27: Med-High | L27: 0.75 | M27: =J27*L27 | O27: Combined COR Rp1,464.6bn × 1.5%
A28: C6 | B28: Energy & power optimization | C28: Shared power at co-located sites, bulk electricity, solar | D28: 1 | E28: 10 | H28: =D28*E28 | I28: 1 | J28: =H28*I28 | K28: Medium | L28: 0.6 | M28: =J28*L28 | O28: Towers power-intensive; conservative
A29: C7 | B29: Distribution commission scale | C29: STARLITE 20% ISP commission reduced by combined scale | D29: =$D$11*0.2 | E29: 0.1 | H29: =D29*E29 | I29: 1 | J29: =H29*I29 | K29: Low-Med | L29: 0.55 | M29: =J29*L29 | O29: 20% commission ≈ Rp108bn × 10% reduction
B30: Total — cost synergies | J30: =SUM(J23:J29) | M30: =SUM(M23:M29)
B31: Selected run-rate (per basis switch) | H31: =IF($D$5=1,J30,M30)
B32: → Feed to Synergy_Schedule (IDR mm) | H32: =H31*1000
B34: CAPITAL ITEM — one-time, NOT in the run-rate above
A35: C8 | B35: Capex avoidance — co-location vs new build | H35: =D75 | O35: NPV, one-time. Build-up in section D.
A37: B. REVENUE SYNERGIES (run-rate, IDR bn)
A38: Code | B38: Initiative | C38: Bottom-up basis | D38: Base driver | E38: Lever | F38: Qty | G38: Unit | H38: Gross | I38: Drop% | J38: Gross EBIT | K38: Conf. | L38: Ret.% | M38: RA EBIT | N38: RA rev | O38: Source / note
A39: R1 | B39: Neutral-host tower tenancy | C39: External co-locations on TOWR towers; intercompany rent excluded | D39: =$D$12 | E39: 0.02 | F39: =D39*E39 | G39: =$D$13 | H39: =F39*G39 | I39: ='TOWR-3-Statements'!G41/'TOWR-3-Statements'!G30 | J39: =H39*I39 | K39: Low | L39: 0.45 | M39: =J39*L39 | N39: =H39*L39 | O39: Drop-through = TOWR EBITDA margin 82%
A40: R2 | B40: FTTH acceleration (STARLITE) | C40: Convert TOWR unpenetrated home passes via STARLITE | D40: =$D$14 | E40: 0.05 | F40: =D40*E40 | G40: =$D$18 | H40: =F40*G40 | I40: ='WIFI Rev-COGS Detail'!H48-0.2 | J40: =H40*I40 | K40: Low | L40: 0.4 | M40: =J40*L40 | N40: =H40*L40 | O40: GM 72.9% − 20% ISP commission
A41: R3 | B41: FWA acceleration (IRA) | C41: Tower co-location speeds IRA coverage | D41: =$D$16 | E41: 0.1 | F41: =D41*E41 | G41: =$D$18 | H41: =F41*G41 | I41: ='WIFI Rev-COGS Detail'!H48-0.15 | J41: =H41*I41 | K41: Low-Med | L41: 0.45 | M41: =J41*L41 | N41: =H41*L41 | O41: GM 72.9% − 15% CPE/delivery
A42: R4 | B42: Enterprise cross-sell (B2B) | C42: Cross-sell TOWR fibre/POPs into WIFI B2B base | D42: =$D$17 | E42: 0.12 | F42: =D42*E42 | G42: 1 | H42: =F42*G42 | I42: ='WIFI Rev-COGS Detail'!H48-0.03 | J42: =H42*I42 | K42: Low | L42: 0.4 | M42: =J42*L42 | N42: =H42*L42 | O42: GM 72.9% (bandwidth/core lease)
A43: R5 | B43: ARPU uplift & churn reduction — EXISTING base | C43: Bundled FTTH+FWA lifts ARPU and retains existing subscribers | H43: =D96 | I43: =D97 | J43: =H43*I43 | K43: Medium | L43: =D98 | M43: =J43*L43 | N43: =H43*L43 | O43: Existing 1.5m subs; +Rp3k/mo ARPU, −1pp churn. Build-up section D
A44: R6 | B44: Advertising inventory scaling | C44: Larger combined subscriber base expands ad inventory | H44: =D105 | I44: =D106 | J44: =H44*I44 | K44: Low-Med | L44: =D107 | M44: =J44*L44 | N44: =H44*L44 | O44: Ad rev Rp459.5bn ÷ 1.5m subs. Build-up section D
B45: Total — revenue synergies | H45: =SUM(H39:H44) | J45: =SUM(J39:J44) | M45: =SUM(M39:M44) | N45: =SUM(N39:N44)
B46: Selected gross revenue | H46: =IF($D$5=1,H45,N45)
B47: Selected EBIT contribution | H47: =IF($D$5=1,J45,M45)
B48: → Feed — gross revenue run-rate (IDR mm) | H48: =H46*1000
B49: → Feed — EBIT run-rate (IDR mm) | H49: =H47*1000
A51: C. FINANCING SYNERGIES (run-rate, IDR bn)
A52: Code | B52: Tranche | C52: Basis | D52: Debt | E52: WIFI rate | F52: TOWR rate | G52: Spread | H52: Gross | K52: Conf. | L52: Ret.% | M52: RA | O52: Source / note
A53: F1 | B53: High-cost bank loans | C53: ST Bank DKI Rp1,350bn + LT bank Rp437bn (J Trust/Hibank/BCA) | D53: 1787 | E53: 0.11 | F53: =$D$19 | G53: =MAX(E53-F53,0) | H53: =D53*G53 | J53: =H53 | K53: High | L53: 0.9 | M53: =J53*L53 | O53: Surge AR p.118 & Note 21; J Trust 10.5–11.75%
A54: F2 | B54: Bonds + sukuk (at maturity) | C54: Obligasi Rp852.5bn + sukuk Rp686.5bn | D54: 1539 | E54: 0.082 | F54: =$D$19 | G54: =MAX(E54-F54,0) | H54: =D54*G54 | J54: =H54 | K54: Medium | L54: 0.55 | M54: =J54*L54 | O54: Surge AR p.118; WIFI blended Kd 8.2%
A55: F3 | B55: Cheaper growth funding | C55: Fund WIFI FWA/FTTH capex on TOWR rating | D55: 4000 | E55: 0.082 | F55: =$D$19 | G55: =MAX(E55-F55,0) | H55: =D55*G55 | J55: =H55 | K55: Med-High | L55: 0.75 | M55: =J55*L55 | O55: Rp4,000bn new debt
B56: Total — financing synergies | J56: =SUM(J53:J55) | M56: =SUM(M53:M55)
B57: Selected run-rate (per basis switch) | H57: =IF($D$5=1,J56,M56)
B58: → Feed to Synergy_Schedule (IDR mm) | H58: =H57*1000
B60: BELOW-THE-LINE — post-tax / one-time, NOT in the run-rate above
A61: F4 | B61: Acquisition-debt tax shield (post-tax NPV) | H61: =D89 | O61: Already after tax → must not be taxed again
A62: F5 | B62: Working-capital release (one-time) | H62: =D118
B63: Subtotal — below-the-line (NPV) | H63: =H61+H62
A65: D. SUPPORTING BUILD-UPS (drivers for C8, R5, R6, F4, F5)
B67: C8 — Capex avoidance
B68: FWA/BTS sites co-located (unit) | D68: 2000 | O68: Same base as C2
B69: Full new-tower capex (IDR bn per tower) | D69: 1.25 | O69: TOWR-3-Statements C22: Rp1,250,000k
B70: % passive/civil portion avoided | D70: 0.2 | O70: Co-location avoids passive/civil only, not a full tower
B71: → Avoided capex — FWA sites (IDR bn) | D71: =D68*D69*D70
B72: Home passes used from TOWR (unit) | D72: =F40 | O72: R2 quantity
B73: Build cost per home pass (IDR mn) | D73: 0.5 | O73: Conservative vs Rp1mn connect capex
B74: → Avoided capex — FTTH (IDR bn) | D74: =D72*D73/1000
B75: TOTAL C8 (NPV, IDR bn) | D75: =D71+D74
B77: F4 — Acquisition-debt tax shield (with debt amortisation)
B78: Acquisition debt (IDR bn) | D78: ='Merger-Model'!L9/1000 | O78: Merger-Model L9
B79: Interest rate | D79: ='Merger-Model'!L11 | O79: Merger-Model L11
B80: Tax rate | D80: ='Merger-Model'!F38 | O80: Merger-Model F38
B81: WACC (discount) | D81: ='Returns Analysis'!B5 | O81: Returns Analysis B5
B82: Amortisation tenor (years) | D82: 10 | O82: Straight-line → shield declines each year
B83: Year | E83: 1 | F83: 2 | G83: 3 | H83: 4 | I83: 5 | J83: 6 | K83: 7 | L83: 8 | M83: 9 | N83: 10
B84: Opening debt | E84: =$D$78*($D$82-E83+1)/$D$82 | F84: =$D$78*($D$82-F83+1)/$D$82 | G84: =$D$78*($D$82-G83+1)/$D$82 | H84: =$D$78*($D$82-H83+1)/$D$82 | I84: =$D$78*($D$82-I83+1)/$D$82 | J84: =$D$78*($D$82-J83+1)/$D$82 | K84: =$D$78*($D$82-K83+1)/$D$82 | L84: =$D$78*($D$82-L83+1)/$D$82 | ... N84: =$D$78*($D$82-N83+1)/$D$82
B85: Interest | E85: =E84*$D$79 | F85: =F84*$D$79 | G85: =G84*$D$79 | H85: =H84*$D$79 | I85: =I84*$D$79 | J85: =J84*$D$79 | K85: =K84*$D$79 | L85: =L84*$D$79 | ... N85: =N84*$D$79
B86: Tax shield | E86: =E85*$D$80 | F86: =F85*$D$80 | G86: =G85*$D$80 | H86: =H85*$D$80 | I86: =I85*$D$80 | J86: =J85*$D$80 | K86: =K85*$D$80 | L86: =L85*$D$80 | ... N86: =N85*$D$80
B87: Discount factor | E87: =1/(1+$D$81)^E83 | F87: =1/(1+$D$81)^F83 | G87: =1/(1+$D$81)^G83 | H87: =1/(1+$D$81)^H83 | I87: =1/(1+$D$81)^I83 | J87: =1/(1+$D$81)^J83 | K87: =1/(1+$D$81)^K83 | L87: =1/(1+$D$81)^L83 | ... N87: =1/(1+$D$81)^N83
B88: PV of shield | E88: =E86*E87 | F88: =F86*F87 | G88: =G86*G87 | H88: =H86*H87 | I88: =I86*I87 | J88: =J86*J87 | K88: =K86*K87 | L88: =L86*L87 | ... N88: =N86*N87
B89: TOTAL F4 (NPV, IDR bn) | D89: =SUM(E88:N88) | O89: Amortising balance → lower & more honest than a flat-balance annuity
B91: R5 — ARPU uplift & churn reduction (existing base)
B92: Existing FTTH subscribers ('000) | D92: ='WIFI 3-Statement Model'!H138 | O92: Surge AR2025: 1.5m STARLITE subs
B93: Current ARPU (Rp'000/month) | D93: ='WIFI 3-Statement Model'!I141
B94: ARPU uplift from bundling (Rp'000/month) | D94: 3 | O94: ≈4.3% of Rp70k ARPU
B95: Annual churn improvement (pp) | D95: 0.01
B96: → Incremental revenue per year (IDR bn) | D96: =D92*D94*12/1000+D92*D95*D93*12/1000
B97: Gross margin — WIFI telecom | D97: ='WIFI 3-Statement Model'!H30/'WIFI 3-Statement Model'!H28
B98: Confidence haircut | D98: 0.6 | O98: Medium
B100: R6 — Advertising inventory scaling
B101: WIFI advertising revenue FY25 (IDR bn) | D101: ='WIFI 3-Statement Model'!H151/1000000 | O101: Rp459.5bn — this is ad REVENUE, not the Rp22bn ad expense
B102: Existing subscriber base ('000) | D102: ='WIFI 3-Statement Model'!H138
B103: → Advertising per subscriber (Rp'000/yr) | D103: =D101/D102*1000
B104: Incremental subscribers from synergy ('000) | D104: =(F40+F41)/1000 | O104: R2 + R3 quantities
B105: → Incremental advertising revenue (IDR bn/yr) | D105: =D104*D103/1000
B106: Advertising contribution margin | D106: 0.7 | O106: Inventory already exists
B107: Confidence haircut | D107: 0.5 | O107: Low-Med
B109: F5 — Working-capital release
B110: Combined revenue (IDR bn) | D110: ='TOWR-3-Statements'!G30/1000000+'WIFI 3-Statement Model'!H28/1000000
B111: Combined COGS (IDR bn) | D111: =-('TOWR-3-Statements'!G31+'TOWR-3-Statements'!G32)/1000000-'WIFI 3-Statement Model'!H29/1000000
B112: WIFI COGS (IDR bn) | D112: =-'WIFI 3-Statement Model'!H29/1000000
B113: Receivable days improvement | D113: 3 | O113: TOWR 87d vs WIFI 50d
...

Sheet Dissynergy
A1: Dissynergy — Data-Anchored Downside (Low / Base / High)
A2: Rp miliar (bn). Tiap item di-anchor ke LK auditan / riset — bukan asumsi bebas. Biru = input · Hijau = link · Hitam = rumus.
A4: Data Anchors (sumber: LK auditan TOWR 2025, Surge AR2025, riset sektor)
A5: Tambahan tenant TOWR 2025 (unit) | B5: 2505 | G5: SMN AR2025: +2.505 tenant (total 60.540)
A6: Pendapatan per tenant (Rp bn/th) | B6: 0.1442 | G6: Rp8.730 bn sewa menara ÷ 60.540 tenant
A7: Margin EBITDA TOWR | B7: 0.82 | G7: TOWR-3-Statements (EBITDA ÷ revenue)
A8: Pendapatan sewa menara (Rp bn) | B8: 8730 | G8: SMN AR2025: Rp8,73 trn = 65,47% dari total
A9: Tenor kontrak rata-rata (tahun) | B9: 11 | G9: SMN AR2025 Catatan 39: sewa 10–13 tahun
A10: Pendapatan WIFI (Rp bn) | B10: 1659 | G10: Surge AR2025 FY25A
A11: Gross margin telco WIFI | B11: 0.729 | G11: WIFI Rev-COGS Detail
A12: Anggaran biaya integrasi (Rp bn) | B12: ='Returns Analysis'!B11 | G12: Link Returns Analysis
A13: SG&A kas WIFI (Rp bn) | B13: 176.7 | G13: Cost Synergy Bottom-Up (ex-iklan & D&A)
A14: Konsentrasi pelanggan TOWR FY25: XLSmart 42% · Indosat 34% · Telkomsel 11% = 87% pendapatan dari 3 operator yang akan bersaing dengan WIFI.
A16: Shared Assumptions
A17: WACC | B17: ='Returns Analysis'!B5
A18: Tax rate | B18: ='Returns Analysis'!B14
A19: (faktor kapitalisasi — tidak lagi dipakai, dissinergi kini lewat schedule) | B19: 10
A20: SKENARIO (1=Low · 2=Base · 3=High) | B20: 2
A22: Dissynergy Items (Rp bn)
A23: Item | B23: Basis | C23: Low | D23: Base | E23: High | F23: AKTIF | G23: Sumber / benchmark
A24: D1 Kehilangan pangsa order tenant BARU | B24: =B5*B6 | C24: 0.1 | D24: 0.15 | E24: 0.2 | F24: =B24*CHOOSE($B$20,C24,D24,E24)*$B$7 | G24: 87% pendapatan dari 3 MNO yang jadi pesaing WIFI; alternatif ada (MTEL 39.593, TBIG 23.892 site)
A25: D2 Konsesi harga saat perpanjangan | B25: =B8/B9 | C25: 0.02 | D25: 0.025 | E25: 0.03 | F25: =B25*CHOOSE($B$20,C25,D25,E25)*$B$7 | G25: Kontrak 10–13 thn → ±1/11 basis jatuh tempo per tahun; preseden ISAT-Hutch 2022
A26: D3 Churn pelanggan pasca-merger | B26: =B10 | C26: 0.02 | D26: 0.035 | E26: 0.05 | F26: =B26*CHOOSE($B$20,C26,D26,E26)*$B$11 | G26: McKinsey: perusahaan merger rata-rata kehilangan 2–5% pelanggan gabungan ⟵ TRANSISI: hanya tahun 1–3, TANPA terminal value (churn pasca-merger bersifat sementara)
A27: D4 Pembengkakan biaya integrasi (sekali) | B27: =B12 | C27: 0.2 | D27: 0.25 | E27: 0.3 | F27: =B27*CHOOSE($B$20,C27,D27,E27) | G27: 59% deal mengalami cost overrun (PMI research)
A28: D5 Atrisi & retensi karyawan kunci (sekali) | B28: =B13 | C28: 0.2 | D28: 0.25 | E28: 0.3 | F28: =B28*CHOOSE($B$20,C28,D28,E28) | G28: Turnover pasca-akuisisi 47% di tahun-1 vs baseline 13%
A29: of which PERMANENT (D1+D2) — structural, carries terminal value | F29: =F24+F25 | G29: D1/D2 = konflik neutral-host: berlangsung selama TOWR memiliki WIFI
A30: Subtotal recurring / tahun (D1–D3) | F30: =SUM(F24:F26)
A31: FEEDS — ke mana dissinergi ini mengalir
A32: D1–D3 recurring → Synergy_Schedule r29 · Returns Analysis r22 · Merger-Model r73 (yr1–3 penuh, yr4+ hanya D1–D2) | F32: =F30
A33: D4–D5 one-time → Returns Analysis value bridge (baris 44) | F33: =F27+F28
A35: Hasil akhir (net value creation all-in) ada di Returns Analysis B43 → | F35: ='Returns Analysis'!B43
A36: Dissinergi kini menyatu di model inti: NPV, IRR, EPS accretion, Football Field, dan M&A_Valuation semua sudah memperhitungkannya.
A37: Perlakuan D3: churn pasca-merger adalah efek TRANSISI (benchmark McKinsey 2–5% terjadi saat integrasi), sehingga tidak diberi terminal value. D1/D2 struktural → perpetuitas.
A46: Sumber
A47: • SMN (TOWR) Annual Report & Laporan Keuangan Auditan 2025 — konsentrasi pelanggan 87%, 36.247 menara / 60.540 tenant, tenor sewa 10–13 thn
A48: • PT Solusi Sinergi Digital (WIFI/Surge) Annual Report 2025 — pendapatan & SG&A
A49: • McKinsey (via Transacted, "Dis-Synergies in M&A") — merger rata-rata kehilangan 2–5% pelanggan gabungan
A50: • PMI Stack, Post-Merger Integration Statistics — 59% deal cost overrun; turnover 47% tahun-1
A51: • Avrist AM, Indonesian Tower Sector — MTEL 39.593 / TOWR 35.506 / TBIG 23.892 site; preseden merger ISAT-Hutch 2022
A52: • Light Reading — konflik kepentingan towerco terintegrasi vertikal (Orange/Totem–Iliad; Vodafone/Vantage–1&1)
A54: Legend: | B54: Biru = input | C54: Hijau = link | F54: Hitam = rumus

Sheet Financial & Dupont Analysis
B2: TOWR Financial Ratio | D2: 2021 | E2: 2022 | F2: 2023 | G2: 2024 | H2: 2025 | J2: DuPont Analysis | K2: 2021 | L2: 2022 | M2: 2023 | N2: 2024 | O2: 2025 | Q2: M&A Operating KPI/Peer Benchmark (latest disclosed) | R2: TOWR | S2: WIFI | T2: TBIG | U2: Source/Period
B3: Growth & Scale | C3: Revenue | D3: ='SOURCE TOWR Income Statemen (2)'!C21/1000000 | E3: ='SOURCE TOWR Income Statemen (2)'!D21/1000000 | F3: ='SOURCE TOWR Income Statemen (2)'!E21/1000000 | G3: ='SOURCE TOWR Income Statemen (2)'!F21/1000000 | H3: ='SOURCE TOWR Income Statemen (2)'!G21/1000000 | J3: NPM | K3: ='SOURCE TOWR Income Statemen (2)'!C198/'SOURCE TOWR Income Statemen (2)'!C21 | L3: ='SOURCE TOWR Income Statemen (2)'!D198/'SOURCE TOWR Income Statemen (2)'!D21 | M3: ='SOURCE TOWR Income Statemen (2)'!E198/'SOURCE TOWR Income Statemen (2)'!E21 | N3: ='SOURCE TOWR Income Statemen (2)'!F198/'SOURCE TOWR Income Statemen (2)'!F21 | O3: ='SOURCE TOWR Income Statemen (2)'!G198/'SOURCE TOWR Income Statemen (2)'!G21 | Q3: Tower/network scale | R3: 36,049 tower sites + ~170,500 km fiber | S3: 2.5m HomePass; 1.5m HomeConnect | T3: 24,321 sites; 24,212 towers + 109 DAS | U3: TOWR 3Q25/WIFI FY25/TBIG FY25
C4: Revenue Growth | E4: =E3/D3-1 | F4: =F3/E3-1 | G4: =G3/F3-1 | H4: =H3/G3-1 | J4: Asset Turnover | K4: ='SOURCE TOWR Income Statemen (2)'!C21/('SOURCE TOWR Balance Sheet (2)'!C167) | L4: ='SOURCE TOWR Income Statemen (2)'!D21/('SOURCE TOWR Balance Sheet (2)'!D167) | M4: ='SOURCE TOWR Income Statemen (2)'!E21/('SOURCE TOWR Balance Sheet (2)'!E167) | N4: ='SOURCE TOWR Income Statemen (2)'!F21/('SOURCE TOWR Balance Sheet (2)'!F167) | O4: ='SOURCE TOWR Income Statemen (2)'!G21/('SOURCE TOWR Balance Sheet (2)'!G167) | Q4: Tenancy/utilization | R4: ~1.64x tenancy (FY24); latest company disclosure | S4: ~60% FTTH take-up | T4: 1.73x tenancy | U4: Official company disclosures
C5: EBITDA | D5: ='SOURCE TOWR Income Statemen (2)'!C277/1000000 | E5: ='SOURCE TOWR Income Statemen (2)'!D277/1000000 | F5: ='SOURCE TOWR Income Statemen (2)'!E277/1000000 | G5: ='SOURCE TOWR Income Statemen (2)'!F277/1000000 | H5: ='SOURCE TOWR Income Statemen (2)'!G277/1000000 | J5: Equity Multiplier | K5: ='SOURCE TOWR Balance Sheet (2)'!C167/('SOURCE TOWR Balance Sheet (2)'!C271) | L5: ='SOURCE TOWR Balance Sheet (2)'!D167/('SOURCE TOWR Balance Sheet (2)'!D271) | M5: ='SOURCE TOWR Balance Sheet (2)'!E167/('SOURCE TOWR Balance Sheet (2)'!E271) | N5: ='SOURCE TOWR Balance Sheet (2)'!F167/('SOURCE TOWR Balance Sheet (2)'!F271) | O5: ='SOURCE TOWR Balance Sheet (2)'!G167/('SOURCE TOWR Balance Sheet (2)'!G271) | Q5: Fiber/connectivity | R5: ~170,500 km fiber | S5: FTTH revenue Rp541.06bn | T5: N/A | U5: Official company disclosures
C6: EBITDA Growth | E6: =E5/D5-1 | F6: =F5/E5-1 | G6: =G5/F5-1 | H6: =H5/G5-1 | J6: ROE | K6: =K3*K4*K5 | L6: =L3*L4*L5 | M6: =M3*M4*M5 | N6: =N3*N4*N5 | O6: =O3*O4*O5 | Q6: M&A interpretation | R6: Large tower + fiber scale; recurring contracted infrastructure | S6: High-growth fiber connectivity platform with strong take-up | T6: Domestic tower peer benchmark | U6: Analyst interpretation
C7: EBITDA Margin | D7: =D5/D3 | E7: =E5/E3 | F7: =F5/F3 | G7: =G5/G3 | H7: =H5/H3 | Q7: TOWR source URL | R7: https://www.ptsmn.co.id/about-us/company-profile | U7: TOWR 3Q25 company profile
C8: Net Income Margin | D8: ='SOURCE TOWR Income Statemen (2)'!C198/'SOURCE TOWR Income Statemen (2)'!C21 | E8: ='SOURCE TOWR Income Statemen (2)'!D198/'SOURCE TOWR Income Statemen (2)'!D21 | F8: ='SOURCE TOWR Income Statemen (2)'!E198/'SOURCE TOWR Income Statemen (2)'!E21 | G8: ='SOURCE TOWR Income Statemen (2)'!F198/'SOURCE TOWR Income Statemen (2)'!F21 | H8: ='SOURCE TOWR Income Statemen (2)'!G198/'SOURCE TOWR Income Statemen (2)'!G21 | Q8: WIFI source URL | R8: https://surge.co.id/pdf/Investor%20Relations/Annual%20Report%202025/Surge-AR_2025_020626.pdf | U8: WIFI FY2025 Annual Report
B9: Cash Flow & Capital Intensity | C9: D&A | D9: ='SOURCE TOWR Income Statemen (2)'!C295/1000000 | E9: ='SOURCE TOWR Income Statemen (2)'!D295/1000000 | F9: ='SOURCE TOWR Income Statemen (2)'!E295/1000000 | G9: ='SOURCE TOWR Income Statemen (2)'!F295/1000000 | H9: ='SOURCE TOWR Income Statemen (2)'!G295/1000000 | Q9: TBIG source URL | R9: https://www.tower-bersama.com/en/news/pt-tower-bersama-infrastructuretbk-tbig-announces-its-full-year-2025-financial-performance | U9: TBIG FY2025 official release
C10: CapEx | D10: =MAX(0,('SOURCE TOWR Balance Sheet (2)'!C71-'SOURCE TOWR Balance Sheet (2)'!B71)/1000000+D9) | E10: =MAX(0,('SOURCE TOWR Balance Sheet (2)'!D71-'SOURCE TOWR Balance Sheet (2)'!C71)/1000000+E9) | F10: =MAX(0,('SOURCE TOWR Balance Sheet (2)'!E71-'SOURCE TOWR Balance Sheet (2)'!D71)/1000000+F9) | G10: =MAX(0,('SOURCE TOWR Balance Sheet (2)'!F71-'SOURCE TOWR Balance Sheet (2)'!E71)/1000000+G9) | H10: =MAX(0,('SOURCE TOWR Balance Sheet (2)'!G71-'SOURCE TOWR Balance Sheet (2)'!F71)/1000000+H9)
C11: CapEx/Revenue | D11: =D10/D3 | E11: =E10/E3 | F11: =F10/F3 | G11: =G10/G3 | H11: =H10/H3
C12: FCF Proxy | D12: =D5-D10 | E12: =E5-E10 | F12: =F5-F10 | G12: =G5-G10 | H12: =H5-H10
C13: FCF Margin | D13: =D12/D3 | E13: =E12/E3 | F13: =F12/F3 | G13: =G12/G3 | H13: =H12/H3
C14: FCF/EBITDA | D14: =D12/D5 | E14: =E12/E5 | F14: =F12/F5 | G14: =G12/G5 | H14: =H12/H5
B15: Leverage & Financial Capacity | C15: Total Debt | D15: =('SOURCE TOWR Balance Sheet (2)'!C172+'SOURCE TOWR Balance Sheet (2)'!C198)/1000000 | E15: =('SOURCE TOWR Balance Sheet (2)'!D172+'SOURCE TOWR Balance Sheet (2)'!D198)/1000000 | F15: =('SOURCE TOWR Balance Sheet (2)'!E172+'SOURCE TOWR Balance Sheet (2)'!E198)/1000000 | G15: =('SOURCE TOWR Balance Sheet (2)'!F172+'SOURCE TOWR Balance Sheet (2)'!F198)/1000000 | H15: =('SOURCE TOWR Balance Sheet (2)'!G172+'SOURCE TOWR Balance Sheet (2)'!G198)/1000000
C16: Cash | D16: ='SOURCE TOWR Balance Sheet (2)'!C21/1000000 | E16: ='SOURCE TOWR Balance Sheet (2)'!D21/1000000 | F16: ='SOURCE TOWR Balance Sheet (2)'!E21/1000000 | G16: ='SOURCE TOWR Balance Sheet (2)'!F21/1000000 | H16: ='SOURCE TOWR Balance Sheet (2)'!G21/1000000
C17: Net Debt/(Net Cash) | D17: =D15-D16 | E17: =E15-E16 | F17: =F15-F16 | G17: =G15-G16 | H17: =H15-H16
C18: Debt/Equity | D18: =D15/('SOURCE TOWR Balance Sheet (2)'!C271/1000000) | E18: =E15/('SOURCE TOWR Balance Sheet (2)'!D271/1000000) | F18: =F15/('SOURCE TOWR Balance Sheet (2)'!E271/1000000) | G18: =G15/('SOURCE TOWR Balance Sheet (2)'!F271/1000000) | H18: =H15/('SOURCE TOWR Balance Sheet (2)'!G271/1000000)
C19: Net Debt/EBITDA | D19: =D17/D5 | E19: =E17/E5 | F19: =F17/F5 | G19: =G17/G5 | H19: =H17/H5
C20: EBITDA/Interest Expense | D20: =D5/ABS('SOURCE TOWR Income Statemen (2)'!C93/1000000) | E20: =E5/ABS('SOURCE TOWR Income Statemen (2)'!D93/1000000) | F20: =F5/ABS('SOURCE TOWR Income Statemen (2)'!E93/1000000) | G20: =G5/ABS('SOURCE TOWR Income Statemen (2)'!F93/1000000) | H20: =H5/ABS('SOURCE TOWR Income Statemen (2)'!G93/1000000)
C21: Current Ratio | D21: ='SOURCE TOWR Balance Sheet (2)'!C53/('SOURCE TOWR Balance Sheet (2)'!C193) | E21: ='SOURCE TOWR Balance Sheet (2)'!D53/('SOURCE TOWR Balance Sheet (2)'!D193) | F21: ='SOURCE TOWR Balance Sheet (2)'!E53/('SOURCE TOWR Balance Sheet (2)'!E193) | G21: ='SOURCE TOWR Balance Sheet (2)'!F53/('SOURCE TOWR Balance Sheet (2)'!F193) | H21: ='SOURCE TOWR Balance Sheet (2)'!G53/('SOURCE TOWR Balance Sheet (2)'!G193)
C22: Cash Ratio | D22: =('SOURCE TOWR Balance Sheet (2)'!C21)/('SOURCE TOWR Balance Sheet (2)'!C193) | E22: =('SOURCE TOWR Balance Sheet (2)'!D21)/('SOURCE TOWR Balance Sheet (2)'!D193) | F22: =('SOURCE TOWR Balance Sheet (2)'!E21)/('SOURCE TOWR Balance Sheet (2)'!E193) | G22: =('SOURCE TOWR Balance Sheet (2)'!F21)/('SOURCE TOWR Balance Sheet (2)'!F193) | H22: =('SOURCE TOWR Balance Sheet (2)'!G21)/('SOURCE TOWR Balance Sheet (2)'!G193)
B23: Telecom Infrastructure Operating Drivers | C23: Network/Asset Scale | D23: 28702 | E23: 29799 | F23: 30558 | G23: 35400 | H23: 36049
C24: Customer/Tenant Scale | D24: 53975 | E24: 53967 | F24: 54284 | G24: 58035 | H24: 58035
C25: Utilization | D25: 1.880531 | E25: 1.8110339 | F25: 1.7764252 | G25: 1.6394068 | H25: 1.6098921
C26: Primary Connectivity Revenue | D26: 7101273000 | E26: 8605930000 | F26: 8346311000 | G26: 8523045000 | H26: 8725566000
C27: Asset/Customer Growth | D27: - | E27: =IFERROR(E23/D23-1,0) | F27: =IFERROR(F23/E23-1,0) | G27: =IFERROR(G23/F23-1,0) | H27: =IFERROR(H23/G23-1,0)
C28: Unit Economics | D28: =IFERROR(D26/D23/1000,0) | E28: =IFERROR(E26/E23/1000,0) | F28: =IFERROR(F26/F23/1000,0) | G28: =IFERROR(G26/G23/1000,0) | H28: =IFERROR(H26/H23/1000,0)
C29: Backbone/Network Scale | D29: 70465 | E29: 88208 | F29: 97994 | G29: 170000 | H29: 170500
B33: WIFI Financial Ratio | D33: 2021 | E33: 2022 | F33: 2023 | G33: 2024 | H33: 2025 | J33: DuPont Analysis | K33: 2021 | L33: 2022 | M33: 2023 | N33: 2024 | O33: 2025
B34: Growth & Scale | C34: Revenue | D34: ='SOURCE WIFI Income Statemen (2)'!B21/1000000 | E34: ='SOURCE WIFI Income Statemen (2)'!C21/1000000 | F34: ='SOURCE WIFI Income Statemen (2)'!D21/1000000 | G34: ='SOURCE WIFI Income Statemen (2)'!E21/1000000 | H34: ='SOURCE WIFI Income Statemen (2)'!F21/1000000 | J34: NPM | K34: ='SOURCE WIFI Income Statemen (2)'!B198/'SOURCE WIFI Income Statemen (2)'!B21 | L34: ='SOURCE WIFI Income Statemen (2)'!C198/'SOURCE WIFI Income Statemen (2)'!C21 | M34: ='SOURCE WIFI Income Statemen (2)'!D198/'SOURCE WIFI Income Statemen (2)'!D21 | N34: ='SOURCE WIFI Income Statemen (2)'!E198/'SOURCE WIFI Income Statemen (2)'!E21 | O34: ='SOURCE WIFI Income Statemen (2)'!F198/'SOURCE WIFI Income Statemen (2)'!F21
C35: Revenue Growth | E35: =E34/D34-1 | F35: =F34/E34-1 | G35: =G34/F34-1 | H35: =H34/G34-1 | J35: Asset Turnover | K35: ='SOURCE WIFI Income Statemen (2)'!B21/('SOURCE WIFI Balance Sheet (2)'!B167) | L35: ='SOURCE WIFI Income Statemen (2)'!C21/('SOURCE WIFI Balance Sheet (2)'!C167) | M35: ='SOURCE WIFI Income Statemen (2)'!D21/('SOURCE WIFI Balance Sheet (2)'!D167) | N35: ='SOURCE WIFI Income Statemen (2)'!E21/('SOURCE WIFI Balance Sheet (2)'!E167) | O35: ='SOURCE WIFI Income Statemen (2)'!F21/('SOURCE WIFI Balance Sheet (2)'!F167)
C36: EBITDA | D36: ='SOURCE WIFI Income Statemen (2)'!B277/1000000 | E36: ='SOURCE WIFI Income Statemen (2)'!C277/1000000 | F36: ='SOURCE WIFI Income Statemen (2)'!D277/1000000 | G36: ='SOURCE WIFI Income Statemen (2)'!E277/1000000 | H36: ='SOURCE WIFI Income Statemen (2)'!F277/1000000 | J36: Equity Multiplier | K36: ='SOURCE WIFI Balance Sheet (2)'!B167/('SOURCE WIFI Balance Sheet (2)'!B271) | L36: ='SOURCE WIFI Balance Sheet (2)'!C167/('SOURCE WIFI Balance Sheet (2)'!C271) | M36: ='SOURCE WIFI Balance Sheet (2)'!D167/('SOURCE WIFI Balance Sheet (2)'!D271) | N36: ='SOURCE WIFI Balance Sheet (2)'!E167/('SOURCE WIFI Balance Sheet (2)'!E271) | O36: ='SOURCE WIFI Balance Sheet (2)'!F167/('SOURCE WIFI Balance Sheet (2)'!F271)
C37: EBITDA Growth | E37: =E36/D36-1 | F37: =F36/E36-1 | G37: =G36/F36-1 | H37: =H36/G36-1 | J37: ROE | K37: =K34*K35*K36 | L37: =L34*L35*L36 | M37: =M34*M35*M36 | N37: =N34*N35*N36 | O37: =O34*O35*O36
C38: EBITDA Margin | D38: =D36/D34 | E38: =E36/E34 | F38: =F36/F34 | G38: =G36/G34 | H38: =H36/H34
C39: Net Income Margin | D39: ='SOURCE WIFI Income Statemen (2)'!B198/'SOURCE WIFI Income Statemen (2)'!B21 | E39: ='SOURCE WIFI Income Statemen (2)'!C198/'SOURCE WIFI Income Statemen (2)'!C21 | F39: ='SOURCE WIFI Income Statemen (2)'!D198/'SOURCE WIFI Income Statemen (2)'!D21 | G39: ='SOURCE WIFI Income Statemen (2)'!E198/'SOURCE WIFI Income Statemen (2)'!E21 | H39: ='SOURCE WIFI Income Statemen (2)'!F198/'SOURCE WIFI Income Statemen (2)'!F21
B40: Cash Flow & Capital Intensity | C40: D&A | D40: ='SOURCE WIFI Income Statemen (2)'!B295/1000000 | E40: ='SOURCE WIFI Income Statemen (2)'!C295/1000000 | F40: ='SOURCE WIFI Income Statemen (2)'!D295/1000000 | G40: ='SOURCE WIFI Income Statemen (2)'!E295/1000000 | H40: ='SOURCE WIFI Income Statemen (2)'!F295/1000000
C41: CapEx | E41: =MAX(0,('SOURCE WIFI Balance Sheet (2)'!C71-'SOURCE WIFI Balance Sheet (2)'!B71)/1000000+E40) | F41: =MAX(0,('SOURCE WIFI Balance Sheet (2)'!D71-'SOURCE WIFI Balance Sheet (2)'!C71)/1000000+F40) | G41: =MAX(0,('SOURCE WIFI Balance Sheet (2)'!E71-'SOURCE WIFI Balance Sheet (2)'!D71)/1000000+G40) | H41: =MAX(0,('SOURCE WIFI Balance Sheet (2)'!F71-'SOURCE WIFI Balance Sheet (2)'!E71)/1000000+H40)
C42: CapEx/Revenue | E42: =E41/E34 | F42: =F41/F34 | G42: =G41/G34 | H42: =H41/H34
C43: FCF Proxy | E43: =E36-E41 | F43: =F36-F41 | G43: =G36-G41 | H43: =H36-H41
C44: FCF Margin | E44: =E43/E34 | F44: =F43/F34 | G44: =G43/G34 | H44: =H43/H34
C45: FCF/EBITDA | E45: =E43/E36 | F45: =F43/F36 | G45: =G43/G36 | H45: =H43/H36
B46: Leverage & Financial Capacity | C46: Total Debt | D46: =('SOURCE WIFI Balance Sheet (2)'!B172+'SOURCE WIFI Balance Sheet (2)'!B198)/1000000 | E46: =('SOURCE WIFI Balance Sheet (2)'!C172+'SOURCE WIFI Balance Sheet (2)'!C198)/1000000 | F46: =('SOURCE WIFI Balance Sheet (2)'!D172+'SOURCE WIFI Balance Sheet (2)'!D198)/1000000 | G46: =('SOURCE WIFI Balance Sheet (2)'!E172+'SOURCE WIFI Balance Sheet (2)'!E198)/1000000 | H46: =('SOURCE WIFI Balance Sheet (2)'!F172+'SOURCE WIFI Balance Sheet (2)'!F198)/1000000
C47: Cash | D47: ='SOURCE WIFI Balance Sheet (2)'!B21/1000000 | E47: ='SOURCE WIFI Balance Sheet (2)'!C21/1000000 | F47: ='SOURCE WIFI Balance Sheet (2)'!D21/1000000 | G47: ='SOURCE WIFI Balance Sheet (2)'!E21/1000000 | H47: ='SOURCE WIFI Balance Sheet (2)'!F21/1000000
C48: Net Debt/(Net Cash) | D48: =D46-D47 | E48: =E46-E47 | F48: =F46-F47 | G48: =G46-G47 | H48: =H46-H47
C49: Debt/Equity | D49: =D46/('SOURCE WIFI Balance Sheet (2)'!B271/1000000) | E49: =E46/('SOURCE WIFI Balance Sheet (2)'!C271/1000000) | F49: =F46/('SOURCE WIFI Balance Sheet (2)'!D271/1000000) | G49: =G46/('SOURCE WIFI Balance Sheet (2)'!E271/1000000) | H49: =H46/('SOURCE WIFI Balance Sheet (2)'!F271/1000000)
C50: Net Debt/EBITDA | D50: =D48/D36 | E50: =E48/E36 | F50: =F48/F36 | G50: =G48/G36 | H50: =H48/H36
C51: EBITDA/Interest Expense | D51: =D36/ABS('SOURCE WIFI Income Statemen (2)'!B93/1000000) | E51: =E36/ABS('SOURCE WIFI Income Statemen (2)'!C93/1000000) | F51: =F36/ABS('SOURCE WIFI Income Statemen (2)'!D93/1000000) | G51: =G36/ABS('SOURCE WIFI Income Statemen (2)'!E93/1000000) | H51: =H36/ABS('SOURCE WIFI Income Statemen (2)'!F93/1000000)
C52: Current Ratio | D52: ='SOURCE WIFI Balance Sheet (2)'!B53/('SOURCE WIFI Balance Sheet (2)'!B193) | E52: ='SOURCE WIFI Balance Sheet (2)'!C53/('SOURCE WIFI Balance Sheet (2)'!C193) | F52: ='SOURCE WIFI Balance Sheet (2)'!D53/('SOURCE WIFI Balance Sheet (2)'!D193) | G52: ='SOURCE WIFI Balance Sheet (2)'!E53/('SOURCE WIFI Balance Sheet (2)'!E193) | H52: ='SOURCE WIFI Balance Sheet (2)'!F53/('SOURCE WIFI Balance Sheet (2)'!F193)
C53: Cash Ratio | D53: =('SOURCE WIFI Balance Sheet (2)'!B21)/('SOURCE WIFI Balance Sheet (2)'!B193) | E53: =('SOURCE WIFI Balance Sheet (2)'!C21)/('SOURCE WIFI Balance Sheet (2)'!C193) | F53: =('SOURCE WIFI Balance Sheet (2)'!D21)/('SOURCE WIFI Balance Sheet (2)'!D193) | G53: =('SOURCE WIFI Balance Sheet (2)'!E21)/('SOURCE WIFI Balance Sheet (2)'!E193) | H53: =('SOURCE WIFI Balance Sheet (2)'!F21)/('SOURCE WIFI Balance Sheet (2)'!F193)
B54: Telecom Infrastructure Operating Drivers | C54: Network/Asset Scale | D54: 0 | E54: 0 | F54: 0 | G54: 200000 | H54: 2500000
C55: Customer/Tenant Scale | D55: 0 | E55: 0 | F55: 0 | G55: - | H55: 1500000
C56: Utilization | D56: - | E56: - | F56: - | G56: - | H56: 0.6
C57: Primary Connectivity Revenue | D57: ='SOURCE WIFI Income Statemen (2)'!B21 | E57: ='SOURCE WIFI Income Statemen (2)'!C21 | F57: ='SOURCE WIFI Income Statemen (2)'!D21 | G57: ='SOURCE WIFI Income Statemen (2)'!E21 | H57: ='SOURCE WIFI Income Statemen (2)'!F21
C58: Asset/Customer Growth | D58: 0 | E58: 0 | F58: 0 | G58: - | H58: 541060
C59: Unit Economics | D59: - | E59: - | F59: - | G59: - | H59: 360706.67
C60: Backbone/Network Scale | D60: - | E60: - | F60: 6927 | G60: 6927 | H60: 7357

Sheet TOWR WIFI-Comparable Preced (2)
C2: COMPARABLE PEER ANALYSIS (TOWR) | K2: Group 1 - Indonesian Tower Precedent Transactions: Benchmarks for TOWR
C3: Ticker | D3: Company | E3: EV/EBITDA (TTM) | F3: P/BV (TTM) | G3: PE RATIO (TTM) | K3: Year | L3: Target | M3: Acquiror | N3: EV/EBITDA (Rp Billion) | O3: EV/Tower | P3: EV/Tenant
C4: Indonesia Peers | K4: National Transaction
C5: MTEL.IJ | D5: PT Dayamitra Telekomunikasi Tbk (Mitratel) | E5: 8.6 | F5: 1.1 | G5: 16.5 | J5: 1 | K5: 2021 | L5: Solusi Tunas Pratama (SUPR) 94.03% | M5: Protelindo (TOWR) | N5: =17800/1900 | O5: =17800/6780 | P5: =17800/12500
C6: TBIG.IJ | D6: PT Tower Bersama Infrastructure Tbk | E6: 11.40 x | F6: 2.5 | G6: 22.1 | J6: 2 | K6: 2024 | L6: Inti Bangun Sejahtera (IBST) 90.11% | M6: iForte (TOWR) | N6: 8 | O6: =3800/3383 | P6: =3800/5791
C7: BALI.IJ | D7: PT Bali Towerindo Sentra Tbk | E7: 10.4 | F7: 2 | G7: 27.80 x | J7: 3 | K7: 2020 | L7: 3000 unit of IBST's Tower | M7: TBIG | N7: =3970/481 | O7: =3970/3000 | P7: 1.32
C8: GHON.IJ | D8: PT Gihon Telekomunikasi Indonesia Tbk | E8: 11.40 x | F8: 1.3 | G8: 12.8 | J8: 4 | K8: 2021 | L8: 6000 unit of Telkomsel's Tower | M8: Mitratel (MTEL) | N8: 13.4 | O8: =10280/6000 | P8: 1.59
C9: Regional Peers | K9: International Transaction
C10: 788 HK | D10: China Tower Corporation Limited | E10: 4.5 | F10: 0.7 | G10: 10.3 | J10: 5 | K10: 2024 | L10: IHS Kuwait Tower | M10: Zain | N10: 14.2 | O10: =3700/2345 | P10: NA
C11: INDUSTOW IN | D11: Indus Towers Ltd | E11: 7.4 | F11: 2.4 | G11: 13.6 | K11: Quartile 1 | N11: =_xlfn.QUARTILE.INC(N5:N10, 1) | O11: =_xlfn.QUARTILE.INC(O5:O10, 1) | P11: =_xlfn.QUARTILE.INC(P5:P10, 1)
C12: Quartile 1 - Worst Case | E12: =_xlfn.QUARTILE.INC(E5:E11, 1) | F12: =_xlfn.QUARTILE.INC(F5:F11, 1) | G12: =_xlfn.QUARTILE.INC(G5:G11, 1) | K12: Median | N12: =MEDIAN(N5:N10) | O12: =MEDIAN(O5:O10) | P12: =MEDIAN(P5:P10)
C13: Median - Base Case | E13: =MEDIAN(E5:E11) | F13: =MEDIAN(F5:F11) | G13: =MEDIAN(G5:G11) | K13: Quartile 3 | N13: =_xlfn.QUARTILE.EXC(N5:N10, 3) | O13: =_xlfn.QUARTILE.EXC(O5:O10, 3) | P13: =_xlfn.QUARTILE.INC(P5:P10, 3)
C14: Quartile 3 - Best Case | E14: =_xlfn.QUARTILE.INC(E5:E11, 3) | F14: =_xlfn.QUARTILE.INC(F5:F11, 3) | G14: =_xlfn.QUARTILE.INC(G5:G11, 3) | K14: Source:
C15: Mean | E15: =_xlfn.QUARTILE.INC(E5:E11, 3) | F15: =_xlfn.QUARTILE.INC(F5:F11, 3) | G15: =_xlfn.QUARTILE.INC(G5:G11, 3) | K15: 1. https://market.bisnis.com/read/20211005/189/1450717/sukses-akuisisi-supr-saham-sarana-menara-towr-menuju-rp1540
C16: TOWR | E16: =E29/E25 | F16: =E21/(E24/E27) | G16: =E21/(E23/E27) | K16: 2.https://samuel.co.id/news-events-ssi/towr-kuatkan-posisi-dengan-akuisisi-ibst/
C17: Implied Share Price - Worst Case | E17: =(($E$25*E12)-$E$22)/$E$27 | F17: =F12*$E$32 | G17: =G12*$E$31 | K17: 3.https://investor.id/market-and-corporate/242971/tower-bersama-segera-akuisisi-menara-rp-397-triliun
C18: Implied Share Price - Base Case | E18: =(($E$25*E13)-$E$22)/$E$27 | F18: =F13*$E$32 | G18: =G13*$E$31 | K18: 4.https://www.indopremier.com/ipotnews/newsDetail.php?jdl=Mitratel_(MTEL)_bakal_Akuisisi_Menara_Telekomunikasi_Rp_9_Triliun&news_id=394832&group_news=RESEARCHNEWS&taging_subtype=PG002&name=&search=y_general&q=,&halaman=1
C19: Implied Share Price - Best Case | E19: =(($E$25*E14)-$E$22)/$E$27 | F19: =F14*$E$32 | G19: =G14*$E$31 | K19: 5.https://www.fticonsulting.com/about/newsroom/press-releases/fti-capital-advisors-supports-zain-group-on-acquisition-of-the-ihs-tower-portfolio-in-kuwait
C21: Price/Share - TOWR (21 Agt) | E21: 434 | K21: Group 2. Indonesian Fiber and Broadband Precedent Transactions: Benchmarks for WIFI
C22: Net Debt | E22: 44509580000000 | K22: Year | L22: Target | M22: Acquiror | N22: EV/EBITDA (Rp Billion) | O22: EV/Homepass (Rp Million)
C23: Net Profit TOWR | E23: 3678316000000 | K23: National Transaction
C24: Book Value TOWR | E24: 26972415000000 | J24: 1 | K24: 2022 | L24: Link Net | M24: Axiata dan XL Axiata | N24: =13210/1870 | O24: =13210/2800
C25: EBITDA TOWR | E25: 10924099000000 | J25: 2 | K25: 2024 | L25: PT Ultra Mandiri Telekomunikasi (UMT) | M25: Mitratel (MTEL) | N25: 7.7 | O25: NA
C26: Revenue TOWR | E26: 13327907000000 | K26: International Transaction
C27: Shares Outstanding | E27: =58272885109 | J27: 3 | K27: 2024 | L27: Frontier Communications | M27: Verizon | N27: 8.5 | O27: 14.2
C28: Market Cap TOWR | E28: =E27*E21 | J28: 4 | K28: 2025 | L28: Quantum Fiber (Lumen) | M28: AT&T | N28: NA | O28: 25.4
C29: Enterprise Value TOWR | E29: =E28+E22 | K29: Quartile 1 | N29: =_xlfn.QUARTILE.INC(N24:N28, 1) | O29: =_xlfn.QUARTILE.INC(O24:O28, 1)
K30: Median | N30: =MEDIAN(N24:N28) | O30: =MEDIAN(O24:O28)
C31: EPS TOWR | E31: =E23/E27 | K31: Quartile 3 | N31: =_xlfn.QUARTILE.EXC(N24:N28, 3) | O31: =_xlfn.QUARTILE.EXC(O24:O28, 3)
C32: BVPS TOWR | E32: =E24/E27 | K32: Implied Share Price - Worst Case | N32: =(($E$61*N29)-$E$58)/$E$63 | O32: =((O29*M54*1000000)-M46)/M51
C33: EBITDA per Share | E33: =E25/E27 | K33: Implied Share Price - Base Case | N33: =(($E$61*N30)-$E$58)/$E$63 | O33: =((O30*M54*1000000)-M46)/M51
C34: *in Rupiah | K34: Implied Share Price - Best Case | N34: =(($E$61*N31)-$E$58)/$E$63 | O34: =((O31*M54*1000000)-M46)/M51
C37: COMPARABLE PEER ANALYSIS (WIFI)
C38: Ticker | D38: Company | E38: EV/EBITDA (TTM) | F38: P/BV (TTM) | G38: PE RATIO (TTM)
C39: Indonesia Peers | K39: Source:
C40: LINK.JK | D40: PT Link Net Tbk | E40: 4.9 | F40: 1.4 | G40: -2.8 x | K40: 1.https://www.cnbcindonesia.com/market/20220623101848-17-349579/tok-axiata-dan-xl--excl--resmi-caplok-link-net-dari-lippo
C41: DATA.JK | D41: PT Remala Abadi Tbk | E41: 12.9 | F41: 6.40 x | G41: 20.8 | K41: 2. https://www.cnbcindonesia.com/market/20241206112118-17-593886/caplok-bisnis-fiber-ptpp-rp650-m-saham-mitratel-ditarget-segini
C42: INET | D42: PT Sinergi Inti Andalan Prima Tbk | E42: 64.4 | F42: 1.9 | G42: 189.4 x | K42: 3.https://www.sec.gov/Archives/edgar/data/20520/000110465924111034/tm2426760d1_ex99-2.htm
C43: EDGE | D43: PT Jasnita Telekomindo Tbk | E43: 28.5 | F43: 5.4 | G43: 159.4 x | K43: 4.https://ir.lumen.com/news/news-details/2026/Lumen-Completes-Sale-of-Consumer-Fiber-to-the-Home-Business-to-ATT/default.aspx
C44: Regional Peers
C45: CNVRG PM | D45: Converage ICT | E45: 3.8 | F45: 1.1 | G45: 6.2 | K45: Price/Share - TOWR (21 Agt) | M45: =E57
C46: NETLINK SP | D46: NetLink NBN Trust | E46: 16.4 | F46: 1.7 | G46: 45.8 | K46: Net Debt | M46: =-565153097.16*1000
C47: TDC MK | D47: TIME dotCom | E47: 12.7 | F47: 3.9 | G47: 25.5 | K47: Net Profit WIFI | M47: =E59
C48: Quartile 1 - Worst Case | E48: =_xlfn.QUARTILE.INC(E40:E47, 1) | F48: =_xlfn.QUARTILE.INC(F40:F47, 1) | G48: =_xlfn.QUARTILE.INC(G40:G47, 1) | K48: Book Value WIFI | M48: =E60
C49: Median - Base Case | E49: =MEDIAN(E40:E47) | F49: =MEDIAN(F40:F47) | G49: =MEDIAN(G40:G47) | K49: EBITDA WIFI | M49: =E61
C50: Quartile 3 - Best Case | E50: =_xlfn.QUARTILE.INC(E40:E47, 3) | F50: =_xlfn.QUARTILE.INC(F40:F47, 3) | G50: =_xlfn.QUARTILE.INC(G40:G47, 3) | K50: Revenue WIFI | M50: =E62
C51: Mean | E51: =_xlfn.QUARTILE.INC(E40:E47, 3) | F51: =_xlfn.QUARTILE.INC(F40:F47, 3) | G51: =_xlfn.QUARTILE.INC(G40:G47, 3) | K51: Shares Outstanding | M51: =E63
C52: WIFI | E52: =E65/E61 | F52: =E57/(E60/E63) | G52: =E57/(E59/E63) | K52: Market Cap WIFI | M52: =E64
C53: Implied Share Price - Worst Case | E53: =(($E$61*E48)-$E$58)/$E$63 | F53: =F48*$E$68 | G53: =G48*$E$67 | K53: Enterprise Value WIFI | M53: =E65
C54: Implied Share Price - Base Case | E54: =(($E$61*E49)-$E$58)/$E$63 | F54: =F49*$E$68 | G54: =G49*$E$67 | K54: Homepass WIFI | M54: 2500000
C55: Implied Share Price - Best Case | E55: =(($E$61*E50)-$E$58)/$E$63 | F55: =F50*$E$68 | G55: =G50*$E$67 | K55: EPS WIFI | M55: =E67
K56: BVPS WIFI | M56: =E68
C57: Price/Share - TOWR (21 Agt) | E57: 2090 | K57: EBITDA per Share | M57: =E69
C58: Net Debt | E58: =-565153097.16*1000
C59: Net Profit WIFI | E59: =408551231.77*1000
C60: Book Value WIFI | E60: =7299442709.11*1000
C61: EBITDA WIFI | E61: =1106232966.57*1000
C62: Revenue WIFI | E62: =1659396069.86*1000
C63: Shares Outstanding | E63: =5308549015
C64: Market Cap WIFI | E64: =E63*E57
C65: Enterprise Value WIFI | E65: =E64-E58
C67: EPS WIFI | E67: =E59/E63
C68: BVPS WIFI | E68: =E60/E63
C69: EBITDA per Share | E69: =E61/E63
C70: *in Rupiah

Sheet TOWR-3-Statements
A1: TOWR | Financial Model | C1: Historical Period | H1: Forecast Period
C2: 2021 | D2: 2022 | E2: 2023 | F2: 2024 | G2: 2025 | H2: 2026 | I2: 2027 | J2: 2028 | K2: 2029 | L2: 2030
A3: End of Period | C3: 44561 | D3: =EOMONTH(C3,12) | E3: =EOMONTH(D3,12) | F3: =EOMONTH(E3,12) | G3: =EOMONTH(F3,12) | H3: =EOMONTH(G3,12) | I3: =EOMONTH(H3,12) | J3: =EOMONTH(I3,12) | K3: =EOMONTH(J3,12) | L3: =EOMONTH(K3,12)
A4: Days in Period | C4: 365 | D4: =D3-C3 | E4: =E3-D3 | F4: =F3-E3 | G4: =G3-F3 | H4: =H3-G3 | I4: =I3-H3 | J4: =J3-I3 | K4: =K3-J3 | L4: =L3-K3
A6: Assumptions
A8: Scenario Switch | B8: 2 | C8: =CHOOSE($B$8."BEAR (konservatif)"."BASE"."BULL (agresif)")
A10: Lever | B10: Unit | C10: Bear | D10: Base | E10: Bull | F10: Active
A11: XLSmart overlap / at-risk rate | B11: % of XLS tenancy | C11: 0.18 | D11: 0.12 | E11: 0.06 | F11: =CHOOSE($B$8,C11,D11,E11)
A12: 5G densification rate (volume) | B12: % tower/yr | C12: 0 | D12: 0.011 | E12: 0.028 | F12: =CHOOSE($B$8,C12,D12,E12)
A13: XLSmart renegotiation pressure | B13: %/yr | C13: -0.025 | D13: -0.018 | E13: -0.01 | F13: =CHOOSE($B$8,C13,D13,E13)
A14: 5G amendment uplift | B14: %/yr | C14: 0.005 | D14: 0.013 | E14: 0.025 | F14: =CHOOSE($B$8,C14,D14,E14)
A15: Fiber lease / FTTT growth | B15: %/yr | C15: 0.03 | D15: 0.08 | E15: 0.14 | F15: =CHOOSE($B$8,C15,D15,E15)
A16: Other connectivity growth | B16: %/yr | C16: 0.1 | D16: 0.15 | E16: 0.2 | F16: =CHOOSE($B$8,C16,D16,E16)
A18: Other Inputs
A19: Tower site growth | B19: %/yr | C19: 0.015
A20: XLSmart share of tenants (2025) | B20: % | C20: 0.478
A21: Baseline organic churn (non-XLS) | B21: %/yr | C21: 0.01
A22: Capex for new tower (Industry Benchmark) | B22: Rp .000 / tower | C22: 1250000
A23: Capex for FTTH | B23: % of FTTH Revenue | C23: 0.3
A24: Tax Rate | C24: 0.22
A29: Income Statement (In Thousands Rupiah)
A30: Revenue | C30: ='SOURCE TOWR Income Statement'!C21 | D30: ='SOURCE TOWR Income Statement'!D21 | E30: ='SOURCE TOWR Income Statement'!E21 | F30: ='SOURCE TOWR Income Statement'!F21 | G30: ='SOURCE TOWR Income Statement'!G21 | H30: =H163 | I30: =I163 | J30: =J163 | K30: =K163 | L30: =L163
A31: =A40 | C31: =-C40 | D31: =-D40 | E31: =-E40 | F31: =-F40 | G31: =-G40 | H31: =H167 | I31: =I167 | J31: =J167 | K31: =K167 | L31: =L167
A32: Other cost of revenues | C32: =-'SOURCE TOWR Income Statement'!C48 | D32: =-'SOURCE TOWR Income Statement'!D48 | E32: =-'SOURCE TOWR Income Statement'!E48 | F32: =-'SOURCE TOWR Income Statement'!F48 | G32: =-'SOURCE TOWR Income Statement'!G48 | H32: =H169 | I32: =I169 | J32: =J169 | K32: =K169 | L32: =L169
A33: Gross Profit | C33: =SUM(C30:C32) | D33: =SUM(D30:D32) | E33: =SUM(E30:E32) | F33: =SUM(F30:F32) | G33: =SUM(G30:G32) | H33: =SUM(H30:H32) | I33: =SUM(I30:I32) | J33: =SUM(J30:J32) | ... L33: =SUM(L30:L32)
A35: Operating Expenses
A36: Selling. General & Administrative Expense | C36: =-'SOURCE TOWR Income Statement'!C65 | D36: =-'SOURCE TOWR Income Statement'!D65 | E36: =-'SOURCE TOWR Income Statement'!E65 | F36: =-'SOURCE TOWR Income Statement'!F65 | G36: =-'SOURCE TOWR Income Statement'!G65 | H36: =H171 | I36: =I171 | J36: =J171 | K36: =K171 | L36: =L171
A37: Other Operating Expense/(Income) - Net | C37: =-'SOURCE TOWR Income Statement'!C81 | D37: =-'SOURCE TOWR Income Statement'!D81 | E37: =-'SOURCE TOWR Income Statement'!E81 | F37: =-'SOURCE TOWR Income Statement'!F81 | G37: =-'SOURCE TOWR Income Statement'!G81 | H37: =H173 | I37: =I173 | J37: =J173 | K37: =K173 | L37: =L173
A38: EBIT | C38: =SUM(C33:C37) | D38: =SUM(D33:D37) | E38: =SUM(E33:E37) | F38: =SUM(F33:F37) | G38: =SUM(G33:G37) | H38: =SUM(H33:H37) | I38: =SUM(I33:I37) | J38: =SUM(J33:J37) | ... L38: =SUM(L33:L37)
A40: Depreciation & Amortization | C40: ='SOURCE TOWR Income Statement'!C295 | D40: ='SOURCE TOWR Income Statement'!D295 | E40: ='SOURCE TOWR Income Statement'!E295 | F40: ='SOURCE TOWR Income Statement'!F295 | G40: ='SOURCE TOWR Income Statement'!G295 | H40: =H210*-1 | I40: =I210*-1 | J40: =J210*-1 | K40: =K210*-1 | L40: =L210*-1
A41: EBITDA | C41: =C38+C40 | D41: =D38+D40 | E41: =E38+E40 | F41: =F38+F40 | G41: =G38+G40 | H41: =H40+H38 | I41: =I40+I38 | J41: =J40+J38 | K41: =K40+K38 | L41: =L40+L38
A43: Non Operating Expenses
A44: Finance Income/(Expense) - Net | C44: ='SOURCE TOWR Income Statement'!C92 | D44: ='SOURCE TOWR Income Statement'!D92 | E44: ='SOURCE TOWR Income Statement'!E92 | F44: ='SOURCE TOWR Income Statement'!F92 | G44: ='SOURCE TOWR Income Statement'!G92 | H44: =H221 | I44: =I221 | J44: =J221 | K44: =K221 | L44: =L221
A45: Sale of Tangible & Intangible Fixed Assets - Gain/(Loss) | C45: ='SOURCE TOWR Income Statement'!C107 | D45: ='SOURCE TOWR Income Statement'!D107 | E45: ='SOURCE TOWR Income Statement'!E107 | F45: ='SOURCE TOWR Income Statement'!F107 | G45: ='SOURCE TOWR Income Statement'!G107 | H45: =AVERAGE(C45:G45) | I45: =H45 | J45: =I45 | K45: =J45 | L45: =K45
A46: Other Non-Operating Income/(Expense) | C46: ='SOURCE TOWR Income Statement'!C111 | D46: ='SOURCE TOWR Income Statement'!D111 | E46: ='SOURCE TOWR Income Statement'!E111 | F46: ='SOURCE TOWR Income Statement'!F111 | G46: ='SOURCE TOWR Income Statement'!G111 | H46: =AVERAGE(C46:G46) | I46: =H46 | J46: =I46 | K46: =J46 | L46: =K46
A47: Non-Recurring Income/(Expense) | C47: ='SOURCE TOWR Income Statement'!C121 | D47: ='SOURCE TOWR Income Statement'!D121 | E47: ='SOURCE TOWR Income Statement'!E121 | F47: ='SOURCE TOWR Income Statement'!F121 | G47: ='SOURCE TOWR Income Statement'!G121 | H47: =AVERAGE(C47:G47) | I47: =H47 | J47: =I47 | K47: =J47 | L47: =K47
A48: EBT | C48: =C38+SUM(C44:C47) | D48: =D38+SUM(D44:D47) | E48: =E38+SUM(E44:E47) | F48: =F38+SUM(F44:F47) | G48: =G38+SUM(G44:G47) | H48: =H38+SUM(H44:H47) | I48: =I38+SUM(I44:I47) | J48: =J38+SUM(J44:J47) | ... L48: =L38+SUM(L44:L47)
A50: Income Taxes | C50: =-'SOURCE TOWR Income Statement'!C159 | D50: =-'SOURCE TOWR Income Statement'!D159 | E50: =-'SOURCE TOWR Income Statement'!E159 | F50: =-'SOURCE TOWR Income Statement'!F159 | G50: =-'SOURCE TOWR Income Statement'!G159 | H50: =H175 | I50: =I175 | J50: =J175 | K50: =K175 | L50: =L175
A51: Net Income | C51: =C48+C50 | D51: =D48+D50 | E51: =E48+E50 | F51: =F48+F50 | G51: =G48+G50 | H51: =H48+H50 | I51: =+I50+I48 | J51: =+J50+J48 | K51: =+K50+K48 | L51: =+L50+L48
A53: Dividend Paid | C53: 0 | D53: 0 | E53: 0 | F53: 0 | G53: 0 | H53: 0 | I53: 0 | J53: 0 | K53: 0 | L53: 0
A55: Balance Sheet
A57: Assets
A58: Current Assets
A59: Cash & Short-Term Investments | C59: ='SOURCE TOWR Balance Sheet'!C21 | D59: ='SOURCE TOWR Balance Sheet'!D21 | E59: ='SOURCE TOWR Balance Sheet'!E21 | F59: ='SOURCE TOWR Balance Sheet'!F21 | G59: ='SOURCE TOWR Balance Sheet'!G21 | H59: =H126 | I59: =I126 | J59: =J126 | K59: =K126 | L59: =L126
A60: Loans & Receivables - Net - Short-Term | C60: ='SOURCE TOWR Balance Sheet'!C26 | D60: ='SOURCE TOWR Balance Sheet'!D26 | E60: ='SOURCE TOWR Balance Sheet'!E26 | F60: ='SOURCE TOWR Balance Sheet'!F26 | G60: ='SOURCE TOWR Balance Sheet'!G26 | H60: =H187 | I60: =I187 | J60: =J187 | K60: =K187 | L60: =L187
A61: Inventories | C61: ='SOURCE TOWR Balance Sheet'!C36 | D61: ='SOURCE TOWR Balance Sheet'!D36 | E61: ='SOURCE TOWR Balance Sheet'!E36 | F61: ='SOURCE TOWR Balance Sheet'!F36 | G61: ='SOURCE TOWR Balance Sheet'!G36 | H61: =H184 | I61: =I184 | J61: =J184 | K61: =K184 | L61: =L184
A62: Prepaid Expenses - Short-Term | C62: ='SOURCE TOWR Balance Sheet'!C45 | D62: ='SOURCE TOWR Balance Sheet'!D45 | E62: ='SOURCE TOWR Balance Sheet'!E45 | F62: ='SOURCE TOWR Balance Sheet'!F45 | G62: ='SOURCE TOWR Balance Sheet'!G45 | H62: =H193 | I62: =I193 | J62: =J193 | K62: =K193 | L62: =L193
A63: Other Current Assets - Total | C63: ='SOURCE TOWR Balance Sheet'!C47 | D63: ='SOURCE TOWR Balance Sheet'!D47 | E63: ='SOURCE TOWR Balance Sheet'!E47 | F63: ='SOURCE TOWR Balance Sheet'!F47 | G63: ='SOURCE TOWR Balance Sheet'!G47 | H63: =G63 | I63: =H63 | J63: =I63 | K63: =J63 | L63: =K63
A64: Total Current Assets | C64: =SUM(C58:C63) | D64: =SUM(D58:D63) | E64: =SUM(E58:E63) | F64: =SUM(F58:F63) | G64: =SUM(G58:G63) | H64: =SUM(H59:H63) | I64: =SUM(I59:I63) | J64: =SUM(J59:J63) | K64: =SUM(K59:K63) | L64: =SUM(L59:L63)
A66: Non-Current Assets
A67: Long-Term Investment | C67: ='SOURCE TOWR Balance Sheet'!C55 | D67: ='SOURCE TOWR Balance Sheet'!D55 | E67: ='SOURCE TOWR Balance Sheet'!E55 | F67: ='SOURCE TOWR Balance Sheet'!F55 | G67: ='SOURCE TOWR Balance Sheet'!G55 | H67: =G67 | I67: =H67 | J67: =I67 | K67: =J67 | L67: =K67
A68: Investments in Associates. Joint Ventures and Unconsolidated Subsidiaries | C68: ='SOURCE TOWR Balance Sheet'!C62 | D68: ='SOURCE TOWR Balance Sheet'!D62 | E68: ='SOURCE TOWR Balance Sheet'!E62 | F68: ='SOURCE TOWR Balance Sheet'!F62 | G68: ='SOURCE TOWR Balance Sheet'!G62 | H68: =G68 | I68: =H68 | J68: =I68 | K68: =J68 | L68: =K68
A69: Receivables & Loans - Long-Term | C69: ='SOURCE TOWR Balance Sheet'!C63 | D69: ='SOURCE TOWR Balance Sheet'!D63 | E69: ='SOURCE TOWR Balance Sheet'!E63 | F69: ='SOURCE TOWR Balance Sheet'!F63 | G69: ='SOURCE TOWR Balance Sheet'!G63 | H69: =G69 | I69: =H69 | J69: =I69 | K69: =J69 | L69: =K69
A70: Derivative Financial Instruments - Hedging - Long-Term | C70: ='SOURCE TOWR Balance Sheet'!C70 | D70: ='SOURCE TOWR Balance Sheet'!D70 | E70: ='SOURCE TOWR Balance Sheet'!E70 | F70: ='SOURCE TOWR Balance Sheet'!F70 | G70: ='SOURCE TOWR Balance Sheet'!G70 | H70: =G70 | I70: =H70 | J70: =I70 | K70: =J70 | L70: =K70
A71: Property. Plant & Equipment - Net - Total | C71: ='SOURCE TOWR Balance Sheet'!C71 | D71: ='SOURCE TOWR Balance Sheet'!D71 | E71: ='SOURCE TOWR Balance Sheet'!E71 | F71: ='SOURCE TOWR Balance Sheet'!F71 | G71: ='SOURCE TOWR Balance Sheet'!G71 | H71: =H202 | I71: =I202 | J71: =J202 | K71: =K202 | L71: =L202
A72: Other Non-Current Assets - Total | C72: ='SOURCE TOWR Balance Sheet'!C129 | D72: ='SOURCE TOWR Balance Sheet'!D129 | E72: ='SOURCE TOWR Balance Sheet'!E129 | F72: ='SOURCE TOWR Balance Sheet'!F129 | G72: ='SOURCE TOWR Balance Sheet'!G129 | H72: =G72 | I72: =H72 | J72: =I72 | K72: =J72 | L72: =K72
A73: Intangible Assets | C73: ='SOURCE TOWR Balance Sheet'!C138 | D73: ='SOURCE TOWR Balance Sheet'!D138 | E73: ='SOURCE TOWR Balance Sheet'!E138 | F73: ='SOURCE TOWR Balance Sheet'!F138 | G73: ='SOURCE TOWR Balance Sheet'!G138 | H73: =G73 | I73: =H73 | J73: =I73 | K73: =J73 | L73: =K73
A74: Total Non-Current Assets | C74: =SUM(C67:C73) | D74: =SUM(D67:D73) | E74: =SUM(E67:E73) | F74: =SUM(F67:F73) | G74: =SUM(G67:G73) | H74: =SUM(H67:H73) | I74: =SUM(I67:I73) | J74: =SUM(J67:J73) | ... L74: =SUM(L67:L73)
A75: Total Assets | C75: =C64+C74 | D75: =D64+D74 | E75: =E64+E74 | F75: =F64+F74 | G75: =G64+G74 | H75: =H64+H74 | I75: =I64+I74 | J75: =J64+J74 | ... L75: =L64+L74
A77: Liabilities
A78: Current Liabilities
A79: Trade Accounts Payable & Accruals - Short-Term | C79: ='SOURCE TOWR Balance Sheet'!C169 | D79: ='SOURCE TOWR Balance Sheet'!D169 | E79: ='SOURCE TOWR Balance Sheet'!E169 | F79: ='SOURCE TOWR Balance Sheet'!F169 | G79: ='SOURCE TOWR Balance Sheet'!G169 | H79: =H190 | I79: =I190 | J79: =J190 | K79: =K190 | L79: =L190
A80: Short-Term Debt & Current Portion of Long-Term Debt | C80: ='SOURCE TOWR Balance Sheet'!C172 | D80: ='SOURCE TOWR Balance Sheet'!D172 | E80: ='SOURCE TOWR Balance Sheet'!E172 | F80: ='SOURCE TOWR Balance Sheet'!F172 | G80: ='SOURCE TOWR Balance Sheet'!G172 | H80: =H228 | I80: =I228 | J80: =J228 | K80: =K228 | L80: =L228
A81: Derivative Liabilities - Hedging - Short-Term | C81: ='SOURCE TOWR Balance Sheet'!C179 | D81: ='SOURCE TOWR Balance Sheet'!D179 | E81: ='SOURCE TOWR Balance Sheet'!E179 | F81: ='SOURCE TOWR Balance Sheet'!F179 | G81: ='SOURCE TOWR Balance Sheet'!G179 | H81: =G81 | I81: =H81 | J81: =I81 | K81: =J81 | L81: =K81
A82: Income Taxes - Payable - Short-Term | C82: ='SOURCE TOWR Balance Sheet'!C181 | D82: ='SOURCE TOWR Balance Sheet'!D181 | E82: ='SOURCE TOWR Balance Sheet'!E181 | F82: ='SOURCE TOWR Balance Sheet'!F181 | G82: ='SOURCE TOWR Balance Sheet'!G181 | H82: =G82 | I82: =H82 | J82: =I82 | K82: =J82 | L82: =K82
A83: Other Current Liabilities - Total | C83: ='SOURCE TOWR Balance Sheet'!C184 | D83: ='SOURCE TOWR Balance Sheet'!D184 | E83: ='SOURCE TOWR Balance Sheet'!E184 | F83: ='SOURCE TOWR Balance Sheet'!F184 | G83: ='SOURCE TOWR Balance Sheet'!G184 | H83: =G83 | I83: =H83 | J83: =I83 | K83: =J83 | L83: =K83
A84: Total Current Liabilities | C84: =SUM(C78:C83) | D84: =SUM(D78:D83) | E84: =SUM(E78:E83) | F84: =SUM(F78:F83) | G84: =SUM(G78:G83) | H84: =SUM(H79:H83) | I84: =SUM(I79:I83) | J84: =SUM(J79:J83) | K84: =SUM(K79:K83) | L84: =SUM(L79:L83)
A86: Non Current Liabilities
A87: Debt - Long-Term - Total | C87: ='SOURCE TOWR Balance Sheet'!C198 | D87: ='SOURCE TOWR Balance Sheet'!D198 | E87: ='SOURCE TOWR Balance Sheet'!E198 | F87: ='SOURCE TOWR Balance Sheet'!F198 | G87: ='SOURCE TOWR Balance Sheet'!G198 | H87: =H233 | I87: =I233 | J87: =J233 | K87: =K233 | L87: =L233
A88: Derivative Liabilities - Hedging - Long-Term | C88: ='SOURCE TOWR Balance Sheet'!C208 | D88: ='SOURCE TOWR Balance Sheet'!D208 | E88: ='SOURCE TOWR Balance Sheet'!E208 | F88: ='SOURCE TOWR Balance Sheet'!F208 | G88: ='SOURCE TOWR Balance Sheet'!G208 | H88: =G88 | I88: =H88 | J88: =I88 | K88: =J88 | L88: =K88
A89: Deferred Tax & Investment Tax Credits - Long-Term | C89: ='SOURCE TOWR Balance Sheet'!C210 | D89: ='SOURCE TOWR Balance Sheet'!D210 | E89: ='SOURCE TOWR Balance Sheet'!E210 | F89: ='SOURCE TOWR Balance Sheet'!F210 | G89: ='SOURCE TOWR Balance Sheet'!G210 | H89: =G89 | I89: =H89 | J89: =I89 | K89: =J89 | L89: =K89
A90: Other Non-Current Liabilities - Total | C90: ='SOURCE TOWR Balance Sheet'!C214 | D90: ='SOURCE TOWR Balance Sheet'!D214 | E90: ='SOURCE TOWR Balance Sheet'!E214 | F90: ='SOURCE TOWR Balance Sheet'!F214 | G90: ='SOURCE TOWR Balance Sheet'!G214 | H90: =G90 | I90: =H90 | J90: =I90 | K90: =J90 | L90: =K90
A91: Total Non-Current Liabilities | C91: =SUM(C87:C90) | D91: =SUM(D87:D90) | E91: =SUM(E87:E90) | F91: =SUM(F87:F90) | G91: =SUM(G87:G90) | H91: =SUM(H87:H90) | I91: =SUM(I87:I90) | J91: =SUM(J87:J90) | ... L91: =SUM(L87:L90)
A92: Total Liabilities | C92: =C84+C91 | D92: =D84+D91 | E92: =E84+E91 | F92: =F84+F91 | G92: =G84+G91 | H92: =H84+H91 | I92: =I84+I91 | J92: =J84+J91 | ... L92: =L84+L91
A94: Equity
A95: Retained Earnings | C95: ='SOURCE TOWR Balance Sheet'!C250 | D95: ='SOURCE TOWR Balance Sheet'!D250 | E95: ='SOURCE TOWR Balance Sheet'!E250 | F95: ='SOURCE TOWR Balance Sheet'!F250 | G95: ='SOURCE TOWR Balance Sheet'!G250 | H95: =SUM(G95,G51,G53) | I95: =SUM(H95,H51,H53) | J95: =SUM(I95,I51,I53) | K95: =SUM(J95,J51,J53) | L95: =SUM(K95,K51,K53)
A96: Common Equity | C96: ='SOURCE TOWR Balance Sheet'!C245 | D96: ='SOURCE TOWR Balance Sheet'!D245 | E96: ='SOURCE TOWR Balance Sheet'!E245 | F96: ='SOURCE TOWR Balance Sheet'!F245 | G96: ='SOURCE TOWR Balance Sheet'!G245 | H96: =G96 | I96: =H96 | J96: =I96 | K96: =J96 | L96: =K96
A97: Treasury Shares | C97: =-'SOURCE TOWR Balance Sheet'!C243 | D97: =-'SOURCE TOWR Balance Sheet'!D243 | E97: =-'SOURCE TOWR Balance Sheet'!E243 | F97: =-'SOURCE TOWR Balance Sheet'!F243 | G97: =-'SOURCE TOWR Balance Sheet'!G243 | H97: =G97 | I97: =H97 | J97: =I97 | K97: =J97 | L97: =K97
A98: Minority Interest - Equity | C98: ='SOURCE TOWR Balance Sheet'!C268 | D98: ='SOURCE TOWR Balance Sheet'!D268 | E98: ='SOURCE TOWR Balance Sheet'!E268 | F98: ='SOURCE TOWR Balance Sheet'!F268 | G98: ='SOURCE TOWR Balance Sheet'!G268 | H98: =G98 | I98: =H98 | J98: =I98 | K98: =J98 | L98: =K98
A99: Total Equity | C99: =SUM(C95:C98) | D99: =SUM(D95:D98) | E99: =SUM(E95:E98) | F99: =SUM(F95:F98) | G99: =SUM(G95:G98) | H99: =H95+H96+H98+H97 | I99: =SUM(I95:I98) | J99: =SUM(J95:J98) | K99: =SUM(K95:K98) | L99: =SUM(L95:L98)
A101: Total Liabilities & Equity | C101: =C92+C99 | D101: =D92+D99 | E101: =E92+E99 | F101: =F92+F99 | G101: =G92+G99 | H101: =H92+H99 | I101: =I92+I99 | J101: =J92+J99 | ... L101: =L92+L99
A103: Check | C103: =C75-C101 | D103: =D75-D101 | E103: =E75-E101 | F103: =F75-F101 | G103: =G75-G101 | H103: =H75-H101 | I103: =I75-I101 | J103: =J75-J101 | ... L103: =L75-L101
A105: Cash Flow
A107: Operating Cash Flow
A108: Net Earnings | H108: =G51 | I108: =H51 | J108: =I51 | K108: =J51 | L108: =K51
A109: Plus: Depreciation & Amortization | H109: =H201*-1 | I109: =I201*-1 | J109: =J201*-1 | K109: =K201*-1 | L109: =L201*-1
A110: Less: Changes in Working Capital | H110: {=(SUM(H79:H83)-SUM(G79:G83))-((SUM(H60:H63-G60:G63)))} | I110: {=(SUM(I79:I83)-SUM(H79:H83))-((SUM(I60:I63-H60:H63)))} | J110: {=(SUM(J79:J83)-SUM(I79:I83))-((SUM(J60:J63-I60:I63)))} | K110: {=(SUM(K79:K83)-SUM(J79:J83))-((SUM(K60:K63-J60:J63)))} | L110: {=(SUM(L79:L83)-SUM(K79:K83))-((SUM(L60:L63-K60:K63)))}
A111: Cash from Operations | H111: =SUM(H108:H110) | I111: =SUM(I108:I110) | J111: =SUM(J108:J110) | K111: =SUM(K108:K110) | L111: =SUM(L108:L110)
A113: Investing Cash Flow
A114: Investments in Property & Equipment (CapEx) | H114: =H200*-1 | I114: =I200*-1 | J114: =J200*-1 | K114: =K200*-1 | L114: =L200*-1
A115: Investments in Businesses | H115: 0 | I115: 0 | J115: 0 | K115: 0 | L115: 0
A116: Cash from Investing | H116: =SUM(H114:H115) | I116: =SUM(I114:I115) | J116: =SUM(J114:J115) | K116: =SUM(K114:K115) | L116: =SUM(L114:L115)
A118: Financing Cash Flow
A119: Issuance (repayment) of debt - net | H119: =H231-H232 | I119: =I231-I232 | J119: =J231-J232 | K119: =K231-K232 | L119: =L231-L232
A120: Issuance (repayment) of equity | H120: 0 | I120: 0 | J120: 0 | K120: 0 | L120: 0
A121: Payment of Dividends | H121: 0 | I121: 0 | J121: 0 | K121: 0 | L121: 0
A122: Cash from Financing | H122: =SUM(H119:H121) | I122: =SUM(I119:I121) | J122: =SUM(J119:J121) | K122: =SUM(K119:K121) | L122: =SUM(L119:L121)
A124: Net Increase (decrease) in Cash | H124: =SUM(H122,H116,H111) | I124: =SUM(I122,I116,I111) | J124: =SUM(J122,J116,J111) | K124: =SUM(K122,K116,K111) | L124: =SUM(L122,L116,L111)
A125: Opening Cash Balance | H125: =G59 | I125: =H59 | J125: =I59 | K125: =J59 | L125: =K59
A126: Closing Cash Balance | H126: =H124+H125 | I126: =I124+I125 | J126: =J124+J125 | K126: =K124+K125 | L126: =L124+L125
...

Sheet TOWR WIFI-Comparable Precedent
C2: COMPARABLE PEER ANALYSIS (TOWR) | K2: Group 1 - Indonesian Tower Precedent Transactions: Benchmarks for TOWR
C3: Ticker | D3: Company | E3: EV/EBITDA (TTM) | F3: P/BV (TTM) | G3: PE RATIO (TTM) | K3: Year | L3: Target | M3: Acquiror | N3: EV/EBITDA (Rp Billion) | O3: EV/Tower | P3: EV/Tenant
C4: Indonesia Peers | K4: National Transaction
C5: MTEL.IJ | D5: PT Dayamitra Telekomunikasi Tbk (Mitratel) | E5: 8.6 | F5: 1.1 | G5: 16.5 | J5: 1 | K5: 2021 | L5: Solusi Tunas Pratama (SUPR) 94.03% | M5: Protelindo (TOWR) | N5: =17800/1900 | O5: =17800/6780 | P5: =17800/12500
C6: TBIG.IJ | D6: PT Tower Bersama Infrastructure Tbk | E6: 11.40 x | F6: 2.5 | G6: 22.1 | J6: 2 | K6: 2024 | L6: Inti Bangun Sejahtera (IBST) 90.11% | M6: iForte (TOWR) | N6: 8 | O6: =3800/3383 | P6: =3800/5791
C7: BALI.IJ | D7: PT Bali Towerindo Sentra Tbk | E7: 10.4 | F7: 2 | G7: 27.80 x | J7: 3 | K7: 2020 | L7: 3000 unit of IBST's Tower | M7: TBIG | N7: =3970/481 | O7: =3970/3000 | P7: 1.32
C8: GHON.IJ | D8: PT Gihon Telekomunikasi Indonesia Tbk | E8: 11.40 x | F8: 1.3 | G8: 12.8 | J8: 4 | K8: 2021 | L8: 6000 unit of Telkomsel's Tower | M8: Mitratel (MTEL) | N8: 13.4 | O8: =10280/6000 | P8: 1.59
C9: Regional Peers | K9: International Transaction
C10: 788 HK | D10: China Tower Corporation Limited | E10: 4.5 | F10: 0.7 | G10: 10.3 | J10: 5 | K10: 2024 | L10: IHS Kuwait Tower | M10: Zain | N10: 14.2 | O10: =3700/2345 | P10: NA
C11: INDUSTOW IN | D11: Indus Towers Ltd | E11: 7.4 | F11: 2.4 | G11: 13.6 | K11: Quartile 1 | N11: =_xlfn.QUARTILE.INC(N5:N10, 1) | O11: =_xlfn.QUARTILE.INC(O5:O10, 1) | P11: =_xlfn.QUARTILE.INC(P5:P10, 1)
C12: Quartile 1 - Worst Case | E12: =_xlfn.QUARTILE.INC(E5:E11, 1) | F12: =_xlfn.QUARTILE.INC(F5:F11, 1) | G12: =_xlfn.QUARTILE.INC(G5:G11, 1) | K12: Median | N12: =MEDIAN(N5:N10) | O12: =MEDIAN(O5:O10) | P12: =MEDIAN(P5:P10)
C13: Median - Base Case | E13: =MEDIAN(E5:E11) | F13: =MEDIAN(F5:F11) | G13: =MEDIAN(G5:G11) | K13: Quartile 3 | N13: =_xlfn.QUARTILE.EXC(N5:N10, 3) | O13: =_xlfn.QUARTILE.EXC(O5:O10, 3) | P13: =_xlfn.QUARTILE.INC(P5:P10, 3)
C14: Quartile 3 - Best Case | E14: =_xlfn.QUARTILE.INC(E5:E11, 3) | F14: =_xlfn.QUARTILE.INC(F5:F11, 3) | G14: =_xlfn.QUARTILE.INC(G5:G11, 3) | K14: Source:
C15: Mean | E15: =_xlfn.QUARTILE.INC(E5:E11, 3) | F15: =_xlfn.QUARTILE.INC(F5:F11, 3) | G15: =_xlfn.QUARTILE.INC(G5:G11, 3) | K15: 1. https://market.bisnis.com/read/20211005/189/1450717/sukses-akuisisi-supr-saham-sarana-menara-towr-menuju-rp1540
C16: TOWR | E16: =E29/E25 | F16: =E21/(E24/E27) | G16: =E21/(E23/E27) | K16: 2.https://samuel.co.id/news-events-ssi/towr-kuatkan-posisi-dengan-akuisisi-ibst/
C17: Implied Share Price - Worst Case | E17: =(($E$25*E12)-$E$22)/$E$27 | F17: =F12*$E$32 | G17: =G12*$E$31 | K17: 3.https://investor.id/market-and-corporate/242971/tower-bersama-segera-akuisisi-menara-rp-397-triliun
C18: Implied Share Price - Base Case | E18: =(($E$25*E13)-$E$22)/$E$27 | F18: =F13*$E$32 | G18: =G13*$E$31 | K18: 4.https://www.indopremier.com/ipotnews/newsDetail.php?jdl=Mitratel_(MTEL)_bakal_Akuisisi_Menara_Telekomunikasi_Rp_9_Triliun&news_id=394832&group_news=RESEARCHNEWS&taging_subtype=PG002&name=&search=y_general&q=,&halaman=1
C19: Implied Share Price - Best Case | E19: =(($E$25*E14)-$E$22)/$E$27 | F19: =F14*$E$32 | G19: =G14*$E$31 | K19: 5.https://www.fticonsulting.com/about/newsroom/press-releases/fti-capital-advisors-supports-zain-group-on-acquisition-of-the-ihs-tower-portfolio-in-kuwait
C21: Price/Share - TOWR (21 Agt) | E21: 434 | K21: Group 2. Indonesian Fiber and Broadband Precedent Transactions: Benchmarks for WIFI
C22: Net Debt | E22: 44509580000000 | K22: Year | L22: Target | M22: Acquiror | N22: EV/EBITDA (Rp Billion) | O22: EV/Homepass (Rp Million)
C23: Net Profit TOWR | E23: 3678316000000 | K23: National Transaction
C24: Book Value TOWR | E24: 26972415000000 | J24: 1 | K24: 2022 | L24: Link Net | M24: Axiata dan XL Axiata | N24: =13210/1870 | O24: =13210/2800
C25: EBITDA TOWR | E25: 10924099000000 | J25: 2 | K25: 2024 | L25: PT Ultra Mandiri Telekomunikasi (UMT) | M25: Mitratel (MTEL) | N25: 7.7 | O25: NA
C26: Revenue TOWR | E26: 13327907000000 | K26: International Transaction
C27: Shares Outstanding | E27: =58272885109 | J27: 3 | K27: 2024 | L27: Frontier Communications | M27: Verizon | N27: 8.5 | O27: 14.2
C28: Market Cap TOWR | E28: =E27*E21 | J28: 4 | K28: 2025 | L28: Quantum Fiber (Lumen) | M28: AT&T | N28: NA | O28: 25.4
C29: Enterprise Value TOWR | E29: =E28+E22 | K29: Quartile 1 | N29: =_xlfn.QUARTILE.INC(N24:N28, 1) | O29: =_xlfn.QUARTILE.INC(O24:O28, 1)
K30: Median | N30: =MEDIAN(N24:N28) | O30: =MEDIAN(O24:O28)
C31: EPS TOWR | E31: =E23/E27 | K31: Quartile 3 | N31: =_xlfn.QUARTILE.EXC(N24:N28, 3) | O31: =_xlfn.QUARTILE.EXC(O24:O28, 3)
C32: BVPS TOWR | E32: =E24/E27 | K32: Source:
C33: EBITDA per Share | E33: =E25/E27 | K33: 1.https://www.cnbcindonesia.com/market/20220623101848-17-349579/tok-axiata-dan-xl--excl--resmi-caplok-link-net-dari-lippo
C34: *in Rupiah | K34: 2. https://www.cnbcindonesia.com/market/20241206112118-17-593886/caplok-bisnis-fiber-ptpp-rp650-m-saham-mitratel-ditarget-segini
K35: 3.https://www.sec.gov/Archives/edgar/data/20520/000110465924111034/tm2426760d1_ex99-2.htm
K36: 4.https://ir.lumen.com/news/news-details/2026/Lumen-Completes-Sale-of-Consumer-Fiber-to-the-Home-Business-to-ATT/default.aspx
C37: COMPARABLE PEER ANALYSIS (WIFI)
C38: Ticker | D38: Company | E38: EV/EBITDA (TTM) | F38: P/BV (TTM) | G38: PE RATIO (TTM)
C39: Indonesia Peers
C40: LINK.JK | D40: PT Link Net Tbk | E40: 4.9 | F40: 1.4 | G40: -2.8 x
C41: DATA.JK | D41: PT Remala Abadi Tbk | E41: 12.9 | F41: 6.40 x | G41: 20.8
C42: INET | D42: PT Sinergi Inti Andalan Prima Tbk | E42: 64.4 | F42: 1.9 | G42: 189.4 x
C43: EDGE | D43: PT Jasnita Telekomindo Tbk | E43: 28.5 | F43: 5.4 | G43: 159.4 x
C44: Regional Peers
C45: CNVRG PM | D45: Converage ICT | E45: 3.8 | F45: 1.1 | G45: 6.2
C46: NETLINK SP | D46: NetLink NBN Trust | E46: 16.4 | F46: 1.7 | G46: 45.8
C47: TDC MK | D47: TIME dotCom | E47: 12.7 | F47: 3.9 | G47: 25.5
C48: Quartile 1 - Worst Case | E48: =_xlfn.QUARTILE.INC(E40:E47, 1) | F48: =_xlfn.QUARTILE.INC(F40:F47, 1) | G48: =_xlfn.QUARTILE.INC(G40:G47, 1)
C49: Median - Base Case | E49: =MEDIAN(E40:E47) | F49: =MEDIAN(F40:F47) | G49: =MEDIAN(G40:G47)
C50: Quartile 3 - Best Case | E50: =_xlfn.QUARTILE.INC(E40:E47, 3) | F50: =_xlfn.QUARTILE.INC(F40:F47, 3) | G50: =_xlfn.QUARTILE.INC(G40:G47, 3)
C51: Mean | E51: =_xlfn.QUARTILE.INC(E40:E47, 3) | F51: =_xlfn.QUARTILE.INC(F40:F47, 3) | G51: =_xlfn.QUARTILE.INC(G40:G47, 3)
C52: WIFI | E52: =E65/E61 | F52: =E57/(E60/E63) | G52: =E57/(E59/E63)
C53: Implied Share Price - Worst Case | E53: =(($E$61*E48)-$E$58)/$E$63 | F53: =F48*$E$68 | G53: =G48*$E$67
C54: Implied Share Price - Base Case | E54: =(($E$61*E49)-$E$58)/$E$63 | F54: =F49*$E$68 | G54: =G49*$E$67
C55: Implied Share Price - Best Case | E55: =(($E$61*E50)-$E$58)/$E$63 | F55: =F50*$E$68 | G55: =G50*$E$67
C57: Price/Share - TOWR (21 Agt) | E57: 2090
C58: Net Debt | E58: =-565153097.16*1000
C59: Net Profit WIFI | E59: =408551231.77*1000
C60: Book Value WIFI | E60: =7299442709.11*1000
C61: EBITDA WIFI | E61: =1106232966.57*1000
C62: Revenue WIFI | E62: =1659396069.86*1000
C63: Shares Outstanding | E63: =5308549015
C64: Market Cap WIFI | E64: =E63*E57
C65: Enterprise Value WIFI | E65: =E64-E58
C67: EPS WIFI | E67: =E59/E63
C68: BVPS WIFI | E68: =E60/E63
C69: EBITDA per Share | E69: =E61/E63
C70: *in Rupiah

Sheet WIFI 3-Statement Model
A1: WIFI | Three-Statement Model
A2: Year to 31 Dec | D2: 2021A | E2: 2022A | F2: 2023A | G2: 2024A | H2: 2025A | I2: 2026F | J2: 2027F | K2: 2028F | L2: 2029F | M2: 2030F
A3: In Thousands of Rupiah (IDR '000) unless stated
A4: SHEET CHECK | C4: =SUMPRODUCT(ABS(D81:M81))+SUMPRODUCT(ABS(I101:M101))
A5: ACTIVE SCENARIO ► set 1=Bear, 2=Base, 3=Bull → | C5: 2 | D5: =CHOOSE($C$5,"BEAR (konservatif)","BASE","BULL (agresif)")
A6: ASSUMPTIONS (Base Case)
A7: Revenue growth (YoY) | E7: =E28/D28-1 | F7: =F28/E28-1 | G7: =G28/F28-1 | H7: =H28/G28-1 | I7: =I28/H28-1 | J7: =J28/I28-1 | K7: =K28/J28-1 | L7: =L28/K28-1 | M7: =M28/L28-1
A8: Gross margin | D8: =D30/D28 | E8: =E30/E28 | F8: =F30/F28 | G8: =G30/G28 | H8: =H30/H28 | I8: =AVERAGE(D8:H8) | J8: =AVERAGE(E8:I8) | K8: =AVERAGE(F8:J8) | L8: =AVERAGE(G8:K8) | M8: =AVERAGE(H8:L8)
A9: SG&A (% of revenue) | D9: =-D32/D28 | E9: =-E32/E28 | F9: =-F32/F28 | G9: =-G32/G28 | H9: =-H32/H28 | I9: =AVERAGE(D9:H9) | J9: =$I$9 | K9: =$I$9 | L9: =$I$9 | M9: =$I$9
A10: Other opex/(income) (% of revenue) | D10: =-D33/D28 | E10: =-E33/E28 | F10: =-F33/F28 | G10: =-G33/G28 | H10: =-H33/H28 | I10: 0.005 | J10: 0.005 | K10: 0.005 | L10: 0.005 | M10: 0.005
A11: D&A (% of opening net PPE) | E11: =E36/D58 | F11: =F36/E58 | G11: =G36/F58 | H11: =H36/G58 | I11: 0.1 | J11: 0.1 | K11: 0.1 | L11: 0.1 | M11: 0.1
A12: Capex (% of revenue) [implied output] | D12: =D90/D28 | E12: =E90/E28 | F12: =F90/F28 | G12: =G90/G28 | H12: =H90/H28 | I12: =I171/I28 | J12: =J171/J28 | K12: =K171/K28 | L12: =L171/L28 | M12: =M171/M28
A13: Receivable days (of revenue) | D13: =D52/D28*365 | E13: =E52/E28*365 | F13: =F52/F28*365 | G13: =G52/G28*365 | H13: =H52/H28*365 | I13: 50 | J13: 50 | K13: 50 | L13: 50 | M13: 50
A14: Inventory days (of COGS) | D14: =D53/-D29*365 | E14: =E53/-E29*365 | F14: =F53/-F29*365 | G14: =G53/-G29*365 | H14: =H53/-H29*365 | I14: 90 | J14: 90 | K14: 90 | L14: 90 | M14: 90
A15: Prepaid expenses (% of revenue) | D15: =D54/D28 | E15: =E54/E28 | F15: =F54/F28 | G15: =G54/G28 | H15: =H54/H28 | I15: 0.2 | J15: 0.2 | K15: 0.2 | L15: 0.2 | M15: 0.2
A16: Payable days (of COGS) | D16: =D65/-D29*365 | E16: =E65/-E29*365 | F16: =F65/-F29*365 | G16: =G65/-G29*365 | H16: =H65/-H29*365 | I16: =AVERAGE(E16:H16) | J16: =I16 | K16: =J16 | L16: =K16 | M16: =L16
A17: Other current liabilities (% of revenue) | D17: =D68/D28 | E17: =E68/E28 | F17: =F68/F28 | G17: =G68/G28 | H17: =H68/H28 | I17: 0.04 | J17: 0.04 | K17: 0.04 | L17: 0.04 | M17: 0.04
A18: Income tax payable (% of tax expense) | D18: =D67/-D43 | E18: =E67/-E43 | F18: =F67/-F43 | G18: =G67/-G43 | H18: =H67/-H43 | I18: 0.4 | J18: 0.4 | K18: 0.4 | L18: 0.4 | M18: 0.4
A19: Effective tax rate | D19: =-D43/D42 | E19: =-E43/E42 | F19: =-F43/F42 | G19: =-G43/G42 | H19: =-H43/H42 | I19: 0.22 | J19: 0.22 | K19: 0.22 | L19: 0.22 | M19: 0.22
A20: Interest rate on debt | E20: =-E39/((D124+E124)/2) | F20: =-F39/((E124+F124)/2) | G20: =-G39/((F124+G124)/2) | H20: =-H39/((G124+H124)/2) | I20: 0.09 | J20: 0.09 | K20: 0.09 | L20: 0.09 | M20: 0.09
A21: Interest income rate on cash | E21: =E40/D51 | F21: =F40/E51 | G21: =G40/F51 | H21: =H40/G51 | I21: 0.04 | J21: 0.04 | K21: 0.04 | L21: 0.04 | M21: 0.04
A22: LT debt net issuance (IDR '000) | E22: =E71-D71 | F22: =F71-E71 | G22: =G71-F71 | H22: =H71-G71 | I22: 2000000000 | J22: 1500000000 | K22: 1000000000 | L22: 500000000 | M22: 0
A23: Minority interest (% of NI before minority) | D23: =-D45/D44 | E23: =-E45/E44 | F23: =-F45/F44 | G23: =-G45/G44 | H23: =-H45/H44 | I23: 0.3 | J23: 0.3 | K23: 0.3 | L23: 0.3 | M23: 0.3
A24: Dividend payout (% of NI to parent) | I24: 0.0115 | J24: 0.1 | K24: 0.1 | L24: 0.1 | M24: 0.1
A26: INCOME STATEMENT
A28: Revenue | D28: ='SOURCE WIFI Income Statement'!B43 | E28: ='SOURCE WIFI Income Statement'!C43 | F28: ='SOURCE WIFI Income Statement'!D43 | G28: ='SOURCE WIFI Income Statement'!E43 | H28: ='SOURCE WIFI Income Statement'!F43 | I28: ='WIFI Rev-COGS Detail'!I26 | J28: ='WIFI Rev-COGS Detail'!J26 | K28: ='WIFI Rev-COGS Detail'!K26 | L28: ='WIFI Rev-COGS Detail'!L26 | M28: ='WIFI Rev-COGS Detail'!M26
A29: Cost of revenue | D29: =-'SOURCE WIFI Income Statement'!B47 | E29: =-'SOURCE WIFI Income Statement'!C47 | F29: =-'SOURCE WIFI Income Statement'!D47 | G29: =-'SOURCE WIFI Income Statement'!E47 | H29: =-'SOURCE WIFI Income Statement'!F47 | I29: ='WIFI Rev-COGS Detail'!I41 | J29: ='WIFI Rev-COGS Detail'!J41 | K29: ='WIFI Rev-COGS Detail'!K41 | L29: ='WIFI Rev-COGS Detail'!L41 | M29: ='WIFI Rev-COGS Detail'!M41
A30: Gross profit | D30: =D28+D29 | E30: =E28+E29 | F30: =F28+F29 | G30: =G28+G29 | H30: =H28+H29 | I30: =I28+I29 | J30: =J28+J29 | K30: =K28+K29 | ... M30: =M28+M29
A32: Selling, general & administrative | D32: =-'SOURCE WIFI Income Statement'!B65 | E32: =-'SOURCE WIFI Income Statement'!C65 | F32: =-'SOURCE WIFI Income Statement'!D65 | G32: =-'SOURCE WIFI Income Statement'!E65 | H32: =-'SOURCE WIFI Income Statement'!F65 | I32: =-I28*I9 | J32: =-J28*J9 | K32: =-K28*K9 | L32: =-L28*L9 | M32: =-M28*M9
A33: Other operating expense/(income) | D33: =-'SOURCE WIFI Income Statement'!B81 | E33: =-'SOURCE WIFI Income Statement'!C81 | F33: =-'SOURCE WIFI Income Statement'!D81 | G33: =-'SOURCE WIFI Income Statement'!E81 | H33: =-'SOURCE WIFI Income Statement'!F81 | I33: =-I28*I10 | J33: =-J28*J10 | K33: =-K28*K10 | L33: =-L28*L10 | M33: =-M28*M10
A34: EBIT (operating profit) | D34: =D30+D32+D33 | E34: =E30+E32+E33 | F34: =F30+F32+F33 | G34: =G30+G32+G33 | H34: =H30+H32+H33 | I34: =I30+I32+I33 | J34: =J30+J32+J33 | K34: =K30+K32+K33 | ... M34: =M30+M32+M33
A36: Add: depreciation & amortisation | D36: ='SOURCE WIFI Income Statement'!B295 | E36: ='SOURCE WIFI Income Statement'!C295 | F36: ='SOURCE WIFI Income Statement'!D295 | G36: ='SOURCE WIFI Income Statement'!E295 | H36: ='SOURCE WIFI Income Statement'!F295 | I36: =-I109 | J36: =-J109 | K36: =-K109 | L36: =-L109 | M36: =-M109
A37: EBITDA | D37: =D34+D36 | E37: =E34+E36 | F37: =F34+F36 | G37: =G34+G36 | H37: =H34+H36 | I37: =I34+I36 | J37: =J34+J36 | K37: =K34+K36 | ... M37: =M34+M36
A39: Interest expense | D39: =-'SOURCE WIFI Income Statement'!B372 | E39: =-'SOURCE WIFI Income Statement'!C372 | F39: =-'SOURCE WIFI Income Statement'!D372 | G39: =-'SOURCE WIFI Income Statement'!E372 | H39: =-'SOURCE WIFI Income Statement'!F372 | I39: =-I20*I125 | J39: =-J20*J125 | K39: =-K20*K125 | L39: =-L20*L125 | M39: =-M20*M125
A40: Interest income | D40: ='SOURCE WIFI Income Statement'!B94 | E40: ='SOURCE WIFI Income Statement'!C94 | F40: ='SOURCE WIFI Income Statement'!D94 | G40: ='SOURCE WIFI Income Statement'!E94 | H40: ='SOURCE WIFI Income Statement'!F94 | I40: =I21*H51 | J40: =J21*I51 | K40: =K21*J51 | L40: =L21*K51 | M40: =M21*L51
A41: Other non-operating income/(expense) | D41: ='SOURCE WIFI Income Statement'!B100+'SOURCE WIFI Income Statement'!B121+'SOURCE WIFI Income Statement'!B107 | E41: ='SOURCE WIFI Income Statement'!C100+'SOURCE WIFI Income Statement'!C121+'SOURCE WIFI Income Statement'!C107 | F41: ='SOURCE WIFI Income Statement'!D100+'SOURCE WIFI Income Statement'!D121+'SOURCE WIFI Income Statement'!D107 | G41: ='SOURCE WIFI Income Statement'!E100+'SOURCE WIFI Income Statement'!E121+'SOURCE WIFI Income Statement'!E107 | H41: ='SOURCE WIFI Income Statement'!F100+'SOURCE WIFI Income Statement'!F121+'SOURCE WIFI Income Statement'!F107 | I41: =0 | J41: =0 | K41: =0 | L41: =0 | M41: =0
A42: Pre-tax profit (EBT) | D42: =D34+D39+D40+D41 | E42: =E34+E39+E40+E41 | F42: =F34+F39+F40+F41 | G42: =G34+G39+G40+G41 | H42: =H34+H39+H40+H41 | I42: =I34+I39+I40+I41 | J42: =J34+J39+J40+J41 | K42: =K34+K39+K40+K41 | ... M42: =M34+M39+M40+M41
A43: Income tax | D43: =-'SOURCE WIFI Income Statement'!B159 | E43: =-'SOURCE WIFI Income Statement'!C159 | F43: =-'SOURCE WIFI Income Statement'!D159 | G43: =-'SOURCE WIFI Income Statement'!E159 | H43: =-'SOURCE WIFI Income Statement'!F159 | I43: =-I42*I19 | J43: =-J42*J19 | K43: =-K42*K19 | L43: =-L42*L19 | M43: =-M42*M19
A44: Net income before minority | D44: =D42+D43 | E44: =E42+E43 | F44: =F42+F43 | G44: =G42+G43 | H44: =H42+H43 | I44: =I42+I43 | J44: =J42+J43 | K44: =K42+K43 | ... M44: =M42+M43
A45: Minority interest | D45: =-'SOURCE WIFI Income Statement'!B197 | E45: =-'SOURCE WIFI Income Statement'!C197 | F45: =-'SOURCE WIFI Income Statement'!D197 | G45: =-'SOURCE WIFI Income Statement'!E197 | H45: =-'SOURCE WIFI Income Statement'!F197 | I45: =-I44*I23 | J45: =-J44*J23 | K45: =-K44*K23 | L45: =-L44*L23 | M45: =-M44*M23
A46: Net income to parent | D46: =D44+D45 | E46: =E44+E45 | F46: =F44+F45 | G46: =G44+G45 | H46: =H44+H45 | I46: =I44+I45 | J46: =J44+J45 | K46: =K44+K45 | ... M46: =M44+M45
H47: =H46/H28 | I47: =I46/I28 | J47: =J46/J28 | K47: =K46/K28 | L47: =L46/L28 | M47: =M46/M28
A49: BALANCE SHEET
A50: Assets
A51: Cash & equivalents | D51: ='SOURCE WIFI Balance Sheet'!B21 | E51: ='SOURCE WIFI Balance Sheet'!C21 | F51: ='SOURCE WIFI Balance Sheet'!D21 | G51: ='SOURCE WIFI Balance Sheet'!E21 | H51: ='SOURCE WIFI Balance Sheet'!F21 | I51: =I80-I61-I52-I53-I54-I55 | J51: =J80-J61-J52-J53-J54-J55 | K51: =K80-K61-K52-K53-K54-K55 | L51: =L80-L61-L52-L53-L54-L55 | M51: =M80-M61-M52-M53-M54-M55
A52: Receivables | D52: ='SOURCE WIFI Balance Sheet'!B26 | E52: ='SOURCE WIFI Balance Sheet'!C26 | F52: ='SOURCE WIFI Balance Sheet'!D26 | G52: ='SOURCE WIFI Balance Sheet'!E26 | H52: ='SOURCE WIFI Balance Sheet'!F26 | I52: =I13/365*I28 | J52: =J13/365*J28 | K52: =K13/365*K28 | L52: =L13/365*L28 | M52: =M13/365*M28
A53: Inventories | D53: ='SOURCE WIFI Balance Sheet'!B36 | E53: ='SOURCE WIFI Balance Sheet'!C36 | F53: ='SOURCE WIFI Balance Sheet'!D36 | G53: ='SOURCE WIFI Balance Sheet'!E36 | H53: ='SOURCE WIFI Balance Sheet'!F36 | I53: =I14/365*-I29 | J53: =J14/365*-J29 | K53: =K14/365*-K29 | L53: =L14/365*-L29 | M53: =M14/365*-M29
A54: Prepaid expenses | D54: ='SOURCE WIFI Balance Sheet'!B45 | E54: ='SOURCE WIFI Balance Sheet'!C45 | F54: ='SOURCE WIFI Balance Sheet'!D45 | G54: ='SOURCE WIFI Balance Sheet'!E45 | H54: ='SOURCE WIFI Balance Sheet'!F45 | I54: =I15*I28 | J54: =J15*J28 | K54: =K15*K28 | L54: =L15*L28 | M54: =M15*M28
A55: Other current assets | D55: ='SOURCE WIFI Balance Sheet'!B47 | E55: ='SOURCE WIFI Balance Sheet'!C47 | F55: ='SOURCE WIFI Balance Sheet'!D47 | G55: ='SOURCE WIFI Balance Sheet'!E47 | H55: ='SOURCE WIFI Balance Sheet'!F47 | I55: =H55 | J55: =I55 | K55: =J55 | L55: =K55 | M55: =L55
A56: Total current assets | D56: =SUM(D51:D55) | E56: =SUM(E51:E55) | F56: =SUM(F51:F55) | G56: =SUM(G51:G55) | H56: =SUM(H51:H55) | I56: =SUM(I51:I55) | J56: =SUM(J51:J55) | K56: =SUM(K51:K55) | ... M56: =SUM(M51:M55)
A58: Net property, plant & equipment | D58: ='SOURCE WIFI Balance Sheet'!B71 | E58: ='SOURCE WIFI Balance Sheet'!C71 | F58: ='SOURCE WIFI Balance Sheet'!D71 | G58: ='SOURCE WIFI Balance Sheet'!E71 | H58: ='SOURCE WIFI Balance Sheet'!F71 | I58: =I110 | J58: =J110 | K58: =K110 | L58: =L110 | M58: =M110
A59: Intangible assets | D59: ='SOURCE WIFI Balance Sheet'!B138 | E59: ='SOURCE WIFI Balance Sheet'!C138 | F59: ='SOURCE WIFI Balance Sheet'!D138 | G59: ='SOURCE WIFI Balance Sheet'!E138 | H59: ='SOURCE WIFI Balance Sheet'!F138 | I59: =H59 | J59: =I59 | K59: =J59 | L59: =K59 | M59: =L59
A60: Other non-current assets | D60: ='SOURCE WIFI Balance Sheet'!B129+'SOURCE WIFI Balance Sheet'!B63 | E60: ='SOURCE WIFI Balance Sheet'!C129+'SOURCE WIFI Balance Sheet'!C63 | F60: ='SOURCE WIFI Balance Sheet'!D129+'SOURCE WIFI Balance Sheet'!D63 | G60: ='SOURCE WIFI Balance Sheet'!E129+'SOURCE WIFI Balance Sheet'!E63 | H60: ='SOURCE WIFI Balance Sheet'!F129+'SOURCE WIFI Balance Sheet'!F63 | I60: =H60 | J60: =I60 | K60: =J60 | L60: =K60 | M60: =L60
A61: Total non-current assets | D61: =SUM(D58:D60) | E61: =SUM(E58:E60) | F61: =SUM(F58:F60) | G61: =SUM(G58:G60) | H61: =SUM(H58:H60) | I61: =SUM(I58:I60) | J61: =SUM(J58:J60) | K61: =SUM(K58:K60) | ... M61: =SUM(M58:M60)
A62: TOTAL ASSETS | D62: =D56+D61 | E62: =E56+E61 | F62: =F56+F61 | G62: =G56+G61 | H62: =H56+H61 | I62: =I56+I61 | J62: =J56+J61 | K62: =K56+K61 | ... M62: =M56+M61
A64: Liabilities
A65: Accounts payable | D65: ='SOURCE WIFI Balance Sheet'!B169 | E65: ='SOURCE WIFI Balance Sheet'!C169 | F65: ='SOURCE WIFI Balance Sheet'!D169 | G65: ='SOURCE WIFI Balance Sheet'!E169 | H65: ='SOURCE WIFI Balance Sheet'!F169 | I65: =I16/365*-I29 | J65: =J16/365*-J29 | K65: =K16/365*-K29 | L65: =L16/365*-L29 | M65: =M16/365*-M29
A66: Short-term debt | D66: ='SOURCE WIFI Balance Sheet'!B172 | E66: ='SOURCE WIFI Balance Sheet'!C172 | F66: ='SOURCE WIFI Balance Sheet'!D172 | G66: ='SOURCE WIFI Balance Sheet'!E172 | H66: ='SOURCE WIFI Balance Sheet'!F172 | I66: =H66 | J66: =I66 | K66: =J66 | L66: =K66 | M66: =L66
A67: Income tax payable | D67: ='SOURCE WIFI Balance Sheet'!B181 | E67: ='SOURCE WIFI Balance Sheet'!C181 | F67: ='SOURCE WIFI Balance Sheet'!D181 | G67: ='SOURCE WIFI Balance Sheet'!E181 | H67: ='SOURCE WIFI Balance Sheet'!F181 | I67: =I18*-I43 | J67: =J18*-J43 | K67: =K18*-K43 | L67: =L18*-L43 | M67: =M18*-M43
A68: Other current liabilities | D68: ='SOURCE WIFI Balance Sheet'!B184 | E68: ='SOURCE WIFI Balance Sheet'!C184 | F68: ='SOURCE WIFI Balance Sheet'!D184 | G68: ='SOURCE WIFI Balance Sheet'!E184 | H68: ='SOURCE WIFI Balance Sheet'!F184 | I68: =I17*I28 | J68: =J17*J28 | K68: =K17*K28 | L68: =L17*L28 | M68: =M17*M28
A69: Total current liabilities | D69: =SUM(D65:D68) | E69: =SUM(E65:E68) | F69: =SUM(F65:F68) | G69: =SUM(G65:G68) | H69: =SUM(H65:H68) | I69: =SUM(I65:I68) | J69: =SUM(J65:J68) | K69: =SUM(K65:K68) | ... M69: =SUM(M65:M68)
A71: Long-term debt | D71: ='SOURCE WIFI Balance Sheet'!B198 | E71: ='SOURCE WIFI Balance Sheet'!C198 | F71: ='SOURCE WIFI Balance Sheet'!D198 | G71: ='SOURCE WIFI Balance Sheet'!E198 | H71: ='SOURCE WIFI Balance Sheet'!F198 | I71: =H71+I22 | J71: =I71+J22 | K71: =J71+K22 | L71: =K71+L22 | M71: =L71+M22
A72: Deferred tax & other LT liabilities | D72: ='SOURCE WIFI Balance Sheet'!B210+'SOURCE WIFI Balance Sheet'!B214 | E72: ='SOURCE WIFI Balance Sheet'!C210+'SOURCE WIFI Balance Sheet'!C214 | F72: ='SOURCE WIFI Balance Sheet'!D210+'SOURCE WIFI Balance Sheet'!D214 | G72: ='SOURCE WIFI Balance Sheet'!E210+'SOURCE WIFI Balance Sheet'!E214 | H72: ='SOURCE WIFI Balance Sheet'!F210+'SOURCE WIFI Balance Sheet'!F214 | I72: =H72 | J72: =I72 | K72: =J72 | L72: =K72 | M72: =L72
A73: Total non-current liabilities | D73: =D71+D72 | E73: =E71+E72 | F73: =F71+F72 | G73: =G71+G72 | H73: =H71+H72 | I73: =I71+I72 | J73: =J71+J72 | K73: =K71+K72 | ... M73: =M71+M72
A74: TOTAL LIABILITIES | D74: =D69+D73 | E74: =E69+E73 | F74: =F69+F73 | G74: =G69+G73 | H74: =H69+H73 | I74: =I69+I73 | J74: =J69+J73 | K74: =K69+K73 | ... M74: =M69+M73
A76: Common equity (contributed) | D76: ='SOURCE WIFI Balance Sheet'!B245 | E76: ='SOURCE WIFI Balance Sheet'!C245 | F76: ='SOURCE WIFI Balance Sheet'!D245 | G76: ='SOURCE WIFI Balance Sheet'!E245 | H76: ='SOURCE WIFI Balance Sheet'!F245 | I76: =H76 | J76: =I76 | K76: =J76 | L76: =K76 | M76: =L76
A77: Retained earnings & reserves | D77: ='SOURCE WIFI Balance Sheet'!B250 | E77: ='SOURCE WIFI Balance Sheet'!C250 | F77: ='SOURCE WIFI Balance Sheet'!D250 | G77: ='SOURCE WIFI Balance Sheet'!E250 | H77: ='SOURCE WIFI Balance Sheet'!F250 | I77: =H77+I46+I95 | J77: =I77+J46+J95 | K77: =J77+K46+K95 | L77: =K77+L46+L95 | M77: =L77+M46+M95
A78: Minority interest | D78: ='SOURCE WIFI Balance Sheet'!B268 | E78: ='SOURCE WIFI Balance Sheet'!C268 | F78: ='SOURCE WIFI Balance Sheet'!D268 | G78: ='SOURCE WIFI Balance Sheet'!E268 | H78: ='SOURCE WIFI Balance Sheet'!F268 | I78: =H78-I45 | J78: =I78-J45 | K78: =J78-K45 | L78: =K78-L45 | M78: =L78-M45
A79: TOTAL EQUITY | D79: =SUM(D76:D78) | E79: =SUM(E76:E78) | F79: =SUM(F76:F78) | G79: =SUM(G76:G78) | H79: =SUM(H76:H78) | I79: =SUM(I76:I78) | J79: =SUM(J76:J78) | K79: =SUM(K76:K78) | ... M79: =SUM(M76:M78)
A80: TOTAL LIABILITIES & EQUITY | D80: =D74+D79 | E80: =E74+E79 | F80: =F74+F79 | G80: =G74+G79 | H80: =H74+H79 | I80: =I74+I79 | J80: =J74+J79 | K80: =K74+K79 | ... M80: =M74+M79
A81: Balance check (Assets - L&E) | D81: =D62-D80 | E81: =E62-E80 | F81: =F62-F80 | G81: =G62-G80 | H81: =H62-H80 | I81: =I62-I80 | J81: =J62-J80 | K81: =K62-K80 | ... M81: =M62-M80
A84: CASH FLOW STATEMENT
A85: Net income before minority | I85: =I44 | J85: =J44 | K85: =K44 | L85: =L44 | M85: =M44
A86: Add: depreciation & amortisation | I86: =I36 | J86: =J36 | K86: =K36 | L86: =L36 | M86: =M36
A87: Change in net working capital | I87: =I120 | J87: =J120 | K87: =K120 | L87: =L120 | M87: =M120
A88: Cash flow from operations | I88: =SUM(I85:I87) | J88: =SUM(J85:J87) | K88: =SUM(K85:K87) | L88: =SUM(L85:L87) | M88: =SUM(M85:M87)
A90: Capital expenditure | D90: 2.9772174e+08 | E90: 4.5423417e+08 | F90: 3.2519817e+08 | G90: 1.477352e+09 | H90: 3.2753253e+09 | I90: =-I108 | J90: =-J108 | K90: =-K108 | L90: =-L108 | M90: =-M108
A91: Change in intangibles & other NCA | I91: =-((I59-H59)+(I60-H60)) | J91: =-((J59-I59)+(J60-I60)) | K91: =-((K59-J59)+(K60-J60)) | L91: =-((L59-K59)+(L60-K60)) | M91: =-((M59-L59)+(M60-L60))
A92: Cash flow from investing | I92: =I90+I91 | J92: =J90+J91 | K92: =K90+K91 | L92: =L90+L91 | M92: =M90+M91
A94: Net debt issuance/(repayment) | I94: =(I66-H66)+(I71-H71) | J94: =(J66-I66)+(J71-I71) | K94: =(K66-J66)+(K71-J71) | L94: =(L66-K66)+(L71-K71) | M94: =(M66-L66)+(M71-L71)
A95: Dividends paid | I95: =-I24*I46 | J95: =-J24*J46 | K95: =-K24*K46 | L95: =-L24*L46 | M95: =-M24*M46
A96: Change in other LT liabilities | I96: =I72-H72 | J96: =J72-I72 | K96: =K72-J72 | L96: =L72-K72 | M96: =M72-L72
A97: Cash flow from financing | I97: =I94+I95+I96 | J97: =J94+J95+J96 | K97: =K94+K95+K96 | L97: =L94+L95+L96 | M97: =M94+M95+M96
A98: Net change in cash | I98: =I88+I92+I97 | J98: =J88+J92+J97 | K98: =K88+K92+K97 | L98: =L88+L92+L97 | M98: =M88+M92+M97
A99: Beginning cash | I99: =H51 | J99: =I51 | K99: =J51 | L99: =K51 | M99: =L51
A100: Ending cash | I100: =I99+I98 | J100: =J99+J98 | K100: =K99+K98 | L100: =L99+L98 | M100: =M99+M98
A101: Cash flow tie (Ending - BS cash) | I101: =I100-I51 | J101: =J100-J51 | K101: =K100-K51 | L101: =L100-L51 | M101: =M100-M51
A104: SUPPORTING SCHEDULES
A106: PPE roll-forward
A107: Opening net PPE | I107: =H58 | J107: =I58 | K107: =J58 | L107: =K58 | M107: =L58
A108: Plus: capex | I108: =I171 | J108: =J171 | K108: =K171 | L108: =L171 | M108: =M171
A109: Less: depreciation & amortisation | I109: =-I11*I107 | J109: =-J11*J107 | K109: =-K11*K107 | L109: =-L11*L107 | M109: =-M11*M107
A110: Closing net PPE | I110: =I107+I108+I109 | J110: =J107+J108+J109 | K110: =K107+K108+K109 | L110: =L107+L108+L109 | M110: =M107+M108+M109
A112: Working capital schedule
A113: Receivables | D113: =D52 | E113: =E52 | F113: =F52 | G113: =G52 | H113: =H52 | I113: =I52 | J113: =J52 | K113: =K52 | ... M113: =M52
A114: Inventories | D114: =D53 | E114: =E53 | F114: =F53 | G114: =G53 | H114: =H53 | I114: =I53 | J114: =J53 | K114: =K53 | ... M114: =M53
A115: Prepaid expenses | D115: =D54 | E115: =E54 | F115: =F54 | G115: =G54 | H115: =H54 | I115: =I54 | J115: =J54 | K115: =K54 | ... M115: =M54
A116: Other current assets | D116: =D55 | E116: =E55 | F116: =F55 | G116: =G55 | H116: =H55 | I116: =I55 | J116: =J55 | K116: =K55 | ... M116: =M55
A117: less: Accounts payable | D117: =-D65 | E117: =-E65 | F117: =-F65 | G117: =-G65 | H117: =-H65 | I117: =-I65 | J117: =-J65 | K117: =-K65 | ... M117: =-M65
A118: less: Tax payable & other current liab. | D118: =-D67-D68 | E118: =-E67-E68 | F118: =-F67-F68 | G118: =-G67-G68 | H118: =-H67-H68 | I118: =-I67-I68 | J118: =-J67-J68 | K118: =-K67-K68 | ... M118: =-M67-M68
...

Sheet TOWR VALUATION
A1: TOWR | Valuation
C2: 2026 | D2: =C2+1 | E2: =D2+1 | F2: =E2+1 | G2: =F2+1
A4: Assumptions
A5: Tax Rate | C5: =22%
A6: Discount Rate | C6: ='TOWR WACC'!D9
A7: Terminal Growth Rate (Inflation Rate) | C7: 0.02
A8: EV/EBITDA Multiple | C8: 9.37
A9: Margin of Safety | C9: 0.15
A11: Discounted Cash Flow (FCFF) | C11: 2026 | D11: =C11+1 | E11: =D11+1 | F11: =E11+1 | G11: =F11+1 | H11: Terminal Value
C12: 1 | D12: 2 | E12: 3 | F12: 4 | G12: 5 | H12: 5
A13: EBIT | C13: ='TOWR-3-Statements'!H38 | D13: ='TOWR-3-Statements'!I38 | E13: ='TOWR-3-Statements'!J38 | F13: ='TOWR-3-Statements'!K38 | G13: ='TOWR-3-Statements'!L38
A14: Tax Rate | C14: 0.22 | D14: 0.22 | E14: 0.22 | F14: 0.22 | G14: 0.22
A15: NOPAT | C15: =C13*(1-C14) | D15: =D13*(1-D14) | E15: =E13*(1-E14) | F15: =F13*(1-F14) | G15: =G13*(1-G14)
A16: Add : Depreciation and Amortization | C16: ='TOWR-3-Statements'!H40 | D16: ='TOWR-3-Statements'!I40 | E16: ='TOWR-3-Statements'!J40 | F16: ='TOWR-3-Statements'!K40 | G16: ='TOWR-3-Statements'!L40
A17: Less : Capex | C17: ='TOWR-3-Statements'!H114 | D17: ='TOWR-3-Statements'!I114 | E17: ='TOWR-3-Statements'!J114 | F17: ='TOWR-3-Statements'!K114 | G17: ='TOWR-3-Statements'!L114
A18: Less : Changes in NWC | C18: ='TOWR-3-Statements'!H110 | D18: ='TOWR-3-Statements'!I110 | E18: ='TOWR-3-Statements'!J110 | F18: ='TOWR-3-Statements'!K110 | G18: ='TOWR-3-Statements'!L110
A19: Free Cashflow to Firm (FCFF) | C19: =SUM(C15:C18) | D19: =SUM(D15:D18) | E19: =SUM(E15:E18) | F19: =SUM(F15:F18) | G19: =SUM(G15:G18) | H19: =(G19*(1+C7)/(C6-C7))
A21: PV of FCFF | C21: =C19/((1+$C$6)^C12) | D21: =D19/((1+$C$6)^D12) | E21: =E19/((1+$C$6)^E12) | F21: =F19/((1+$C$6)^F12) | G21: =G19/((1+$C$6)^G12) | H21: =H19/((1+$C$6)^H12)
A23: Enterprise Value | H23: =SUM(C21:H21)
A24: Less : Debt | H24: ='TOWR-3-Statements'!G87+'TOWR-3-Statements'!G80
A25: Add : Cash | H25: ='TOWR-3-Statements'!G59
A26: Equity Value | H26: =H23-H24+H25
A27: Shares Outstanding | H27: 59100000000
A28: Target Price | H28: =H26/H27*1000
A29: Current Share Price | H29: 434
A30: Upside Potential | H30: =H28/H29-1
A32: Relative Valuation (Comparable Company Analysis)
A34: Current Price (IDR) | D34: 434
A35: Shares Outstanding | D35: =H27
A37: EV/EBITDA
A38: MTEL.IJ | D38: 8.6
A39: TBIG.IJ | D39: 11.4
A40: BALI.IJ | D40: 10.4
A41: GHON.IJ | D41: 11.4
A42: Average | D42: =AVERAGE(D38:D41)
A43: EBITDA | D43: ='TOWR-3-Statements'!G41
A45: Forward EV/EBITDA Multiple | D45: =D42
A46: Enterprise Value | D46: =D45*D43
A47: Less: Debt | D47: =H24
A48: Plus: Cash | D48: =H25
A49: Equity Value | D49: =D46-D47+D48
A50: Shares Outstanding | D50: =D35
A51: Target Price | D51: =D49/D50*1000
A52: Current Share Price | D52: 434
A53: Upside Potential | D53: =D51/D52-1
A56: Tower Segment - EV/Tower Multiple (Precedent Transaction)
A58: EV/Tower (in Rp billions )
A59: ='TOWR WIFI-Comparable Precedent'!L5 | D59: ='TOWR WIFI-Comparable Precedent'!O5
A60: Inti Bangun Sejahtera (IBST) 90.11% | D60: ='TOWR WIFI-Comparable Precedent'!O6
A61: 3000 unit of IBST's Tower | D61: ='TOWR WIFI-Comparable Precedent'!O7
A62: 6000 unit of Telkomsel's Tower | D62: ='TOWR WIFI-Comparable Precedent'!O8
A63: Average | D63: =AVERAGE(D59:D62)
A64: Tower Sites | D64: ='TOWR-3-Statements'!G131
A65: Enterprise Value | D65: =D63*D64*1000000
A68: Fiber and Connectivity Segment - EV / EBITDA Multiple
A70: EV/EBITDA
A71: LINK.JK | D71: ='TOWR WIFI-Comparable Precedent'!E40
A72: DATA.JK | D72: ='TOWR WIFI-Comparable Precedent'!E41
A73: INET.JK | D73: ='TOWR WIFI-Comparable Precedent'!E42
A74: EDGE.JK | D74: ='TOWR WIFI-Comparable Precedent'!E43
A75: WIFI.JK | D75: ='TOWR WIFI-Comparable Precedent'!E52
A76: Median | D76: =MEDIAN(D71:D75)
A77: Fiber and Connectivity EBITDA | D77: 3109993
A78: Enterprise Value | D78: =D76*D77*1000
A80: Sum of the Parts Valuation
A82: Business Segment | C82: Method | D82: Implied Enterprise Value
A83: Tower Segment | C83: EV/Tower | D83: =D65
A84: Fiber and Connectivity Segment | C84: EV/EBITDA | D84: =D78
A85: Total Enterprise Value | D85: =D83+D84
A86: Less: Debt | D86: =H24
A87: Plus: Cash | D87: =H25
A88: Equity Value | D88: =D85-D86+D87
A89: Shares Outstanding | D89: =H27
A90: Target Price | D90: =D88/D89*1000
A91: Current Share Price | D91: 434
A92: Upside Potential | D92: =D90/D91-1
A95: Blended Valuation
A96: Method | B96: Value | C96: Weighting | D96: Ending Value
A97: =A11 | B97: =H28 | C97: 0.7 | D97: =B97*C97
A98: Relative (EV/EBITDA) | B98: =D51 | C98: 0.15 | D98: =B98*C98
A99: Sum-of-the-parts (EV/Tower, EV/EBITDA) | B99: =D90 | C99: 0.15 | D99: =B99*C99
A100: Target Price | D100: =SUM(D97:D99)
A101: =A91 | D101: =D91
A102: =A92 | D102: =D100/D101-1

Sheet TOWR WACC
A1: TOWR
A3: Weighted Average Cost of Capital
A5: Debt-to-Asset | D5: ='TOWR-3-Statements'!G92/'TOWR-3-Statements'!G75
A6: Equity-to-Asset | D6: =1-D5
A7: Cost of Equity (Ke) | D7: =D24
A8: Cost of Debt (Kd) | D8: =D17
A9: Weighted Average Cost of Capital | D9: =D5*D8+D6*D7
A11: Cost of Debt
A13: Interest Expense | D13: ='TOWR-3-Statements'!G218
A14: Average Total Debt | D14: =('TOWR-3-Statements'!G80+'TOWR-3-Statements'!G87+'TOWR-3-Statements'!F87+'TOWR-3-Statements'!F79)/2
A15: Pre-tax Cost of Debt | D15: =D13/D14*-1
A16: Tax Rate | D16: 0.22
A17: After Tax Cost of debt | D17: =D15*(1-D16)
A19: Cost of Debt
A21: Risk Free Rate (Indonesia 10Y Government Bond) | D21: 0.0696
A22: Equity Risk Premium | D22: 0.0669
A23: Beta | D23: ='BETA TOWR'!L3
A24: Cost of Equity | D24: =D21+D23*(D22)

Sheet SOURCE TOWR Income Statement
A1: Company Fundamentals - Income Statement
A2: Company Name | B2: Sarana Menara Nusantara Tbk PT (TOWR.JK)
A3: Country of Exchange | B3: Indonesia
A4: Country of Headquarters | B4: Indonesia
A5: TRBC Industry Group | B5: Telecommunications Services
A6: CF Template | B6: IND
A7: Consolidation Basis | B7: Consolidated
A8: Scaling | B8: Thousands
A9: Period | B9: Annual
A10: Export Date | B10: 46247.281
A11: Statement Data | B11: 2020 | C11: 2021 | D11: 2022 | E11: 2023 | F11: 2024 | G11: 2025
A12: Period End Date | B12: 44196 | C12: 44561 | D12: 44926 | E12: 45291 | F12: 45657 | G12: 46022
A13: Standardized Currency | B13: IDR | C13: IDR | D13: IDR | E13: IDR | F13: IDR | G13: IDR
A14: Statement Date | B14: 44196 | C14: 44561 | D14: 44926 | E14: 45291 | F14: 45657 | G14: 46022
A15: Complete Statement | B15: Complete | C15: Complete | D15: Complete | E15: Complete | F15: Complete | G15: Complete
A16: Consolidated | B16: Consolidated | C16: Consolidated | D16: Consolidated | E16: Consolidated | F16: Consolidated | G16: Consolidated
A17: Accounting Standard | B17: Indonesian | C17: Indonesian | D17: Indonesian | E17: Indonesian | F17: Indonesian | G17: Indonesian
A18: Income Statement - Standardized (Currency: Indonesia Rupiah)
A19: Field Name | B19: 31-12-2020 | C19: 31-12-2021 | D19: 31-12-2022 | E19: 31-12-2023 | F19: 31-12-2024 | G19: 31-12-2025
A20: Revenues
A21: Revenue from Goods & Services | B21: 7445426000 | C21: 8635346000 | D21: 11035650000 | E21: 11740345000 | F21: 12735815000 | G21: 13327907000
A22: Sales of Goods & Services - Net - Unclassified | B22: 7445426000 | C22: 8635346000 | D22: 11035650000 | E22: 11740345000 | F22: 12735815000 | G22: 13327907000
A23: Hotel Revenue
A24: Hotel Revenue - Rooms
A25: Hotel Revenue - Hotel Lease Income
A26: Hotel Revenue - Food & Beverages
A27: Hotel Revenue - Other
A28: Utility Revenue - Total
A29: Utility Revenue - Other Utility Operations
A30: Utility Revenue - Steam Operations
A31: Utility Revenue - Water Operations
A32: Utility Revenue - Gas Operations
A33: Utility Revenue - Electric Operations
A34: Utility Revenue - Non-Utility Operations
... A42: Royalty Income - Business
A43: Revenue from Business Activities - Total | B43: 7445426000 | C43: 8635346000 | D43: 11035650000 | E43: 11740345000 | F43: 12735815000 | G43: 13327907000
A44: Operating Expenses
A45: Cost of Operating Revenue | B45: 2059254000 | C45: 2340173000 | D45: 2914450000 | E45: 3527754000 | F45: 3996322000 | G45: 4188377000
A46: Cost of Financing-Related Operations
A47: Cost of Revenues - Total | B47: 2059254000 | C47: 2340173000 | D47: 2914450000 | E47: 3527754000 | F47: 3996322000 | G47: 4188377000
A48: Cost of Revenues - Unclassified | B48: 415240000 | C48: 480354000 | D48: 607770000 | E48: 684486000 | F48: 898595000 | G48: 1115112000
A49: Production Taxes & Royalty Expenses
A50: Amortization in Cost of Revenues | B50: 215644000 | C50: 222157000 | D50: 246177000 | E50: 270216000 | F50: 297992000 | G50: 202480000
A51: Depreciation in Cost of Revenues | B51: 1428370000 | C51: 1637662000 | D51: 2060503000 | E51: 2573052000 | F51: 2799735000 | G51: 2870785000
A52: Labor & Related Expenses including Stock-Based Compensation in Cost of Revenues
A53: Material Expenses
A54: Material Expenses - Materials, Inventory, Own Work & Utility - Unclassified
A55: Utility Cost of Revenue - Fuel Expense
A56: Utility Cost of Revenue - Fuel Purchased for Resale
A57: Utility Cost of Revenue - Purchased Power
A58: Own Work Capitalized
A59: Changes in Inventory
A60: Materials Purchased
A61: Ground leases/Rental Expenses in Cost of Revenues
A62: Property Operating Expenses - Hotel
A63: Cost of Revenues - Other - Total
A64: Gross Profit - Industrials/Property - Total | B64: 5386172000 | C64: 6295173000 | D64: 8121200000 | E64: 8212591000 | F64: 8739493000 | G64: 9139530000
A65: Selling, General & Administrative Expenses - Total | B65: 592782000 | C65: 707120000 | D65: 916111000 | E65: 1119731000 | F65: 1217595000 | G65: 1211640000
A66: Selling, General & Administrative Expenses - Unclassified | B66: 205878000 | C66: 250154000 | D66: 230432000 | E66: 243340000 | F66: 295836000 | G66: 313724000
A67: Labor & Related Expenses including Stock-Based Compensation in Selling, General & Administrative Expenses | B67: 419388000 | C67: 470514000 | D67: 680892000 | E67: 788501000 | F67: 818343000 | G67: 917491000
A68: Research & Development Expense
A69: Exploration/Dry Hole Expenses (including Write-Off)
A70: Depreciation in Selling, General & Administrative Expenses
A71: Amortization of Intangibles in Selling, General & Administrative Expenses
A72: Operations & Maintenance (Utility)
A73: Selling, General & Administrative Expenses - Other - Total | B73: -32484000 | C73: -13548000 | D73: 4787000 | E73: 87890000 | F73: 103416000 | G73: -19575000
A74: Advertising Expense
A75: Property & Other Taxes | F75: 123833000 | G75: 14583000
A76: Rental Expense
A77: Occupancy Expense - Other
A78: Pre-Opening Expenses
A79: Provision for Doubtful Accounts & Write-off | B79: -32484000 | C79: -13548000 | D79: 4787000 | E79: 43435000 | F79: -43315000 | G79: -45280000
A80: Equipment/Occupancy Expense - Bank/Financial - Other
A81: Other Operating Expense/(Income) - Net | B81: 22690000 | C81: 167429000 | D81: 88975000 | E81: -56826000 | F81: 70469000 | G81: 77056000
A82: Other Operating Income - Total
A83: Other Operating Expense
A84: Provision for Decommissioning Fund & Environmental Obligations
A85: Operating Provisions - Increase/(Decrease)
A86: Non-Recurring Adjustments - Operating - Decrease/(Increase)
A87: Supplementary Adjustments - Operating - Decrease/(Increase)
A88: Operating Expenses - Total | B88: 2674726000 | C88: 3214722000 | D88: 3919536000 | E88: 4590659000 | F88: 5284386000 | G88: 5477073000
A89: Operating Profit
A90: Operating Profit before Non-Recurring Income/Expense | B90: 4770700000 | C90: 5420624000 | D90: 7116114000 | E90: 7149686000 | F90: 7451429000 | G90: 7850834000
A91: Non-Operating Expenses
A92: Financing Income/(Expense) - Net - Total | B92: -1266742000 | C92: -1281231000 | D92: -2404208000 | E92: -2797013000 | F92: -3021973000 | G92: -3086514000
A93: Interest Expense - Net of (Interest Income) | B93: 1050842000 | C93: 1254452000 | D93: 2280344000 | E93: 2694489000 | F93: 2940697000 | G93: 2831713000
A94: Interest Income - Non-Bank | B94: 33587000 | C94: 30866000 | D94: 29265000 | E94: 25649000 | F94: 84309000 | G94: 44354000
A95: Interest Expense - Net of Capitalized Interest | B95: 1084429000 | C95: 1285318000 | D95: 2309609000 | E95: 2720138000 | F95: 3025006000 | G95: 2876067000
A96: Interest Expense on Capital Financing - Gross
A97: Dividends on Hybrid Financial Instruments - Liability Portion
A98: Interest Capitalized
A99: Allowance for Funds Used during Construction - Debt Portion (AFUDC)
A100: Non-Interest Financial Income/(Expense) - Total | B100: -215900000 | C100: -26779000 | D100: -123864000 | E100: -102524000 | F100: -81276000 | G100: -254801000
A101: Dividend & Investment Income
A102: Foreign Exchange Gain/(Loss) - Non-Business | B102: -182776000 | C102: 8880000 | D102: -92842000 | E102: -14536000 | F102: -17317000 | G102: -83748000
A103: Amortization of Deferred Financing Charges
A104: Sale of Investments Held for Sale, Maturity & Trading - Gain/(Loss)
A105: Accretion - Site Closure & Reclamation Expenses
A106: Non-Interest Financial Income/(Expense) - Other - Net | B106: -33124000 | C106: -35659000 | D106: -31022000 | E106: -87988000 | F106: -63959000 | G106: -171053000
A107: Sale of Tangible & Intangible Fixed Assets - Gain/(Loss) | B107: -43365000 | C107: -84504000 | D107: -144699000 | E107: -173608000 | F107: -168191000 | G107: -269391000
...

Sheet SOURCE TOWR Balance Sheet
A1: Company Fundamentals - Balance Sheet
A2: Company Name | B2: Sarana Menara Nusantara Tbk PT (TOWR.JK)
A3: Country of Exchange | B3: Indonesia
A4: Country of Headquarters | B4: Indonesia
A5: TRBC Industry Group | B5: Telecommunications Services
A6: CF Template | B6: IND
A7: Consolidation Basis | B7: Consolidated
A8: Scaling | B8: Thousands
A9: Period | B9: Annual
A10: Export Date | B10: 46247.281
A11: Statement Data | B11: 2020 | C11: 2021 | D11: 2022 | E11: 2023 | F11: 2024 | G11: 2025
A12: Period End Date | B12: 44196 | C12: 44561 | D12: 44926 | E12: 45291 | F12: 45657 | G12: 46022
A13: Standardized Currency | B13: IDR | C13: IDR | D13: IDR | E13: IDR | F13: IDR | G13: IDR
A14: Statement Date | B14: 44196 | C14: 44561 | D14: 44926 | E14: 45291 | F14: 45657 | G14: 46022
A15: Complete Statement | B15: Complete | C15: Complete | D15: Complete | E15: Complete | F15: Complete | G15: Complete
A16: Consolidated | B16: Consolidated | C16: Consolidated | D16: Consolidated | E16: Consolidated | F16: Consolidated | G16: Consolidated
A17: Accounting Standard | B17: Indonesian | C17: Indonesian | D17: Indonesian | E17: Indonesian | F17: Indonesian | G17: Indonesian
A18: Balance Sheet - Standardized (Currency: Indonesia Rupiah)
A19: Field Name | B19: 31-12-2020 | C19: 31-12-2021 | D19: 31-12-2022 | E19: 31-12-2023 | F19: 31-12-2024 | G19: 31-12-2025
A20: Current Assets
A21: Cash & Short-Term Investments | B21: 1442627000 | C21: 4748364000 | D21: 342703000 | E21: 517126000 | F21: 979223000 | G21: 709858000
A22: Cash & Cash Equivalents | B22: 1442627000 | C22: 4748364000 | D22: 308636000 | E22: 428677000 | F22: 940183000 | G22: 647545000
A23: Short-Term Investments - Total | D23: 34067000 | E23: 88449000 | F23: 39040000 | G23: 62313000
A24: Financial Assets - Short-Term
A25: Derivative Financial Instruments - Hedging - Short-Term
A26: Loans & Receivables - Net - Short-Term | B26: 1275857000 | C26: 2184362000 | D26: 2615727000 | E26: 3145293000 | F26: 3564702000 | G26: 2220530000
A27: Trade Accounts & Trade Notes Receivable - Net | B27: 1240069000 | C27: 2171296000 | D27: 2557804000 | E27: 3086334000 | F27: 3292793000 | G27: 1973530000
A28: Trade Accounts & Trade Notes Receivable - Gross | B28: 1348589000 | C28: 2269848000 | D28: 2597461000 | E28: 3169354000 | F28: 3386022000 | G28: 2008853000
A29: Provision - Trade Accounts & Trade Notes Receivable | B29: 108520000 | C29: 98552000 | D29: 39657000 | E29: 83020000 | F29: 93229000 | G29: 35323000
A30: Unbilled Utility Revenue - Short-Term
A31: Loans - Short-Term | F31: 168639000 | G31: 175604000
A32: Income Tax - Receivables - Short-Term
A33: Receivables - Other - Total | B33: 35788000 | C33: 13066000 | D33: 57923000 | E33: 58959000 | F33: 103270000 | G33: 71396000
A34: Provision - Doubtful Accounts
A35: Receivables Over One Year included within Short-Term Receivables
A36: Inventories - Total | E36: 14572000 | F36: 15943000 | G36: 8517000
A37: Inventories - Raw Materials
A38: Inventories - Work in Progress
A39: Inventories - Finished Goods
A40: Inventories - Other - Total
A41: Inventories - Cost in excess of Billings
A42: Inventories - Gas in Storage
A43: Inventories - LIFO Reserve
A44: Biological Assets - Short-Term
A45: Prepaid Expenses - Short-Term | B45: 278899000 | C45: 463431000 | D45: 692688000 | E45: 749770000 | F45: 395437000 | G45: 488811000
A46: Assets Held for Sale/Discontinued Operations - Short-Term
A47: Other Current Assets - Total | B47: 4949000 | C47: 1981000 | D47: 16000 | E47: 122000 | F47: 535000 | G47: 5516000
A48: Deferred Tax - Asset - Short-Term
A49: Deferred Costs - Short-Term
A50: Restricted Accounts - Short-Term | B50: 4949000 | C50: 1981000 | D50: 16000 | E50: 122000 | F50: 535000 | G50: 5516000
A51: Regulatory Assets - Short-Term
A52: Other Current Assets
A53: Total Current Assets | B53: 3002332000 | C53: 7398138000 | D53: 3651134000 | E53: 4426883000 | F53: 4955840000 | G53: 3433232000
A54: Non-Current Assets
A55: Investments - Long-Term | B55: 476210000 | C55: 531308000 | D55: 506502000 | E55: 0
A56: Investment Property - Net
A57: Investment Property - Accumulated Depreciation & Impairment
A58: Investment Property - Gross
A59: Investments - Available for Sale/Held to Maturity - Long-Term | B59: 476210000 | C59: 531308000 | D59: 506502000 | E59: 0
A60: Marketable Securities - Long-Term
A61: Financial Assets - Long-Term
A62: Investments in Associates, Joint Ventures and Unconsolidated Subsidiaries | E62: 494088000 | F62: 571632000 | G62: 1225771000
A63: Receivables & Loans - Long-Term | B63: 26524000 | C63: 323304000 | D63: 283839000 | E63: 253419000 | F63: 1059168000 | G63: 512637000
A64: Accounts & Notes Receivable - Trade - Net - Long-Term | B64: 0 | C64: 0 | D64: -42748000 | E64: -42748000 | F64: -42748000 | G64: -42748000
A65: Accounts & Notes Receivable - Trade - Gross - Long-Term | B65: 339195000 | C65: 339195000 | D65: 824542000 | E65: 824542000 | F65: 856631000 | G65: 856631000
A66: Loans - Long-Term
A67: Finance Lease Receivables - Long-Term | F67: 685858000 | G67: 452834000
A68: Receivables - Other - Net - Long-Term | B68: 26524000 | C68: 323304000 | D68: 326587000 | E68: 296167000 | F68: 416058000 | G68: 102551000
A69: Provision - Doubtful Accounts - Long-Term
A70: Derivative Financial Instruments - Hedging - Long-Term | D70: 286484000 | E70: 157051000 | F70: 273499000 | G70: 266109000
A71: Property, Plant & Equipment - Net - Total | B71: 28208085000 | C71: 39802265000 | D71: 43374481000 | E71: 45743956000 | F71: 53256586000 | G71: 53906900000
A72: Assets Leased Out under Operating Lease - Net
A73: Property, Plant & Equipment - excluding Assets Leased Out - Net - Total | B73: 28208085000 | C73: 39802265000 | D73: 43374481000 | E73: 45743956000 | F73: 53256586000 | G73: 53906900000
A74: Land & Buildings - Net | B74: 20106446000 | C74: 28745202000 | D74: 29522908000 | E74: 30407322000 | F74: 35007835000 | G74: 35515238000
A75: Land/Improvements - Net | B75: 9596000 | C75: 15706000 | D75: 16156000 | E75: 14953000 | F75: 132186000 | G75: 202142000
A76: Buildings - Net | B76: 20096850000 | C76: 28729496000 | D76: 29506752000 | E76: 30392369000 | F76: 34875649000 | G76: 35313096000
A77: Leasehold Improvements - Net
A78: Plant, Machinery & Equipment - Net | B78: 1855939000 | C78: 3059663000 | D78: 6474261000 | E78: 8454649000 | F78: 10979962000 | G78: 11415862000
A79: Transportation Equipment - Net | B79: 10566000 | C79: 13790000 | D79: 36049000 | E79: 37060000 | F79: 38327000 | G79: 33989000
A80: Computer Software & Equipment - Net
A81: Construction in Progress - Net | B81: 849501000 | C81: 1168989000 | D81: 1104049000 | E81: 1618619000 | F81: 1546908000 | G81: 1455515000
A82: Property, Plant & Equipment - Under Capital Lease - Net | F82: 21927000 | G82: 17242000
A83: Right of Use Tangible Assets - Total - Net | B83: 5264096000 | C83: 6676348000 | D83: 6113351000 | E83: 5121186000 | F83: 5567137000 | G83: 5371315000
A84: Right of Use Tangible Assets - Operating Lease - Net
A85: Right of Use Tangible Assets - Capital/Finance Lease - Net | B85: 5264096000 | C85: 6676348000 | D85: 6113351000 | E85: 5121186000 | F85: 5567137000 | G85: 5371315000
A86: Property, Plant & Equipment - Other - Net | B86: 132103000 | C86: 152063000 | D86: 159912000 | E86: 142180000 | F86: 132817000 | G86: 131728000
A87: Natural Resources/Biological Assets - Net
A88: Mining/Exploration Specific Assets - Net
A89: Utility Plant - Net
A90: Property, Plant & Equipment - Gross - Total | B90: 34253612000 | C90: 49284395000 | D90: 53913677000 | E90: 57377186000 | F90: 72855517000 | G90: 75918546000
A91: Assets Leased Out under Operating Lease - Gross
A92: Property, Plant & Equipment - excluding Assets Leased Out - Gross | B92: 34253612000 | C92: 49284395000 | D92: 53913677000 | E92: 57377186000 | F92: 72855517000 | G92: 75918546000
A93: Land & Buildings - Gross | B93: 25612484000 | C93: 36921838000 | D93: 38327559000 | E93: 39800852000 | F93: 45660307000 | G93: 46940363000
A94: Land/Improvements - Gross | B94: 9596000 | C94: 15706000 | D94: 16156000 | E94: 14953000 | F94: 132186000 | G94: 202142000
A95: Buildings - Gross | B95: 25602888000 | C95: 36906132000 | D95: 38311403000 | E95: 39785899000 | F95: 45528121000 | G95: 46738221000
A96: Leasehold Improvements - Gross
A97: Plant, Machinery & Equipment - Gross | B97: 2226051000 | C97: 4086137000 | D97: 7866586000 | E97: 10281033000 | F97: 13759442000 | G97: 14831155000
A98: Transportation Equipment - Gross | B98: 24196000 | C98: 33044000 | D98: 59259000 | E98: 67287000 | F98: 86251000 | G98: 86771000
A99: Computer Software & Equipment - Gross
A100: Construction in Progress - Gross | B100: 849501000 | C100: 1168989000 | D100: 1104049000 | E100: 1618619000 | F100: 1546908000 | G100: 1455515000
...

Sheet WIFI Rev-COGS Detail
A1: WIFI | Detailed Revenue & Cost-of-Revenue Schedule
A2: In Thousands of Rupiah (IDR '000).
D3: 2021A | E3: 2022A | F3: 2023A | G3: 2024A | H3: 2025A | I3: 2026F | J3: 2027F | K3: 2028F | L3: 2029F | M3: 2030F
A5: A. REVENUE BUILD
A6: Forward growth / driver assumptions (YoY %)
A8: Bandwidth growth (YoY) | I8: 0.3 | J8: 0.22 | K8: 0.16 | L8: 0.11 | M8: 0.08
A9: Sewa core growth (YoY) | I9: 0 | J9: 0 | K9: 0 | L9: 0 | M9: 0
A10: Colocation growth (YoY) | I10: 0.05 | J10: 0.05 | K10: 0.05 | L10: 0.05 | M10: 0.05
A11: Lainnya growth (YoY) | I11: 0 | J11: 0 | K11: 0 | L11: 0 | M11: 0
A12: Advertising growth (YoY) | I12: 0.3 | J12: 0.25 | K12: 0.2 | L12: 0.15 | M12: 0.12
A13: Discount (% of gross revenue) | I13: 0.0056 | J13: 0.0056 | K13: 0.0056 | L13: 0.0056 | M13: 0.0056
A15: Telecommunication:
A16: Bandwidth | G16: 2.2719523e+08 | H16: 5.6085059e+08 | I16: =H16*(1+I8) | J16: =I16*(1+J8) | K16: =J16*(1+K8) | L16: =K16*(1+L8) | M16: =L16*(1+M8)
A17: Fiber to the home (FTTH) | G17: 0 | H17: 5.4105591e+08 | I17: ='WIFI 3-Statement Model'!I142 | J17: ='WIFI 3-Statement Model'!J142 | K17: ='WIFI 3-Statement Model'!K142 | L17: ='WIFI 3-Statement Model'!L142 | M17: ='WIFI 3-Statement Model'!M142
A18: FWA / wireless (IRA) [new segment - not in audited] | G18: 0 | H18: 0 | I18: ='WIFI 3-Statement Model'!I148 | J18: ='WIFI 3-Statement Model'!J148 | K18: ='WIFI 3-Statement Model'!K148 | L18: ='WIFI 3-Statement Model'!L148 | M18: ='WIFI 3-Statement Model'!M148
A19: Sewa core (Core lease) | G19: 1.0190335e+08 | H19: 96420659 | I19: =H19*(1+I9) | J19: =I19*(1+J9) | K19: =J19*(1+K9) | L19: =K19*(1+L9) | M19: =L19*(1+M9)
A20: Colocation | G20: 2363155.5 | H20: 2558194.8 | I20: =H20*(1+I10) | J20: =I20*(1+J10) | K20: =J20*(1+K10) | L20: =K20*(1+L10) | M20: =L20*(1+M10)
A21: Lainnya (Others) | G21: 8559825 | H21: 8331694.5 | I21: =H21*(1+I11) | J21: =I21*(1+J11) | K21: =J21*(1+K11) | L21: =K21*(1+L11) | M21: =L21*(1+M11)
A22: Telecom sub-total | D22: =290197011.74 | E22: =37573231.215+234525318.143 | F22: =122457112.56+57460084.82 | G22: =SUM(G16:G21) | H22: =SUM(H16:H21) | I22: =SUM(I16:I21) | J22: =SUM(J16:J21) | K22: =SUM(K16:K21) | L22: =SUM(L16:L21) | M22: =SUM(M16:M21)
A23: Advertising (Periklanan) | D23: =114182189.709 | E23: =189213101.126 | F23: =260164112.56 | G23: 3.3690897e+08 | H23: 4.5946609e+08 | I23: =H23*(1+I12) | J23: =I23*(1+J12) | K23: =J23*(1+K12) | L23: =K23*(1+L12) | M23: =L23*(1+M12)
A24: GROSS REVENUE (sub-total) | G24: =G22+G23 | H24: =H22+H23 | I24: =I22+I23 | J24: =J22+J23 | K24: =K22+K23 | L24: =L22+L23 | M24: =M22+M23 | Q24: =5679800+89320
A25: Less: Discount (Potongan harga) | G25: -5076527 | H25: -9287068.7 | I25: =-I24*I13 | J25: =-J24*J13 | K25: =-K24*K13 | L25: =-L24*L13 | M25: =-M24*M13 | Q25: =8967700+171600
A26: NET REVENUE (-> 3-Statement row 28) | G26: =G24+G25 | H26: =H24+H25 | I26: =I24+I25 | J26: =J24+J25 | K26: =K24+K25 | L26: =L24+L25 | M26: =M24+M25
Q27: =4004000+1596000
A28: B. COST OF REVENUE BUILD | Q28: =6900000+2300000
A29: Advertising direct cash cost (% of ad revenue) | D29: =D36/D23 | E29: =E36/E23 | F29: =F36/F23 | G29: =-G36/G23 | H29: =-H36/H23 | I29: =AVERAGE(D29:H29) | J29: =I29 | K29: =J29 | L29: =K29 | M29: =L29
A30: Telecom direct cash cost (% of telecom revenue) | E30: =E40/E22 | F30: =F40/F22 | G30: =-G40/G22 | H30: =-H40/H22 | I30: =AVERAGE(E30:H30) | J30: =$I$30 | K30: =$I$30 | L30: =$I$30 | M30: =$I$30
A31: Depreciation allocated to Advertising (% of total D&A) | I31: 0.675 | J31: 0.675 | K31: 0.675 | L31: 0.675 | M31: 0.675
A33: Advertising cost of revenue:
A34: Direct cash costs | G34: -77534817 | H34: -84348051 | I34: =-I23*I29 | J34: =-J23*J29 | K34: =-K23*K29 | L34: =-L23*L29 | M34: =-M23*M29
A35: Depreciation (Note 10, allocated) | G35: -1.0342626e+08 | H35: -1.2123325e+08 | I35: =-'WIFI 3-Statement Model'!I36*I31 | J35: =-'WIFI 3-Statement Model'!J36*J31 | K35: =-'WIFI 3-Statement Model'!K36*K31 | L35: =-'WIFI 3-Statement Model'!L36*L31 | M35: =-'WIFI 3-Statement Model'!M36*M31
A36: Advertising COGS sub-total | D36: =47528702.37 | E36: =89995932.65 | F36: =140896788.552 | G36: =G34+G35 | H36: =H34+H35 | I36: =I34+I35 | J36: =J34+J35 | K36: =K34+K35 | L36: =L34+L35 | M36: =M34+M35
A37: Telecommunication cost of revenue:
A38: Direct cash costs | G38: -51099812 | H38: -2.6895443e+08 | I38: =-I22*I30 | J38: =-J22*J30 | K38: =-K22*K30 | L38: =-L22*L30 | M38: =-M22*M30
A39: Depreciation (Note 10, allocated) | G39: -25019800 | H39: -58225379 | I39: =-'WIFI 3-Statement Model'!I36*(1-I31) | J39: =-'WIFI 3-Statement Model'!J36*(1-J31) | K39: =-'WIFI 3-Statement Model'!K36*(1-K31) | L39: =-'WIFI 3-Statement Model'!L36*(1-L31) | M39: =-'WIFI 3-Statement Model'!M36*(1-M31)
A40: Telecom COGS sub-total | E40: 29290883 | F40: =71085873.331 | G40: =G38+G39 | H40: =H38+H39 | I40: =I38+I39 | J40: =J38+J39 | K40: =K38+K39 | L40: =L38+L39 | M40: =M38+M39
A41: TOTAL COST OF REVENUE | G41: =G36+G40 | H41: =H36+H40 | I41: =I36+I40 | J41: =J36+J40 | K41: =K36+K40 | L41: =L36+L40 | M41: =M36+M40
A43: GROSS PROFIT | G43: =G26+G41 | H43: =H26+H41 | I43: =I26+I41 | J43: =J26+J41 | K43: =K26+K41 | L43: =L26+L41 | M43: =M26+M41
A44: Gross margin % | G44: =G43/G26 | H44: =H43/H26 | I44: =I43/I26 | J44: =J43/J26 | K44: =K43/K26 | L44: =L43/L26 | M44: =M43/M26
A46: Memo — gross margin by segment (check vs audited):
A47: Advertising GM % | G47: =(G23+G36)/G23 | H47: =(H23+H36)/H23 | I47: =(I23+I36)/I23 | J47: =(J23+J36)/J23 | K47: =(K23+K36)/K23 | L47: =(L23+L36)/L23 | M47: =(M23+M36)/M23
A48: Telecom GM % | G48: =(G22+G40)/G22 | H48: =(H22+H40)/H22 | I48: =(I22+I40)/I22 | J48: =(J22+J40)/J22 | K48: =(K22+K40)/K22 | L48: =(L22+L40)/L22 | M48: =(M22+M40)/M22

Sheet WIFI VALUATION
A1: WIFI | Valuation
C2: 2026 | D2: =C2+1 | E2: =D2+1 | F2: =E2+1 | G2: =F2+1
A4: Assumptions
A5: Tax Rate | C5: =22%
A6: Discount Rate | C6: ='WIFI WACC'!D9
A7: Terminal Growth Rate (Inflation Rate) | C7: 0.01
A8: EV/EBITDA Multiple
A10: Discounted Cashflow | C10: 2026 | D10: =C10+1 | E10: =D10+1 | F10: =E10+1 | G10: =F10+1 | H10: Terminal Value
C11: 1 | D11: 2 | E11: 3 | F11: 4 | G11: 5 | H11: 5
A12: EBIT | C12: ='WIFI 3-Statement Model'!I34 | D12: ='WIFI 3-Statement Model'!J34 | E12: ='WIFI 3-Statement Model'!K34 | F12: ='WIFI 3-Statement Model'!L34 | G12: ='WIFI 3-Statement Model'!M34
A13: Tax Rate | C13: 0.22 | D13: 0.22 | E13: 0.22 | F13: 0.22 | G13: 0.22
A14: NOPAT | C14: =C12*(1-C13) | D14: =D12*(1-D13) | E14: =E12*(1-E13) | F14: =F12*(1-F13) | G14: =G12*(1-G13)
A15: Add : Depreciation and Amortization | C15: ='WIFI 3-Statement Model'!I36 | D15: ='WIFI 3-Statement Model'!J36 | E15: ='WIFI 3-Statement Model'!K36 | F15: ='WIFI 3-Statement Model'!L36 | G15: ='WIFI 3-Statement Model'!M36
A16: Less : Capex | C16: =-'WIFI 3-Statement Model'!I108 | D16: =-'WIFI 3-Statement Model'!J108 | E16: =-'WIFI 3-Statement Model'!K108 | F16: =-'WIFI 3-Statement Model'!L108 | G16: =-'WIFI 3-Statement Model'!M108
A17: Less : Changes in NWC | C17: ='WIFI 3-Statement Model'!I87 | D17: ='WIFI 3-Statement Model'!J87 | E17: ='WIFI 3-Statement Model'!K87 | F17: ='WIFI 3-Statement Model'!L87 | G17: ='WIFI 3-Statement Model'!M87
A18: Free Cashflow to Firm (FCFF) | C18: =SUM(C14:C17) | D18: =SUM(D14:D17) | E18: =SUM(E14:E17) | F18: =SUM(F14:F17) | G18: =SUM(G14:G17) | H18: =G18*(1+C7)/(C6-C7)
A20: PV of FCFF | C20: =C18/((1+$C$6)^C11) | D20: =D18/((1+$C$6)^D11) | E20: =E18/((1+$C$6)^E11) | F20: =F18/((1+$C$6)^F11) | G20: =G18/((1+$C$6)^G11) | H20: =H18/((1+$C$6)^H11)
A22: Enterprise Value | H22: =SUM(C20:H20)
A23: Less : Debt | H23: ='WIFI 3-Statement Model'!H66+'WIFI 3-Statement Model'!H71
A24: Less: Minority Interest | H24: ='SOURCE WIFI Balance Sheet (2)'!F268
A25: Add : Cash | H25: ='WIFI 3-Statement Model'!H51
A26: Equity Value | H26: =H22-H23+H25-H24
A27: Shares Outstanding | H27: 5308549015
A28: Share Price | H28: =H26/H27*1000
A29: Current Price 21 Agt (Rp) | H29: 2090
A30: Upside | H30: =H28/H29-1
A32: Terminal value – steady-state normalization
A33: Terminal NOPAT (2030F) | H33: =G14
A34: Add: D&A (2030F) | H34: =G15
A35: Less: maintenance capex (= D&A in steady state) | H35: =-G15
A36: Less: normalized change in NWC (= g x NWC) | H36: =-$C$7*'WIFI 3-Statement Model'!M119
A37: Normalized terminal FCFF | H37: =SUM(H33:H36)
A40: MINORITY INTEREST CALCULATION (NTT's 49% of FTTH sub 'IJE')
A41: Method A – value the FTTH business, take NTT's 49% share
A42: FTTH revenue (FY2026F) | H42: ='WIFI 3-Statement Model'!I142
A43: FTTH EBITDA margin | H43: 0.55
A44: FTTH EBITDA | H44: =H42*H43
A45: EV/EBITDA multiple (fibre peers) | H45: 8
A46: FTTH enterprise value | H46: =H44*H45
A47: less: FTTH net debt (approx; group near net-cash) | H47: 0
A48: FTTH equity value | H48: =H46-H47
A49: NTT ownership stake | H49: 0.49
A50: minority interest | H50: =H49*H48

Sheet WIFI BLENDED
A1: WIFI | Blended Valuation
A3: A. METHOD SUMMARY
A4: Valuation method | B4: Target price (Rp) | C4: Weight | D4: Weighted (Rp)
A5: DCF (normalized terminal value) | B5: ='WIFI VALUATION'!H28 | C5: 0.5 | D5: =B5*C5
A6: Sum-of-the-Parts (SOTP) | B6: ='WIFI SOTP'!F24 | C6: 0.3 | D6: =B6*C6
A7: Relative – EV/EBITDA peers | B7: ='TOWR WIFI-Comparable Preced (2)'!E54 | C7: 0.15 | D7: =B7*C7
A8: Precedent Transactions | B8: ='TOWR WIFI-Comparable Preced (2)'!O33 | C8: 0.05 | D8: =B8*C8
A9: Total / Blended target price | C9: =SUM(C5:C8) | D9: =SUM(D5:D8)
A10: (weights must sum to 100%)
A12: B. VS MARKET
A13: Blended target price (Rp) | B13: =D9
A14: Current price (Rp) | B14: ='WIFI VALUATION'!H29
A15: Upside / (downside) | B15: =B13/B14-1
A16: Recommendation | B16: =IF(B15>0.1,"BUY",IF(B15<-0.1,"SELL","HOLD"))
A18: C. METHOD RANGE (triangulation)
A19: Highest method | B19: =MAX(B5:B7)
A20: Lowest method | B20: =MIN(B5:B7)
A21: Simple average (unweighted) | B21: =AVERAGE(B5:B7)
A22: Blended (weighted) | B22: =D9
A24: Memo – other relative anchors (reference, not weighted):
A25: Relative – P/BV peers (Rp) | B25: ='TOWR WIFI-Comparable Preced (2)'!F54
A26: Relative – P/E peers (Rp) | B26: ='TOWR WIFI-Comparable Preced (2)'!G54

Sheet BETA TOWR
B1: IHSG | C1: TOWR | D1: IHSG | E1: TOWR | G1: IHSG | H1: TOWR
A2: Tanggal | B2: Price | D2: Return | F2: Risk Free Return | G2: Excess Daily Return | K2: Risk Free Rate | L2: 0.0696
A3: 08/21/2026 | B3: 6525.69 | C3: 434 | D3: =B3/B4-1 | E3: =C3/C4-1 | F3: =$L$2/365 | G3: =D3-F3 | H3: =E3-F3 | K3: Beta | L3: =L24
A4: 08/20/2026 | B4: 6501.58 | C4: 428 | D4: =B4/B5-1 | E4: =C4/C5-1 | F4: =$L$2/365 | G4: =D4-F4 | H4: =E4-F4
A5: 08/19/2026 | B5: 6394.13 | C5: 422 | D5: =B5/B6-1 | E5: =C5/C6-1 | F5: =$L$2/365 | G5: =D5-F5 | H5: =E5-F5
A6: 08/18/2026 | B6: 6449.83 | C6: 422 | D6: =B6/B7-1 | E6: =C6/C7-1 | F6: =$L$2/365 | G6: =D6-F6 | H6: =E6-F6
A7: 08/14/2026 | B7: 6401.89 | C7: 390 | D7: =B7/B8-1 | E7: =C7/C8-1 | F7: =$L$2/365 | G7: =D7-F7 | H7: =E7-F7 | K7: SUMMARY OUTPUT
A8: 08/13/2026 | B8: 6301.77 | C8: 388 | D8: =B8/B9-1 | E8: =C8/C9-1 | F8: =$L$2/365 | G8: =D8-F8 | H8: =E8-F8
A9: 08/12/2026 | B9: 6373.85 | C9: 392 | D9: =B9/B10-1 | E9: =C9/C10-1 | F9: =$L$2/365 | G9: =D9-F9 | H9: =E9-F9 | K9: Regression Statistics
A10: 08/11/2026 | B10: 6267.88 | C10: 390 | D10: =B10/B11-1 | E10: =C10/C11-1 | F10: =$L$2/365 | G10: =D10-F10 | H10: =E10-F10 | K10: Multiple R | L10: 0.42906698
A11: 08/10/2026 | B11: 6365.37 | C11: 394 | D11: =B11/B12-1 | E11: =C11/C12-1 | F11: =$L$2/365 | G11: =D11-F11 | H11: =E11-F11 | K11: R Square | L11: 0.18409848
A12: 08/07/2026 | B12: 6409.65 | C12: 404 | D12: =B12/B13-1 | E12: =C12/C13-1 | F12: =$L$2/365 | G12: =D12-F12 | H12: =E12-F12 | K12: Adjusted R Square | L12: 0.18341685
A13: 08/06/2026 | B13: 6343.71 | C13: 400 | D13: =B13/B14-1 | E13: =C13/C14-1 | F13: =$L$2/365 | G13: =D13-F13 | H13: =E13-F13 | K13: Standard Error | L13: 0.020153515
A14: 08/05/2026 | B14: 6351.14 | C14: 406 | D14: =B14/B15-1 | E14: =C14/C15-1 | F14: =$L$2/365 | G14: =D14-F14 | H14: =E14-F14 | K14: Observations | L14: 1199
A15: 08/04/2026 | B15: 6319.61 | C15: 410 | D15: =B15/B16-1 | E15: =C15/C16-1 | F15: =$L$2/365 | G15: =D15-F15 | H15: =E15-F15
A16: 08/03/2026 | B16: 6234.5 | C16: 400 | D16: =B16/B17-1 | E16: =C16/C17-1 | F16: =$L$2/365 | G16: =D16-F16 | H16: =E16-F16 | K16: ANOVA
A17: 07/31/2026 | B17: 6236.13 | C17: 404 | D17: =B17/B18-1 | E17: =C17/C18-1 | F17: =$L$2/365 | G17: =D17-F17 | H17: =E17-F17 | L17: df | M17: SS | N17: MS | O17: F | P17: Significance F
A18: 07/30/2026 | B18: 6186.36 | C18: 404 | D18: =B18/B19-1 | E18: =C18/C19-1 | F18: =$L$2/365 | G18: =D18-F18 | H18: =E18-F18 | K18: Regression | L18: 1 | M18: 0.1097004 | N18: 0.1097004 | O18: 270.08882 | P18: 6.9803346e-55
A19: 07/29/2026 | B19: 6091.39 | C19: 404 | D19: =B19/B20-1 | E19: =C19/C20-1 | F19: =$L$2/365 | G19: =D19-F19 | H19: =E19-F19 | K19: Residual | L19: 1197 | M19: 0.4861785 | N19: 0.00040616416
A20: 07/28/2026 | B20: 6130.59 | C20: 402 | D20: =B20/B21-1 | E20: =C20/C21-1 | F20: =$L$2/365 | G20: =D20-F20 | H20: =E20-F20 | K20: Total | L20: 1198 | M20: 0.59587889
A21: 07/27/2026 | B21: 6185.78 | C21: 406 | D21: =B21/B22-1 | E21: =C21/C22-1 | F21: =$L$2/365 | G21: =D21-F21 | H21: =E21-F21
A22: 07/24/2026 | B22: 6196.43 | C22: 402 | D22: =B22/B23-1 | E22: =C22/C23-1 | F22: =$L$2/365 | G22: =D22-F22 | H22: =E22-F22 | L22: Coefficients | M22: Standard Error | N22: t Stat | O22: P-value | P22: Lower 95% | Q22: Upper 95% | R22: Lower 95,0% | S22: Upper 95,0%
A23: 07/23/2026 | B23: 6315.31 | C23: 414 | D23: =B23/B24-1 | E23: =C23/C24-1 | F23: =$L$2/365 | G23: =D23-F23 | H23: =E23-F23 | K23: Intercept | L23: -0.00081626709 | M23: 0.00058204079 | N23: -1.4024225 | O23: 0.16104841 | P23: -0.0019582007 | Q23: 0.00032566656 | R23: -0.0019582007 | S23: 0.00032566656
A24: 07/22/2026 | B24: 6334.48 | C24: 412 | D24: =B24/B25-1 | E24: =C24/C25-1 | F24: =$L$2/365 | G24: =D24-F24 | H24: =E24-F24 | K24: X Variable 1 | L24: 0.90350907 | M24: 0.05497677 | N24: 16.434379 | O24: 6.9803346e-55 | P24: 0.79564752 | Q24: 1.0113706 | R24: 0.79564752 | S24: 1.0113706
A25: 07/21/2026 | B25: 6340.02 | C25: 412 | D25: =B25/B26-1 | E25: =C25/C26-1 | F25: =$L$2/365 | G25: =D25-F25 | H25: =E25-F25
A26: 07/20/2026 | B26: 6231.78 | C26: 408 | D26: =B26/B27-1 | E26: =C26/C27-1 | F26: =$L$2/365 | G26: =D26-F26 | H26: =E26-F26
A27: 07/17/2026 | B27: 6175.54 | C27: 410 | D27: =B27/B28-1 | E27: =C27/C28-1 | F27: =$L$2/365 | G27: =D27-F27 | H27: =E27-F27
A28: 07/16/2026 | B28: 6108.21 | C28: 390 | D28: =B28/B29-1 | E28: =C28/C29-1 | F28: =$L$2/365 | G28: =D28-F28 | H28: =E28-F28
A29: 07/15/2026 | B29: 6041.97 | C29: 378 | D29: =B29/B30-1 | E29: =C29/C30-1 | F29: =$L$2/365 | G29: =D29-F29 | H29: =E29-F29
A30: 07/14/2026 | B30: 6039.52 | C30: 378 | D30: =B30/B31-1 | E30: =C30/C31-1 | F30: =$L$2/365 | G30: =D30-F30 | H30: =E30-F30
A31: 07/13/2026 | B31: 6037.84 | C31: 374 | D31: =B31/B32-1 | E31: =C31/C32-1 | F31: =$L$2/365 | G31: =D31-F31 | H31: =E31-F31
A32: 07/10/2026 | B32: 5924.36 | C32: 372 | D32: =B32/B33-1 | E32: =C32/C33-1 | F32: =$L$2/365 | G32: =D32-F32 | H32: =E32-F32
A33: 07/09/2026 | B33: 5912.44 | C33: 368 | D33: =B33/B34-1 | E33: =C33/C34-1 | F33: =$L$2/365 | G33: =D33-F33 | H33: =E33-F33
A34: 07/08/2026 | B34: 5873.37 | C34: 370 | D34: =B34/B35-1 | E34: =C34/C35-1 | F34: =$L$2/365 | G34: =D34-F34 | H34: =E34-F34
A35: 07/07/2026 | B35: 5986.5 | C35: 374 | D35: =B35/B36-1 | E35: =C35/C36-1 | F35: =$L$2/365 | G35: =D35-F35 | H35: =E35-F35
A36: 07/06/2026 | B36: 5916.07 | C36: 372 | D36: =B36/B37-1 | E36: =C36/C37-1 | F36: =$L$2/365 | G36: =D36-F36 | H36: =E36-F36
... A621: 01/05/2024 | B621: 7350.62 | C621: 995 | D621: =B621/B622-1 | E621: =C621/C622-1 | F621: =$L$2/365 | G621: =D621-F621 | H621: =E621-F621
A622: 01/04/2024 | B622: 7359.76 | C622: 1020 | D622: =B622/B623-1 | E622: =C622/C623-1 | F622: =$L$2/365 | G622: =D622-F622 | H622: =E622-F622
A623: 01/03/2024 | B623: 7279.09 | C623: 1015 | D623: =B623/B624-1 | E623: =C623/C624-1 | F623: =$L$2/365 | G623: =D623-F623 | H623: =E623-F623
A624: 01/02/2024 | B624: 7323.59 | C624: 1010 | D624: =B624/B625-1 | E624: =C624/C625-1 | F624: =$L$2/365 | G624: =D624-F624 | H624: =E624-F624
A625: 12/29/2023 | B625: 7272.8 | C625: 990 | D625: =B625/B626-1 | E625: =C625/C626-1 | F625: =$L$2/365 | G625: =D625-F625 | H625: =E625-F625
A626: 12/28/2023 | B626: 7303.89 | C626: 970 | D626: =B626/B627-1 | E626: =C626/C627-1 | F626: =$L$2/365 | G626: =D626-F626 | H626: =E626-F626
A627: 12/27/2023 | B627: 7245.92 | C627: 965 | D627: =B627/B628-1 | E627: =C627/C628-1 | F627: =$L$2/365 | G627: =D627-F627 | H627: =E627-F627
A628: 12/22/2023 | B628: 7237.52 | C628: 965 | D628: =B628/B629-1 | E628: =C628/C629-1 | F628: =$L$2/365 | G628: =D628-F628 | H628: =E628-F628
A629: 12/21/2023 | B629: 7209.62 | C629: 955 | D629: =B629/B630-1 | E629: =C629/C630-1 | F629: =$L$2/365 | G629: =D629-F629 | H629: =E629-F629
A630: 12/20/2023 | B630: 7219.67 | C630: 980 | D630: =B630/B631-1 | E630: =C630/C631-1 | F630: =$L$2/365 | G630: =D630-F630 | H630: =E630-F630
A631: 12/19/2023 | B631: 7187.85 | C631: 970 | D631: =B631/B632-1 | E631: =C631/C632-1 | F631: =$L$2/365 | G631: =D631-F631 | H631: =E631-F631
A632: 12/18/2023 | B632: 7119.52 | C632: 955 | D632: =B632/B633-1 | E632: =C632/C633-1 | F632: =$L$2/365 | G632: =D632-F632 | H632: =E632-F632
A633: 12/15/2023 | B633: 7190.99 | C633: 1000 | D633: =B633/B634-1 | E633: =C633/C634-1 | F633: =$L$2/365 | G633: =D633-F633 | H633: =E633-F633
A634: 12/14/2023 | B634: 7176.02 | C634: 1000 | D634: =B634/B635-1 | E634: =C634/C635-1 | F634: =$L$2/365 | G634: =D634-F634 | H634: =E634-F634
A635: 12/13/2023 | B635: 7075.34 | C635: 990 | D635: =B635/B636-1 | E635: =C635/C636-1 | F635: =$L$2/365 | G635: =D635-F635 | H635: =E635-F635
A636: 12/12/2023 | B636: 7125.31 | C636: 965 | D636: =B636/B637-1 | E636: =C636/C637-1 | F636: =$L$2/365 | G636: =D636-F636 | H636: =E636-F636
A637: 12/11/2023 | B637: 7088.79 | C637: 940 | D637: =B637/B638-1 | E637: =C637/C638-1 | F637: =$L$2/365 | G637: =D637-F637 | H637: =E637-F637
A638: 12/08/2023 | B638: 7159.6 | C638: 905 | D638: =B638/B639-1 | E638: =C638/C639-1 | F638: =$L$2/365 | G638: =D638-F638 | H638: =E638-F638
A639: 12/07/2023 | B639: 7134.62 | C639: 905 | D639: =B639/B640-1 | E639: =C639/C640-1 | F639: =$L$2/365 | G639: =D639-F639 | H639: =E639-F639
A640: 12/06/2023 | B640: 7087.4 | C640: 950 | D640: =B640/B641-1 | E640: =C640/C641-1 | F640: =$L$2/365 | G640: =D640-F640 | H640: =E640-F640
A641: 12/05/2023 | B641: 7100.85 | C641: 980 | D641: =B641/B642-1 | E641: =C641/C642-1 | F641: =$L$2/365 | G641: =D641-F641 | H641: =E641-F641
A642: 12/04/2023 | B642: 7093.6 | C642: 965 | D642: =B642/B643-1 | E642: =C642/C643-1 | F642: =$L$2/365 | G642: =D642-F642 | H642: =E642-F642
A643: 12/01/2023 | B643: 7059.91 | C643: 940 | D643: =B643/B644-1 | E643: =C643/C644-1 | F643: =$L$2/365 | G643: =D643-F643 | H643: =E643-F643
A644: 11/30/2023 | B644: 7080.74 | C644: 1000 | D644: =B644/B645-1 | E644: =C644/C645-1 | F644: =$L$2/365 | G644: =D644-F644 | H644: =E644-F644
A645: 11/29/2023 | B645: 7036.09 | C645: 990 | D645: =B645/B646-1 | E645: =C645/C646-1 | F645: =$L$2/365 | G645: =D645-F645 | H645: =E645-F645
A646: 11/28/2023 | B646: 7041.07 | C646: 990 | D646: =B646/B647-1 | E646: =C646/C647-1 | F646: =$L$2/365 | G646: =D646-F646 | H646: =E646-F646
A647: 11/27/2023 | B647: 7013.41 | C647: 970 | D647: =B647/B648-1 | E647: =C647/C648-1 | F647: =$L$2/365 | G647: =D647-F647 | H647: =E647-F647
A648: 11/24/2023 | B648: 7009.63 | C648: 975 | D648: =B648/B649-1 | E648: =C648/C649-1 | F648: =$L$2/365 | G648: =D648-F648 | H648: =E648-F648
A649: 11/23/2023 | B649: 7004.34 | C649: 970 | D649: =B649/B650-1 | E649: =C649/C650-1 | F649: =$L$2/365 | G649: =D649-F649 | H649: =E649-F649
A650: 11/22/2023 | B650: 6906.95 | C650: 980 | D650: =B650/B651-1 | E650: =C650/C651-1 | F650: =$L$2/365 | G650: =D650-F650 | H650: =E650-F650
A651: 11/21/2023 | B651: 6961.79 | C651: 990 | D651: =B651/B652-1 | E651: =C651/C652-1 | F651: =$L$2/365 | G651: =D651-F651 | H651: =E651-F651
A652: 11/20/2023 | B652: 6994.89 | C652: 980 | D652: =B652/B653-1 | E652: =C652/C653-1 | F652: =$L$2/365 | G652: =D652-F652 | H652: =E652-F652
A653: 11/17/2023 | B653: 6977.67 | C653: 980 | D653: =B653/B654-1 | E653: =C653/C654-1 | F653: =$L$2/365 | G653: =D653-F653 | H653: =E653-F653
A654: 11/16/2023 | B654: 6958.01 | C654: 960 | D654: =B654/B655-1 | E654: =C654/C655-1 | F654: =$L$2/365 | G654: =D654-F654 | H654: =E654-F654
A655: 11/15/2023 | B655: 6958.21 | C655: 960 | D655: =B655/B656-1 | E655: =C655/C656-1 | F655: =$L$2/365 | G655: =D655-F655 | H655: =E655-F655
A656: 11/14/2023 | B656: 6862.06 | C656: 930 | D656: =B656/B657-1 | E656: =C656/C657-1 | F656: =$L$2/365 | G656: =D656-F656 | H656: =E656-F656
... A693: 09/21/2023 | B693: 6991.47 | C693: 995 | D693: =B693/B694-1 | E693: =C693/C694-1 | F693: =$L$2/365 | G693: =D693-F693 | H693: =E693-F693
A694: 09/20/2023 | B694: 7011.68 | C694: 1000 | D694: =B694/B695-1 | E694: =C694/C695-1 | F694: =$L$2/365 | G694: =D694-F694 | H694: =E694-F694
A695: 09/19/2023 | B695: 6980.32 | C695: 1025 | D695: =B695/B696-1 | E695: =C695/C696-1 | F695: =$L$2/365 | G695: =D695-F695 | H695: =E695-F695
